Workbook

Sheet 01_Dashboard
A1: P2P / AUDIT COMMAND CENTER
A3: SOCIEDAD X, S.L. • DEMO SINTÉTICA • FY 2026 • v1.1.0
B5: PERIODO DE ANÁLISIS | D5: Todos | G5: El selector actualiza importes y volúmenes de cada mes. Las alertas son indicios, no conclusiones.
B7: PEDIDOS REGISTRADOS | G7: IMPORTE TOTAL POs | L7: FACTURAS REGISTRADAS
B8: =IF($D$5="Todos",SUM('11_Resumen_Mensual'!B6:B17),SUMIF('11_Resumen_Mensual'!$A$6:$A$17,$D$5,'11_Resumen_Mensual'!B$6:B$17)) | G8: =IF($D$5="Todos",SUM('11_Resumen_Mensual'!C6:C17),SUMIF('11_Resumen_Mensual'!$A$6:$A$17,$D$5,'11_Resumen_Mensual'!C$6:C$17)) | L8: =IF($D$5="Todos",SUM('11_Resumen_Mensual'!D6:D17),SUMIF('11_Resumen_Mensual'!$A$6:$A$17,$D$5,'11_Resumen_Mensual'!D$6:D$17))
B11: IMPORTE TOTAL FACTURAS | G11: EXCEPCIONES DETECTADAS | L11: EXCEPCIONES PRIORIDAD ALTA
B12: =IF($D$5="Todos",SUM('11_Resumen_Mensual'!E6:E17),SUMIF('11_Resumen_Mensual'!$A$6:$A$17,$D$5,'11_Resumen_Mensual'!E$6:E$17)) | G12: =IF($D$5="Todos",SUM('11_Resumen_Mensual'!F6:F17),SUMIF('11_Resumen_Mensual'!$A$6:$A$17,$D$5,'11_Resumen_Mensual'!F$6:F$17)) | L12: =IF($D$5="Todos",SUM('11_Resumen_Mensual'!G6:G17),SUMIF('11_Resumen_Mensual'!$A$6:$A$17,$D$5,'11_Resumen_Mensual'!G$6:G$17))
B15: ANÁLISIS MENSUAL | VOLUMEN OPERATIVO Y VALOR (€)
B17: Mes | C17: Nº POs | D17: Pedidos (€) | E17: Nº facturas | F17: Facturas (€) | G17: Alertas | H17: Altas
B18: ='11_Resumen_Mensual'!A6 | C18: ='11_Resumen_Mensual'!B6 | D18: ='11_Resumen_Mensual'!C6 | E18: ='11_Resumen_Mensual'!D6 | F18: ='11_Resumen_Mensual'!E6 | G18: ='11_Resumen_Mensual'!F6 | H18: ='11_Resumen_Mensual'!G6
B19: ='11_Resumen_Mensual'!A7 | C19: ='11_Resumen_Mensual'!B7 | D19: ='11_Resumen_Mensual'!C7 | E19: ='11_Resumen_Mensual'!D7 | F19: ='11_Resumen_Mensual'!E7 | G19: ='11_Resumen_Mensual'!F7 | H19: ='11_Resumen_Mensual'!G7
B20: ='11_Resumen_Mensual'!A8 | C20: ='11_Resumen_Mensual'!B8 | D20: ='11_Resumen_Mensual'!C8 | E20: ='11_Resumen_Mensual'!D8 | F20: ='11_Resumen_Mensual'!E8 | G20: ='11_Resumen_Mensual'!F8 | H20: ='11_Resumen_Mensual'!G8
B21: ='11_Resumen_Mensual'!A9 | C21: ='11_Resumen_Mensual'!B9 | D21: ='11_Resumen_Mensual'!C9 | E21: ='11_Resumen_Mensual'!D9 | F21: ='11_Resumen_Mensual'!E9 | G21: ='11_Resumen_Mensual'!F9 | H21: ='11_Resumen_Mensual'!G9
B22: ='11_Resumen_Mensual'!A10 | C22: ='11_Resumen_Mensual'!B10 | D22: ='11_Resumen_Mensual'!C10 | E22: ='11_Resumen_Mensual'!D10 | F22: ='11_Resumen_Mensual'!E10 | G22: ='11_Resumen_Mensual'!F10 | H22: ='11_Resumen_Mensual'!G10
B23: ='11_Resumen_Mensual'!A11 | C23: ='11_Resumen_Mensual'!B11 | D23: ='11_Resumen_Mensual'!C11 | E23: ='11_Resumen_Mensual'!D11 | F23: ='11_Resumen_Mensual'!E11 | G23: ='11_Resumen_Mensual'!F11 | H23: ='11_Resumen_Mensual'!G11
B24: ='11_Resumen_Mensual'!A12 | C24: ='11_Resumen_Mensual'!B12 | D24: ='11_Resumen_Mensual'!C12 | E24: ='11_Resumen_Mensual'!D12 | F24: ='11_Resumen_Mensual'!E12 | G24: ='11_Resumen_Mensual'!F12 | H24: ='11_Resumen_Mensual'!G12
B25: ='11_Resumen_Mensual'!A13 | C25: ='11_Resumen_Mensual'!B13 | D25: ='11_Resumen_Mensual'!C13 | E25: ='11_Resumen_Mensual'!D13 | F25: ='11_Resumen_Mensual'!E13 | G25: ='11_Resumen_Mensual'!F13 | H25: ='11_Resumen_Mensual'!G13
B26: ='11_Resumen_Mensual'!A14 | C26: ='11_Resumen_Mensual'!B14 | D26: ='11_Resumen_Mensual'!C14 | E26: ='11_Resumen_Mensual'!D14 | F26: ='11_Resumen_Mensual'!E14 | G26: ='11_Resumen_Mensual'!F14 | H26: ='11_Resumen_Mensual'!G14
B27: ='11_Resumen_Mensual'!A15 | C27: ='11_Resumen_Mensual'!B15 | D27: ='11_Resumen_Mensual'!C15 | E27: ='11_Resumen_Mensual'!D15 | F27: ='11_Resumen_Mensual'!E15 | G27: ='11_Resumen_Mensual'!F15 | H27: ='11_Resumen_Mensual'!G15
B28: ='11_Resumen_Mensual'!A16 | C28: ='11_Resumen_Mensual'!B16 | D28: ='11_Resumen_Mensual'!C16 | E28: ='11_Resumen_Mensual'!D16 | F28: ='11_Resumen_Mensual'!E16 | G28: ='11_Resumen_Mensual'!F16 | H28: ='11_Resumen_Mensual'!G16
B29: ='11_Resumen_Mensual'!A17 | C29: ='11_Resumen_Mensual'!B17 | D29: ='11_Resumen_Mensual'!C17 | E29: ='11_Resumen_Mensual'!D17 | F29: ='11_Resumen_Mensual'!E17 | G29: ='11_Resumen_Mensual'!F17 | H29: ='11_Resumen_Mensual'!G17
B32: LECTURA CORRECTA DEL DASHBOARD
B33: • Los totales de POs y facturas son series independientes y no representan cobertura monetaria.
B34: • Las excepciones de fecha se revisan, pero no prueban errores de corte contable.
B35: • El campo 'Pagado' procede de un export, no de confirmación bancaria ni de libro mayor.
B36: • Los números con signo negativo (abonos) se conservan en las sumas.
B37: • El historial de decisiones se registra en 05_Excepciones antes de volver a generar el fichero.

Sheet 02_Reconciliacion
A1: CONCILIACIÓN PEDIDOS ↔ FACTURAS
A3: Cruce 1:N por referencia PO en descripción; importes al total con IVA, no confundir con gasto devengado
A5: PO | B5: Fecha PO | C5: Proveedor | D5: Descripción | E5: Total PO € | F5: Nº facturas | G5: Facturado enlazado € | H5: Dif. PO - fact. € | I5: Facturado ERP € | J5: Resultado | K5: Aprobación PO | L5: Estado PO | M5: Facturas vinculadas | N5: Proyecto | O5: Estado proyecto | P5: Estado CECO | Q5: CECO identificado | R5: Fila origen
A6: O2690001 | B6: 19/07/2026 | C6: Proveedor Ficticio X 042, S.L. | D6: Asesoria operativa - operacion ficticia | E6: 27362.42 | F6: 2 | G6: 29765.03 | H6: -2402.61 | I6: 29765.03 | J6: SOBRE PEDIDO | K6: Aceptado | L6: Facturado | M6: FX26-000046, FX26-000382 | O6: NO INFORMADO | P6: NO INFORMADO | R6: 6
A7: O2690002 | B7: 17/04/2026 | C7: Proveedor Ficticio X 140, S.L. | D7: Servicios logisticos - operacion ficticia | E7: 7894.52 | F7: 0 | G7: 0 | H7: 7894.52 | I7: 0 | J7: SIN FACTURA LOCALIZADA | K7: Aceptado | L7: Pendiente | N7: XPR26-00164 | Proyecto demostracion 00164 | O7: VALIDO | P7: VALIDO | Q7: TECNOLOGIA_X214 | R7: 7
A8: O2690003 | B8: 07/09/2026 | C8: Proveedor Ficticio X 121, S.L. | D8: Servicios profesionales - operacion ficticia | E8: 9481.16 | F8: 0 | G8: 0 | H8: 9481.16 | I8: 0 | J8: SIN FACTURA LOCALIZADA | K8: Aceptado | L8: Pendiente | N8: XPR26-01546 | Proyecto demostracion 01546 | O8: VALIDO | P8: VALIDO | Q8: COMERCIAL_X080 | R8: 8
A9: O2690004 | B9: 25/03/2026 | C9: Proveedor Ficticio X 004, S.L. | D9: Produccion audiovisual - operacion ficticia | E9: 28118.25 | F9: 3 | G9: 28118.25 | H9: 0 | I9: 28118.25 | J9: CONCILIADO | K9: Aceptado | L9: Facturado | M9: FX26-001774, FX26-002004, FX26-002069 | N9: XPR26-00086 | Proyecto demostracion 00086 | O9: VALIDO | P9: VALIDO | Q9: TECNOLOGIA_X204 | R9: 9
A10: O2690005 | B10: 05/09/2026 | C10: Proveedor Ficticio X 121, S.L. | D10: Traduccion y localizacion - operacion ficticia | E10: 28298.46 | F10: 0 | G10: 0 | H10: 28298.46 | I10: 0 | J10: SIN FACTURA LOCALIZADA | K10: Aceptado | L10: Pendiente | N10: XPR26-03638 | Proyecto demostracion 03638 | O10: VALIDO | P10: VALIDO | Q10: CREATIVIDAD_X142 | R10: 10
A11: O2690006 | B11: 11/07/2026 | C11: Proveedor Ficticio X 151, S.L. | D11: Servicios profesionales - operacion ficticia | E11: 60605.65 | F11: 0 | G11: 0 | H11: 60605.65 | I11: 0 | J11: CANCELADO / SIN FACTURA | K11: Cancelado | L11: Pendiente | N11: XPR26-01049 | Proyecto demostracion 01049 | O11: VALIDO | P11: VALIDO | Q11: CREATIVIDAD_X232 | R11: 11
A12: O2690007 | B12: 10/08/2026 | C12: Proveedor Ficticio X 006, S.L. | D12: Mantenimiento informatico - operacion ficticia | E12: 20281.08 | F12: 0 | G12: 0 | H12: 20281.08 | I12: 0 | J12: SIN FACTURA LOCALIZADA | K12: Aceptado | L12: Pendiente | O12: NO INFORMADO | P12: VALIDO | Q12: PRODUCCION_X231 | R12: 12
A13: O2690008 | B13: 25/07/2026 | C13: Proveedor Ficticio X 079, S.L. | D13: Produccion audiovisual - operacion ficticia | E13: 14529.84 | F13: 0 | G13: 0 | H13: 14529.84 | I13: 0 | J13: SIN FACTURA LOCALIZADA | K13: Aceptado | L13: Pendiente | N13: XPR26-01278 | Proyecto demostracion 01278 | O13: VALIDO | P13: VALIDO | Q13: CREATIVIDAD_X252 | R13: 13
A14: O2690009 | B14: 29/07/2026 | C14: Proveedor Ficticio X 152, S.L. | D14: Traduccion y localizacion - operacion ficticia | E14: 312.25 | F14: 1 | G14: 312.25 | H14: 0 | I14: 312.25 | J14: CONCILIADO | K14: Aceptado | L14: Facturado | M14: FX26-001284 | O14: NO INFORMADO | P14: VALIDO | Q14: CONSULTORIA_X119 | R14: 14
A15: O2690010 | B15: 17/03/2026 | C15: Proveedor Ficticio X 032, S.L. | D15: Subcontratacion de proyectos - operacion ficticia | E15: 24527.05 | F15: 3 | G15: 24527.05 | H15: 0 | I15: 24527.05 | J15: CONCILIADO | K15: Pendiente | L15: Facturado | M15: FX26-000846, FX26-001068, FX26-001993 | N15: XPR26-02376 | Proyecto demostracion 02376 | O15: VALIDO | P15: VALIDO | Q15: ADMINISTRACION_X246 | R15: 15
A16: O2690011 | B16: 06/09/2026 | C16: Proveedor Ficticio X 138, S.L. | D16: Servicios profesionales - operacion ficticia | E16: 15799.79 | F16: 2 | G16: 15799.8 | H16: -0.01 | I16: 15799.8 | J16: CONCILIADO | K16: Aceptado | L16: Facturado | M16: FX26-000120, FX26-001875 | O16: NO INFORMADO | P16: VALIDO | Q16: FINANZAS_X247 | R16: 16
A17: O2690012 | B17: 24/07/2026 | C17: Proveedor Ficticio X 090, S.L. | D17: Subcontratacion de proyectos - operacion ficticia | E17: 5974.22 | F17: 0 | G17: 0 | H17: 5974.22 | I17: 0 | J17: SIN FACTURA LOCALIZADA | K17: Aceptado | L17: Pendiente | N17: XPR26-02296 | Proyecto demostracion 02296 | O17: VALIDO | P17: VALIDO | Q17: COMERCIAL_X080 | R17: 17
A18: O2690013 | B18: 23/03/2026 | C18: Proveedor Ficticio X 095, S.L. | D18: Alquiler de equipos - operacion ficticia | E18: 14145.04 | F18: 1 | G18: 14145.04 | H18: 0 | I18: 14145.04 | J18: CONCILIADO | K18: Aceptado | L18: Facturado | M18: FX26-000845 | N18: XPR26-00606 | Proyecto demostracion 00606 | O18: VALIDO | P18: VALIDO | Q18: CREATIVIDAD_X192 | R18: 18
A19: O2690014 | B19: 05/05/2026 | C19: Proveedor Ficticio X 137, S.L. | D19: Servicios logisticos - operacion ficticia | E19: 15928.27 | F19: 1 | G19: 15928.27 | H19: 0 | I19: 15928.27 | J19: CONCILIADO | K19: Aceptado | L19: Facturado | M19: FX26-000230 | N19: XPR26-01348 | Proyecto demostracion 01348 | O19: VALIDO | P19: VALIDO | Q19: CREATIVIDAD_X192 | R19: 19
A20: O2690015 | B20: 24/06/2026 | C20: Proveedor Ficticio X 123, S.L. | D20: Servicios de diseno - operacion ficticia | E20: 10439.37 | F20: 1 | G20: 10439.37 | H20: 0 | I20: 10439.37 | J20: CONCILIADO | K20: Aceptado | L20: Facturado | M20: FX26-001256 | O20: NO INFORMADO | P20: VALIDO | Q20: CREATIVIDAD_X042 | R20: 20
A21: O2690016 | B21: 13/05/2026 | C21: Proveedor Ficticio X 022, S.L. | D21: Produccion audiovisual - operacion ficticia | E21: 96552.01 | F21: 1 | G21: 96552.01 | H21: 0 | I21: 96552.01 | J21: CONCILIADO | K21: Aceptado | L21: Facturado | M21: FX26-001628 | O21: NO INFORMADO | P21: VALIDO | Q21: CONSULTORIA_X159 | R21: 21
A22: O2690017 | B22: 17/08/2026 | C22: Proveedor Ficticio X 015, S.L. | D22: Mantenimiento informatico - operacion ficticia | E22: 11369.96 | F22: 2 | G22: 5211.29 | H22: 6158.67 | I22: 5211.29 | J22: PARCIAL / DIFERENCIA | K22: Aceptado | L22: Parcialmente | M22: FX26-001147, FX26-001158 | N22: XPR26-00396 | Proyecto demostracion 00396 | O22: VALIDO | P22: VALIDO | Q22: CREATIVIDAD_X032 | R22: 22
A23: O2690018 | B23: 19/01/2026 | C23: Proveedor Ficticio X 041, S.L. | D23: Licencias de software - operacion ficticia | E23: 60641.49 | F23: 1 | G23: 24764.57 | H23: 35876.92 | I23: 24764.57 | J23: PARCIAL / DIFERENCIA | K23: Aceptado | L23: Parcialmente | M23: FX26-000255 | N23: XPR26-03653 | Proyecto demostracion 03653 | O23: VALIDO | P23: VALIDO | Q23: COMERCIAL_X040 | R23: 23
A24: O2690019 | B24: 13/07/2026 | C24: Proveedor Ficticio X 020, S.L. | D24: Traduccion y localizacion - operacion ficticia | E24: 22672.16 | F24: 0 | G24: 0 | H24: 22672.16 | I24: 0 | J24: SIN FACTURA LOCALIZADA | K24: Aceptado | L24: Pendiente | O24: NO INFORMADO | P24: VALIDO | Q24: CONSULTORIA_X009 | R24: 24
A25: O2690020 | B25: 21/01/2026 | C25: Proveedor Ficticio X 139, S.L. | D25: Equipamiento tecnologico - operacion ficticia | E25: 11211.04 | F25: 2 | G25: 11211.04 | H25: 0 | I25: 11211.04 | J25: CONCILIADO | K25: Aceptado | L25: Facturado | M25: FX26-000847, FX26-001278 | N25: XPR26-01281 | Proyecto demostracion 01281 | O25: VALIDO | P25: NO INFORMADO | R25: 25
A26: O2690021 | B26: 05/10/2026 | C26: Proveedor Ficticio X 120, S.L. | D26: Subcontratacion de proyectos - operacion ficticia | E26: 4279.15 | F26: 0 | G26: 0 | H26: 4279.15 | I26: 0 | J26: SIN FACTURA LOCALIZADA | K26: Aceptado | L26: Pendiente | O26: NO INFORMADO | P26: VALIDO | Q26: TECNOLOGIA_X154 | R26: 26
A27: O2690022 | B27: 06/09/2026 | C27: Proveedor Ficticio X 116, S.L. | D27: Equipamiento tecnologico - operacion ficticia | E27: 5646.18 | F27: 0 | G27: 0 | H27: 5646.18 | I27: 0 | J27: SIN FACTURA LOCALIZADA | K27: Aceptado | L27: Pendiente | N27: XPR26-02771 | Proyecto demostracion 02771 | O27: VALIDO | P27: VALIDO | Q27: FINANZAS_X117 | R27: 27
A28: O2690023 | B28: 10/02/2026 | C28: Proveedor Ficticio X 080, S.L. | D28: Asesoria operativa - operacion ficticia | E28: 21106.11 | F28: 2 | G28: 15849.8 | H28: 5256.31 | I28: 15849.8 | J28: PARCIAL / DIFERENCIA | K28: Aceptado | L28: Parcialmente | M28: FX26-000667, FX26-001528 | N28: XPR26-03635 | Proyecto demostracion 03635 | O28: VALIDO | P28: VALIDO | Q28: CREATIVIDAD_X112 | R28: 28
A29: O2690024 | B29: 14/01/2026 | C29: Proveedor Ficticio X 167, S.L. | D29: Servicios logisticos - operacion ficticia | E29: 10625.07 | F29: 0 | G29: 0 | H29: 10625.07 | I29: 0 | J29: CANCELADO / SIN FACTURA | K29: Cancelado | L29: Pendiente | O29: NO INFORMADO | P29: VALIDO | Q29: OPERACIONES_X013 | R29: 29
A30: O2690025 | B30: 02/01/2026 | C30: Proveedor Ficticio X 084, S.L. | D30: Campana de marketing - operacion ficticia | E30: 14902.77 | F30: 2 | G30: 14902.77 | H30: 0 | I30: 14902.77 | J30: CONCILIADO | K30: Aceptado | L30: Facturado | M30: FX26-000007, FX26-000794 | N30: XPR26-00654 | Proyecto demostracion 00654 | O30: VALIDO | P30: VALIDO | Q30: OPERACIONES_X113 | R30: 30
A31: O2690026 | B31: 02/08/2026 | C31: Proveedor Ficticio X 150, S.L. | D31: Licencias de software - operacion ficticia | E31: 19479.43 | F31: 1 | G31: 21651.03 | H31: -2171.6 | I31: 21651.03 | J31: SOBRE PEDIDO | K31: Aceptado | L31: Facturado | M31: FX26-000614 | N31: XPR26-01689 | Proyecto demostracion 01689 | O31: VALIDO | P31: VALIDO | Q31: FINANZAS_X227 | R31: 31
A32: O2690027 | B32: 20/04/2026 | C32: Proveedor Ficticio X 176, S.L. | D32: Produccion audiovisual - operacion ficticia | E32: 8591.27 | F32: 1 | G32: 8591.27 | H32: 0 | I32: 8591.27 | J32: CONCILIADO | K32: Aceptado | L32: Facturado | M32: FX26-000345 | O32: NO INFORMADO | P32: VALIDO | Q32: COMERCIAL_X140 | R32: 32
A33: O2690028 | B33: 13/07/2026 | C33: Proveedor Ficticio X 156, S.L. | D33: Servicios de diseno - operacion ficticia | E33: 21324.73 | F33: 1 | G33: 21324.73 | H33: 0 | I33: 21324.73 | J33: CONCILIADO | K33: Aceptado | L33: Facturado | M33: FX26-001196 | O33: NO INFORMADO | P33: VALIDO | Q33: FINANZAS_X037 | R33: 33
A34: O2690029 | B34: 23/07/2026 | C34: Proveedor Ficticio X 130, S.L. | D34: Subcontratacion de proyectos - operacion ficticia | E34: 25421.37 | F34: 1 | G34: 25421.37 | H34: 0 | I34: 25421.37 | J34: CONCILIADO | K34: Pendiente | L34: Facturado | M34: FX26-001136 | N34: XPR26-02650 | Proyecto demostracion 02650 | O34: VALIDO | P34: VALIDO | Q34: PRODUCCION_X231 | R34: 34
A35: O2690030 | B35: 20/06/2026 | C35: Proveedor Ficticio X 048, S.L. | D35: Licencias de software - operacion ficticia | E35: 5101.92 | F35: 1 | G35: 5101.92 | H35: 0 | I35: 5101.92 | J35: CONCILIADO | K35: Pendiente | L35: Facturado | M35: FX26-001693 | N35: XPR26-03114 | Proyecto demostracion 03114 | O35: VALIDO | P35: VALIDO | Q35: DISENO_X178 | R35: 35
A36: O2690031 | B36: 22/07/2026 | C36: Proveedor Ficticio X 097, S.L. | D36: Subcontratacion de proyectos - operacion ficticia | E36: 20874.84 | F36: 1 | G36: 20874.84 | H36: 0 | I36: 20874.84 | J36: CONCILIADO | K36: Aceptado | L36: Facturado | M36: FX26-001822 | N36: XPR26-01419 | Proyecto demostracion 01419 | O36: VALIDO | P36: VALIDO | Q36: TECNOLOGIA_X204 | R36: 36
A37: O2690032 | B37: 09/01/2026 | C37: Proveedor Ficticio X 049, S.L. | D37: Asesoria operativa - operacion ficticia | E37: 17693.82 | F37: 1 | G37: 17693.82 | H37: 0 | I37: 17693.82 | J37: CONCILIADO | K37: Pendiente | L37: Facturado | M37: FX26-000282 | N37: XPR26-03191 | Proyecto demostracion 03191 | O37: VALIDO | P37: VALIDO | Q37: CONSULTORIA_X109 | R37: 37
A38: O2690033 | B38: 22/01/2026 | C38: Proveedor Ficticio X 133, S.L. | D38: Servicios de diseno - operacion ficticia | E38: 5400.48 | F38: 1 | G38: 5400.48 | H38: 0 | I38: 5400.48 | J38: CONCILIADO | K38: Pendiente | L38: Facturado | M38: FX26-002085 | O38: NO INFORMADO | P38: VALIDO | Q38: CREATIVIDAD_X052 | R38: 38
A39: O2690034 | B39: 11/01/2026 | C39: Proveedor Ficticio X 002, S.L. | D39: Subcontratacion de proyectos - operacion ficticia | E39: 12026.82 | F39: 0 | G39: 0 | H39: 12026.82 | I39: 0 | J39: SIN FACTURA LOCALIZADA | K39: Aceptado | L39: Pendiente | O39: NO INFORMADO | P39: VALIDO | Q39: TECNOLOGIA_X134 | R39: 39
A40: O2690035 | B40: 23/09/2026 | C40: Proveedor Ficticio X 182, S.L. | D40: Material de oficina - operacion ficticia | E40: 8646.51 | F40: 1 | G40: 6073.78 | H40: 2572.73 | I40: 6073.78 | J40: PARCIAL / DIFERENCIA | K40: Aceptado | L40: Parcialmente | M40: FX26-002174 | N40: XPR26-00209 | Proyecto demostracion 00209 | O40: VALIDO | P40: VALIDO | Q40: COMERCIAL_X150 | R40: 40
A41: O2690036 | B41: 09/07/2026 | C41: Proveedor Ficticio X 007, S.L. | D41: Servicios de diseno - operacion ficticia | E41: 459.6 | F41: 1 | G41: 168.33 | H41: 291.27 | I41: 168.33 | J41: PARCIAL / DIFERENCIA | K41: Pendiente | L41: Parcialmente | M41: FX26-000508 | O41: NO INFORMADO | P41: VALIDO | Q41: MARKETING_X275 | R41: 41
A42: O2690037 | B42: 03/03/2026 | C42: Proveedor Ficticio X 001, S.L. | D42: Equipamiento tecnologico - operacion ficticia | E42: 4581.64 | F42: 1 | G42: 4581.64 | H42: 0 | I42: 4581.64 | J42: CONCILIADO | K42: Aceptado | L42: Facturado | M42: FX26-001479 | N42: XPR26-00986 | Proyecto demostracion 00986 | O42: VALIDO | P42: VALIDO | Q42: CONSULTORIA_X029 | R42: 42
A43: O2690038 | B43: 09/09/2026 | C43: Proveedor Ficticio X 155, S.L. | D43: Servicios de diseno - operacion ficticia | E43: 23952.65 | F43: 0 | G43: 0 | H43: 23952.65 | I43: 0 | J43: SIN FACTURA LOCALIZADA | K43: Aceptado | L43: Pendiente | N43: XPR26-00923 | Proyecto demostracion 00923 | O43: VALIDO | P43: VALIDO | Q43: CREATIVIDAD_X062 | R43: 43
A44: O2690039 | B44: 29/08/2026 | C44: Proveedor Ficticio X 075, S.L. | D44: Asistencia tecnica - operacion ficticia | E44: 3408.37 | F44: 0 | G44: 0 | H44: 3408.37 | I44: 0 | J44: SIN FACTURA LOCALIZADA | K44: Pendiente | L44: Pendiente | N44: XPR26-00930 | Proyecto demostracion 00930 | O44: VALIDO | P44: NO INFORMADO | R44: 44
A45: O2690040 | B45: 09/09/2026 | C45: Proveedor Ficticio X 139, S.L. | D45: Mantenimiento informatico - operacion ficticia | E45: 14996.4 | F45: 0 | G45: 0 | H45: 14996.4 | I45: 0 | J45: SIN FACTURA LOCALIZADA | K45: Pendiente | L45: Pendiente | N45: XPR26-00795 | Proyecto demostracion 00795 | O45: VALIDO | P45: VALIDO | Q45: PRODUCCION_X071 | R45: 45
A46: O2690041 | B46: 21/03/2026 | C46: Proveedor Ficticio X 082, S.L. | D46: Servicios logisticos - operacion ficticia | E46: 15984.37 | F46: 1 | G46: 9425.62 | H46: 6558.75 | I46: 9425.62 | J46: PARCIAL / DIFERENCIA | K46: Aceptado | L46: Parcialmente | M46: FX26-000144 | N46: XPR26-00137 | Proyecto demostracion 00137 | O46: VALIDO | P46: VALIDO | Q46: ADMINISTRACION_X046 | R46: 46
A47: O2690042 | B47: 13/09/2026 | C47: Proveedor Ficticio X 184, S.L. | D47: Traduccion y localizacion - operacion ficticia | E47: 24000.92 | F47: 1 | G47: 24000.92 | H47: 0 | I47: 24000.92 | J47: CONCILIADO | K47: Aceptado | L47: Facturado | M47: FX26-001737 | O47: NO INFORMADO | P47: VALIDO | Q47: TECNOLOGIA_X044 | R47: 47
A48: O2690043 | B48: 20/09/2026 | C48: Proveedor Ficticio X 112, S.L. | D48: Mantenimiento informatico - operacion ficticia | E48: 16083.62 | F48: 1 | G48: 16083.62 | H48: 0 | I48: 16083.62 | J48: CONCILIADO | K48: Aceptado | L48: Facturado | M48: FX26-001424 | N48: XPR26-00435 | Proyecto demostracion 00435 | O48: VALIDO | P48: VALIDO | Q48: DISENO_X208 | R48: 48
A49: O2690044 | B49: 28/09/2026 | C49: Proveedor Ficticio X 161, S.L. | D49: Mantenimiento informatico - operacion ficticia | E49: 3419.56 | F49: 1 | G49: 1222.06 | H49: 2197.5 | I49: 1222.06 | J49: PARCIAL / DIFERENCIA | K49: Aceptado | L49: Parcialmente | M49: FX26-000830 | O49: NO INFORMADO | P49: VALIDO | Q49: FINANZAS_X127 | R49: 49
A50: O2690045 | B50: 13/08/2026 | C50: Proveedor Ficticio X 177, S.L. | D50: Licencias de software - operacion ficticia | E50: 23397.08 | F50: 1 | G50: 20012.67 | H50: 3384.41 | I50: 20012.67 | J50: PARCIAL / DIFERENCIA | K50: Aceptado | L50: Parcialmente | M50: FX26-001195 | N50: XPR26-01869 | Proyecto demostracion 01869 | O50: VALIDO | P50: VALIDO | Q50: FINANZAS_X277 | R50: 50
A51: O2690046 | B51: 19/03/2026 | C51: Proveedor Ficticio X 089, S.L. | D51: Servicios de diseno - operacion ficticia | E51: 18876.34 | F51: 1 | G51: 18876.34 | H51: 0 | I51: 18876.34 | J51: CONCILIADO | K51: Pendiente | L51: Facturado | M51: FX26-001790 | N51: XPR26-00166 | Proyecto demostracion 00166 | O51: VALIDO | P51: VALIDO | Q51: FINANZAS_X177 | R51: 51
A52: O2690047 | B52: 25/01/2026 | C52: Proveedor Ficticio X 080, S.L. | D52: Traduccion y localizacion - operacion ficticia | E52: 946.55 | F52: 2 | G52: 946.54 | H52: 0.01 | I52: 946.54 | J52: CONCILIADO | K52: Aceptado | L52: Facturado | M52: FX26-000011, FX26-000945 | N52: XPR26-00173 | Proyecto demostracion 00173 | O52: VALIDO | P52: VALIDO | Q52: DISENO_X148 | R52: 52
A53: O2690048 | B53: 08/10/2026 | C53: Proveedor Ficticio X 095, S.L. | D53: Equipamiento tecnologico - operacion ficticia | E53: 5391.33 | F53: 1 | G53: 6379.4 | H53: -988.07 | I53: 6379.4 | J53: SOBRE PEDIDO | K53: Aceptado | L53: Facturado | M53: FX26-001571 | N53: XPR26-03191 | Proyecto demostracion 03191 | O53: VALIDO | P53: VALIDO | Q53: CONSULTORIA_X109 | R53: 53
A54: O2690049 | B54: 21/02/2026 | C54: Proveedor Ficticio X 167, S.L. | D54: Asistencia tecnica - operacion ficticia | E54: 11382.77 | F54: 0 | G54: 0 | H54: 11382.77 | I54: 0 | J54: SIN FACTURA LOCALIZADA | K54: Pendiente | L54: Pendiente | N54: XPR26-00667 | Proyecto demostracion 00667 | O54: VALIDO | P54: VALIDO | Q54: COMERCIAL_X080 | R54: 54
A55: O2690050 | B55: 27/08/2026 | C55: Proveedor Ficticio X 146, S.L. | D55: Subcontratacion de proyectos - operacion ficticia | E55: 781.76 | F55: 0 | G55: 0 | H55: 781.76 | I55: 0 | J55: SIN FACTURA LOCALIZADA | K55: Aceptado | L55: Pendiente | N55: XPR26-03762 | Proyecto demostracion 03762 | O55: VALIDO | P55: VALIDO | Q55: FINANZAS_X147 | R55: 55
A56: O2690051 | B56: 03/01/2026 | C56: Proveedor Ficticio X 144, S.L. | D56: Servicios logisticos - operacion ficticia | E56: 11779.01 | F56: 1 | G56: 11779.01 | H56: 0 | I56: 11779.01 | J56: CONCILIADO | K56: Aceptado | L56: Facturado | M56: FX26-000334 | N56: XPR26-02632 | Proyecto demostracion 02632 | O56: VALIDO | P56: VALIDO | Q56: DISENO_X058 | R56: 56
A57: O2690052 | B57: 04/03/2026 | C57: Proveedor Ficticio X 031, S.L. | D57: Servicios logisticos - operacion ficticia | E57: 24403.53 | F57: 0 | G57: 0 | H57: 24403.53 | I57: 0 | J57: SIN FACTURA LOCALIZADA | K57: Aceptado | L57: Pendiente | O57: NO INFORMADO | P57: VALIDO | Q57: PRODUCCION_X091 | R57: 57
A58: O2690053 | B58: 19/02/2026 | C58: Proveedor Ficticio X 176, S.L. | D58: Asesoria operativa - operacion ficticia | E58: 1298.15 | F58: 1 | G58: 1298.15 | H58: 0 | I58: 1298.15 | J58: CONCILIADO | K58: Aceptado | L58: Facturado | M58: FX26-002168 | N58: XPR26-01984 | Proyecto demostracion 01984 | O58: VALIDO | P58: VALIDO | Q58: ADMINISTRACION_X196 | R58: 58
A59: O2690054 | B59: 28/03/2026 | C59: Proveedor Ficticio X 012, S.L. | D59: Servicios de diseno - operacion ficticia | E59: 21437.91 | F59: 0 | G59: 0 | H59: 21437.91 | I59: 0 | J59: SIN FACTURA LOCALIZADA | K59: Aceptado | L59: Pendiente | N59: XPR26-00964 | Proyecto demostracion 00964 | O59: VALIDO | P59: VALIDO | Q59: DISENO_X238 | R59: 59
A60: O2690055 | B60: 16/05/2026 | C60: Proveedor Ficticio X 104, S.L. | D60: Servicios logisticos - operacion ficticia | E60: 26980.45 | F60: 1 | G60: 26980.45 | H60: 0 | I60: 26980.45 | J60: CONCILIADO | K60: Aceptado | L60: Facturado | M60: FX26-001985 | O60: NO INFORMADO | P60: VALIDO | Q60: MARKETING_X085 | R60: 60
A61: O2690056 | B61: 06/03/2026 | C61: Proveedor Ficticio X 070, S.L. | D61: Mantenimiento informatico - operacion ficticia | E61: 17665.04 | F61: 1 | G61: 17665.04 | H61: 0 | I61: 17665.04 | J61: CONCILIADO | K61: Aceptado | L61: Facturado | M61: FX26-002080 | N61: XPR26-02976 | Proyecto demostracion 02976 | O61: VALIDO | P61: VALIDO | Q61: CONSULTORIA_X199 | R61: 61
A62: O2690057 | B62: 29/07/2026 | C62: Proveedor Ficticio X 020, S.L. | D62: Equipamiento tecnologico - operacion ficticia | E62: 797.2 | F62: 0 | G62: 0 | H62: 797.2 | I62: 0 | J62: SIN FACTURA LOCALIZADA | K62: Aceptado | L62: Pendiente | N62: XPR26-02237 | Proyecto demostracion 02237 | O62: VALIDO | P62: VALIDO | Q62: FINANZAS_X167 | R62: 62
A63: O2690058 | B63: 20/09/2026 | C63: Proveedor Ficticio X 140, S.L. | D63: Asistencia tecnica - operacion ficticia | E63: 11265.73 | F63: 1 | G63: 11265.73 | H63: 0 | I63: 11265.73 | J63: CONCILIADO | K63: Aceptado | L63: Facturado | M63: FX26-001903 | N63: XPR26-02936 | Proyecto demostracion 02936 | O63: VALIDO | P63: NO INFORMADO | R63: 63
A64: O2690059 | B64: 02/02/2026 | C64: Proveedor Ficticio X 133, S.L. | D64: Traduccion y localizacion - operacion ficticia | E64: 25598.93 | F64: 0 | G64: 0 | H64: 25598.93 | I64: 0 | J64: CANCELADO / SIN FACTURA | K64: Cancelado | L64: Pendiente | N64: XPR26-02407 | Proyecto demostracion 02407 | O64: VALIDO | P64: VALIDO | Q64: PRODUCCION_X091 | R64: 64
A65: O2690060 | B65: 03/03/2026 | C65: Proveedor Ficticio X 172, S.L. | D65: Alquiler de equipos - operacion ficticia | E65: 21461.45 | F65: 1 | G65: 21461.45 | H65: 0 | I65: 21461.45 | J65: CONCILIADO | K65: Aceptado | L65: Facturado | M65: FX26-001087 | N65: XPR26-02528 | Proyecto demostracion 02528 | O65: VALIDO | P65: VALIDO | Q65: MARKETING_X215 | R65: 65
A66: O2690061 | B66: 08/02/2026 | C66: Proveedor Ficticio X 077, S.L. | D66: Traduccion y localizacion - operacion ficticia | E66: 54003.11 | F66: 0 | G66: 0 | H66: 54003.11 | I66: 0 | J66: SIN FACTURA LOCALIZADA | K66: Aceptado | L66: Pendiente | O66: NO INFORMADO | P66: VALIDO | Q66: CONSULTORIA_X089 | R66: 66
A67: O2690062 | B67: 12/09/2026 | C67: Proveedor Ficticio X 056, S.L. | D67: Licencias de software - operacion ficticia | E67: 245.25 | F67: 1 | G67: 245.25 | H67: 0 | I67: 245.25 | J67: CONCILIADO | K67: Pendiente | L67: Facturado | M67: FX26-000504 | N67: XPR26-02237 | Proyecto demostracion 02237 | O67: VALIDO | P67: VALIDO | Q67: FINANZAS_X167 | R67: 67
A68: O2690063 | B68: 27/06/2026 | C68: Proveedor Ficticio X 104, S.L. | D68: Traduccion y localizacion - operacion ficticia | E68: 1254.31 | F68: 1 | G68: 1254.31 | H68: 0 | I68: 1254.31 | J68: CONCILIADO | K68: Aceptado | L68: Facturado | M68: FX26-000017 | N68: XPR26-01235 | Proyecto demostracion 01235 | O68: VALIDO | P68: VALIDO | Q68: ADMINISTRACION_X036 | R68: 68
A69: O2690064 | B69: 22/06/2026 | C69: Proveedor Ficticio X 133, S.L. | D69: Traduccion y localizacion - operacion ficticia | E69: 2138.03 | F69: 1 | G69: 756.42 | H69: 1381.61 | I69: 756.42 | J69: PARCIAL / DIFERENCIA | K69: Aceptado | L69: Parcialmente | M69: FX26-001420 | N69: XPR26-00091 | Proyecto demostracion 00091 | O69: VALIDO | P69: VALIDO | Q69: OPERACIONES_X063 | R69: 69
A70: O2690065 | B70: 13/03/2026 | C70: Proveedor Ficticio X 087, S.L. | D70: Servicios logisticos - operacion ficticia | E70: 20261.84 | F70: 1 | G70: 20261.84 | H70: 0 | I70: 20261.84 | J70: CONCILIADO | K70: Aceptado | L70: Facturado | M70: FX26-000005 | N70: XPR26-00178 | Proyecto demostracion 00178 | O70: VALIDO | P70: VALIDO | Q70: CONSULTORIA_X089 | R70: 70
A71: O2690066 | B71: 18/07/2026 | C71: Proveedor Ficticio X 065, S.L. | D71: Produccion de contenido - operacion ficticia | E71: 18000.09 | F71: 0 | G71: 0 | H71: 18000.09 | I71: 0 | J71: SIN FACTURA LOCALIZADA | K71: Aceptado | L71: Pendiente | O71: NO INFORMADO | P71: VALIDO | Q71: OPERACIONES_X253 | R71: 71
A72: O2690067 | B72: 09/09/2026 | C72: Proveedor Ficticio X 061, S.L. | D72: Produccion audiovisual - operacion ficticia | E72: 7930.21 | F72: 2 | G72: 7930.2 | H72: 0.01 | I72: 7930.2 | J72: CONCILIADO | K72: Aceptado | L72: Facturado | M72: FX26-001652, FX26-002193 | N72: XPR26-01869 | Proyecto demostracion 01869 | O72: VALIDO | P72: VALIDO | Q72: FINANZAS_X277 | R72: 72
A73: O2690068 | B73: 14/05/2026 | C73: Proveedor Ficticio X 026, S.L. | D73: Produccion de contenido - operacion ficticia | E73: 24190.65 | F73: 1 | G73: 24190.65 | H73: 0 | I73: 24190.65 | J73: CONCILIADO | K73: Aceptado | L73: Facturado | M73: FX26-001556 | N73: XPR26-02958 | Proyecto demostracion 02958 | O73: VALIDO | P73: VALIDO | Q73: CREATIVIDAD_X232 | R73: 73
A74: O2690069 | B74: 29/01/2026 | C74: Proveedor Ficticio X 096, S.L. | D74: Material de oficina - operacion ficticia | E74: 21479.63 | F74: 0 | G74: 0 | H74: 21479.63 | I74: 0 | J74: SIN FACTURA LOCALIZADA | K74: Aceptado | L74: Pendiente | O74: NO INFORMADO | P74: VALIDO | Q74: MARKETING_X055 | R74: 74
A75: O2690070 | B75: 26/06/2026 | C75: Proveedor Ficticio X 140, S.L. | D75: Equipamiento tecnologico - operacion ficticia | E75: 16955.27 | F75: 0 | G75: 0 | H75: 16955.27 | I75: 0 | J75: SIN FACTURA LOCALIZADA | K75: Aceptado | L75: Pendiente | N75: XPR26-03729 | Proyecto demostracion 03729 | O75: VALIDO | P75: VALIDO | Q75: DISENO_X238 | R75: 75
A76: O2690071 | B76: 01/03/2026 | C76: Proveedor Ficticio X 181, S.L. | D76: Alquiler de equipos - operacion ficticia | E76: 20224.64 | F76: 1 | G76: 11455.69 | H76: 8768.95 | I76: 11455.69 | J76: PARCIAL / DIFERENCIA | K76: Aceptado | L76: Parcialmente | M76: FX26-002166 | O76: NO INFORMADO | P76: VALIDO | Q76: CONSULTORIA_X169 | R76: 76
A77: O2690072 | B77: 24/02/2026 | C77: Proveedor Ficticio X 138, S.L. | D77: Servicios profesionales - operacion ficticia | E77: 2449.52 | F77: 0 | G77: 0 | H77: 2449.52 | I77: 0 | J77: SIN FACTURA LOCALIZADA | K77: Aceptado | L77: Pendiente | N77: XPR26-01878 | Proyecto demostracion 01878 | O77: VALIDO | P77: VALIDO | Q77: MARKETING_X165 | R77: 77
A78: O2690073 | B78: 06/02/2026 | C78: Proveedor Ficticio X 080, S.L. | D78: Campana de marketing - operacion ficticia | E78: 5398.84 | F78: 0 | G78: 0 | H78: 5398.84 | I78: 0 | J78: SIN FACTURA LOCALIZADA | K78: Aceptado | L78: Pendiente | N78: XPR26-00316 | Proyecto demostracion 00316 | O78: VALIDO | P78: VALIDO | Q78: FINANZAS_X077 | R78: 78
A79: O2690074 | B79: 21/02/2026 | C79: Proveedor Ficticio X 060, S.L. | D79: Mantenimiento informatico - operacion ficticia | E79: 82471.42 | F79: 1 | G79: 82471.42 | H79: 0 | I79: 82471.42 | J79: CONCILIADO | K79: Aceptado | L79: Facturado | M79: FX26-000709 | O79: NO INFORMADO | P79: VALIDO | Q79: MARKETING_X025 | R79: 79
A80: O2690075 | B80: 16/04/2026 | C80: Proveedor Ficticio X 084, S.L. | D80: Subcontratacion de proyectos - operacion ficticia | E80: 5412.09 | F80: 1 | G80: 6250.29 | H80: -838.2 | I80: 6250.29 | J80: SOBRE PEDIDO | K80: Aceptado | L80: Facturado | M80: FX26-000114 | N80: XPR26-02313 | Proyecto demostracion 02313 | O80: VALIDO | P80: VALIDO | Q80: DISENO_X218 | R80: 80
A81: O2690076 | B81: 23/01/2026 | C81: Proveedor Ficticio X 053, S.L. | D81: Asistencia tecnica - operacion ficticia | E81: 18829.98 | F81: 1 | G81: 9969.19 | H81: 8860.79 | I81: 9969.19 | J81: PARCIAL / DIFERENCIA | K81: Aceptado | L81: Parcialmente | M81: FX26-000539 | N81: XPR26-00923 | Proyecto demostracion 00923 | O81: VALIDO | P81: VALIDO | Q81: CREATIVIDAD_X062 | R81: 81
A82: O2690077 | B82: 19/07/2026 | C82: Proveedor Ficticio X 015, S.L. | D82: Alquiler de equipos - operacion ficticia | E82: 22852.58 | F82: 0 | G82: 0 | H82: 22852.58 | I82: 0 | J82: SIN FACTURA LOCALIZADA | K82: Aceptado | L82: Pendiente | N82: XPR26-00923 | Proyecto demostracion 00923 | O82: VALIDO | P82: NO INFORMADO | R82: 82
A83: O2690078 | B83: 01/04/2026 | C83: Proveedor Ficticio X 057, S.L. | D83: Servicios logisticos - operacion ficticia | E83: 16322.86 | F83: 0 | G83: 0 | H83: 16322.86 | I83: 0 | J83: SIN FACTURA LOCALIZADA | K83: Aceptado | L83: Pendiente | N83: XPR26-03886 | Proyecto demostracion 03886 | O83: VALIDO | P83: VALIDO | Q83: MARKETING_X205 | R83: 83
A84: O2690079 | B84: 02/07/2026 | C84: Proveedor Ficticio X 071, S.L. | D84: Asesoria operativa - operacion ficticia | E84: 13977.68 | F84: 2 | G84: 15466.73 | H84: -1489.05 | I84: 15466.73 | J84: SOBRE PEDIDO | K84: Pendiente | L84: Facturado | M84: FX26-000236, FX26-000269 | O84: NO INFORMADO | P84: VALIDO | Q84: TECNOLOGIA_X214 | R84: 84
A85: O2690080 | B85: 23/04/2026 | C85: Proveedor Ficticio X 095, S.L. | D85: Mantenimiento informatico - operacion ficticia | E85: 27574.25 | F85: 1 | G85: 18393.91 | H85: 9180.34 | I85: 18393.91 | J85: PARCIAL / DIFERENCIA | K85: Aceptado | L85: Parcialmente | M85: FX26-001454 | O85: NO INFORMADO | P85: VALIDO | Q85: MARKETING_X135 | R85: 85
A86: O2690081 | B86: 29/04/2026 | C86: Proveedor Ficticio X 156, S.L. | D86: Subcontratacion de proyectos - operacion ficticia | E86: 16127.55 | F86: 1 | G86: 16127.55 | H86: 0 | I86: 16127.55 | J86: CONCILIADO | K86: Aceptado | L86: Facturado | M86: FX26-000358 | N86: XPR26-01443 | Proyecto demostracion 01443 | O86: VALIDO | P86: VALIDO | Q86: FINANZAS_X007 | R86: 86
A87: O2690082 | B87: 02/05/2026 | C87: Proveedor Ficticio X 113, S.L. | D87: Asistencia tecnica - operacion ficticia | E87: 5248.92 | F87: 1 | G87: 6445.48 | H87: -1196.56 | I87: 6445.48 | J87: SOBRE PEDIDO | K87: Aceptado | L87: Facturado | M87: FX26-000921 | N87: XPR26-03739 | Proyecto demostracion 03739 | O87: VALIDO | P87: VALIDO | Q87: DISENO_X148 | R87: 87
A88: O2690083 | B88: 04/01/2026 | C88: Proveedor Ficticio X 022, S.L. | D88: Produccion audiovisual - operacion ficticia | E88: 22668.54 | F88: 0 | G88: 0 | H88: 22668.54 | I88: 0 | J88: SIN FACTURA LOCALIZADA | K88: Aceptado | L88: Pendiente | O88: NO INFORMADO | P88: VALIDO | Q88: CONSULTORIA_X169 | R88: 88
A89: O2690084 | B89: 14/01/2026 | C89: Proveedor Ficticio X 053, S.L. | D89: Asistencia tecnica - operacion ficticia | E89: 23554.16 | F89: 1 | G89: 23554.16 | H89: 0 | I89: 23554.16 | J89: CONCILIADO | K89: Aceptado | L89: Facturado | M89: FX26-002173 | N89: XPR26-03729 | Proyecto demostracion 03729 | O89: VALIDO | P89: VALIDO | Q89: DISENO_X238 | R89: 89
A90: O2690085 | B90: 12/01/2026 | C90: Proveedor Ficticio X 008, S.L. | D90: Servicios logisticos - operacion ficticia | E90: 13128.57 | F90: 1 | G90: 13128.57 | H90: 0 | I90: 13128.57 | J90: CONCILIADO | K90: Aceptado | L90: Facturado | M90: FX26-001242 | N90: XPR26-00986 | Proyecto demostracion 00986 | O90: VALIDO | P90: VALIDO | Q90: CONSULTORIA_X029 | R90: 90
A91: O2690086 | B91: 13/04/2026 | C91: Proveedor Ficticio X 036, S.L. | D91: Servicios profesionales - operacion ficticia | E91: 1594.36 | F91: 0 | G91: 0 | H91: 1594.36 | I91: 0 | J91: SIN FACTURA LOCALIZADA | K91: Aceptado | L91: Pendiente | N91: XPR26-00491 | Proyecto demostracion 00491 | O91: VALIDO | P91: VALIDO | Q91: CONSULTORIA_X159 | R91: 91
A92: O2690087 | B92: 19/07/2026 | C92: Proveedor Ficticio X 053, S.L. | D92: Mantenimiento informatico - operacion ficticia | E92: 4299.05 | F92: 1 | G92: 4299.05 | H92: 0 | I92: 4299.05 | J92: CONCILIADO | K92: Pendiente | L92: Facturado | M92: FX26-001406 | N92: XPR26-00178 | Proyecto demostracion 00178 | O92: VALIDO | P92: VALIDO | Q92: CONSULTORIA_X089 | R92: 92
A93: O2690088 | B93: 01/10/2026 | C93: Proveedor Ficticio X 017, S.L. | D93: Equipamiento tecnologico - operacion ficticia | E93: 10928.26 | F93: 1 | G93: 6208.73 | H93: 4719.53 | I93: 6208.73 | J93: PARCIAL / DIFERENCIA | K93: Pendiente | L93: Parcialmente | M93: FX26-000761 | N93: XPR26-02930 | Proyecto demostracion 02930 | O93: VALIDO | P93: VALIDO | Q93: MARKETING_X145 | R93: 93
A94: O2690089 | B94: 27/07/2026 | C94: Proveedor Ficticio X 175, S.L. | D94: Subcontratacion de proyectos - operacion ficticia | E94: 15705.13 | F94: 1 | G94: 15705.13 | H94: 0 | I94: 15705.13 | J94: CONCILIADO | K94: Aceptado | L94: Facturado | M94: FX26-001760 | N94: XPR26-02324 | Proyecto demostracion 02324 | O94: VALIDO | P94: VALIDO | Q94: COMERCIAL_X070 | R94: 94
A95: O2690090 | B95: 31/05/2026 | C95: Proveedor Ficticio X 173, S.L. | D95: Equipamiento tecnologico - operacion ficticia | E95: 2019.61 | F95: 2 | G95: 2019.62 | H95: -0.01 | I95: 2019.62 | J95: CONCILIADO | K95: Pendiente | L95: Facturado | M95: FX26-000563, FX26-001829 | N95: XPR26-03739 | Proyecto demostracion 03739 | O95: VALIDO | P95: VALIDO | Q95: DISENO_X148 | R95: 95
A96: O2690091 | B96: 11/02/2026 | C96: Proveedor Ficticio X 128, S.L. | D96: Mantenimiento informatico - operacion ficticia | E96: 271.96 | F96: 3 | G96: 271.97 | H96: -0.01 | I96: 271.97 | J96: CONCILIADO | K96: Aceptado | L96: Facturado | M96: FX26-000367, FX26-000566, FX26-001043 | N96: XPR26-00964 | Proyecto demostracion 00964 | O96: VALIDO | P96: VALIDO | Q96: DISENO_X238 | R96: 96
A97: O2690092 | B97: 25/07/2026 | C97: Proveedor Ficticio X 160, S.L. | D97: Mantenimiento informatico - operacion ficticia | E97: 17708.74 | F97: 1 | G97: 17708.74 | H97: 0 | I97: 17708.74 | J97: CONCILIADO | K97: Aceptado | L97: Facturado | M97: FX26-001238 | O97: NO INFORMADO | P97: VALIDO | Q97: OPERACIONES_X133 | R97: 97
A98: O2690093 | B98: 16/01/2026 | C98: Proveedor Ficticio X 015, S.L. | D98: Alquiler de equipos - operacion ficticia | E98: 28055.12 | F98: 1 | G98: 12694.76 | H98: 15360.36 | I98: 12694.76 | J98: PARCIAL / DIFERENCIA | K98: Aceptado | L98: Parcialmente | M98: FX26-000524 | N98: XPR26-02315 | Proyecto demostracion 02315 | O98: VALIDO | P98: VALIDO | Q98: TECNOLOGIA_X184 | R98: 98
A99: O2690094 | B99: 23/08/2026 | C99: Proveedor Ficticio X 082, S.L. | D99: Servicios logisticos - operacion ficticia | E99: 12100.17 | F99: 1 | G99: 12100.17 | H99: 0 | I99: 12100.17 | J99: CONCILIADO | K99: Aceptado | L99: Facturado | M99: FX26-001110 | N99: XPR26-00310 | Proyecto demostracion 00310 | O99: VALIDO | P99: VALIDO | Q99: MARKETING_X245 | R99: 99
A100: O2690095 | B100: 13/08/2026 | C100: Proveedor Ficticio X 021, S.L. | D100: Licencias de software - operacion ficticia | E100: 22850.1 | F100: 0 | G100: 0 | H100: 22850.1 | I100: 0 | J100: SIN FACTURA LOCALIZADA | K100: Pendiente | L100: Pendiente | O100: NO INFORMADO | P100: VALIDO | Q100: MARKETING_X165 | R100: 100
A101: O2690096 | B101: 09/04/2026 | C101: Proveedor Ficticio X 106, S.L. | D101: Campana de marketing - operacion ficticia | E101: 15937.27 | F101: 1 | G101: 18372.14 | H101: -2434.87 | I101: 18372.14 | J101: SOBRE PEDIDO | K101: Aceptado | L101: Facturado | M101: FX26-001997 | N101: XPR26-01668 | Proyecto demostracion 01668 | O101: VALIDO | P101: NO INFORMADO | R101: 101
A102: O2690097 | B102: 11/08/2026 | C102: Proveedor Ficticio X 097, S.L. | D102: Asistencia tecnica - operacion ficticia | E102: 20452.59 | F102: 2 | G102: 13983.43 | H102: 6469.16 | I102: 13983.43 | J102: PARCIAL / DIFERENCIA | K102: Pendiente | L102: Parcialmente | M102: FX26-000086, FX26-001529 | O102: NO INFORMADO | P102: VALIDO | Q102: MARKETING_X115 | R102: 102
...

Sheet 03_Facturas
A1: UNIVERSO DE FACTURAS
A3: Todas las facturas de Compras; mantener abonos y facturas sin referencia PO; fecha contable vs emisión
A5: Factura | B5: Emisión | C5: Fecha contable | D5: Proveedor | E5: Descripción | F5: PO citada | G5: Vínculo | H5: Subtotal € | I5: IVA € | J5: Total € | K5: Pagado € | L5: Pendiente € | M5: Estado | N5: Proyecto | O5: Val. proyecto | P5: Val. CECO | Q5: Cuenta | R5: Fila origen
A6: FX26-000001 | B6: 26/02/2026 | C6: 26/02/2026 | D6: Proveedor Ficticio X 233, S.L. | E6: Subcontratacion de proyectos | servicio ficticio 0001 | G6: SIN REFERENCIA PO | H6: -12760.68 | I6: 0 | J6: -12760.68 | K6: -12760.68 | L6: 0 | M6: Pagado | N6: XPR26-03528 | Proyecto demostracion 03528 | O6: VALIDO | P6: VALIDO | Q6: Publicidad, propaganda y relaciones publicas | R6: 6
A7: FX26-000002 | B7: 11/09/2026 | C7: 11/09/2026 | D7: Proveedor Ficticio X 194, S.L. | E7: Equipamiento tecnologico | servicio ficticio 0002 | G7: SIN REFERENCIA PO | H7: 12344.41 | I7: 2592.33 | J7: 14936.74 | K7: 14936.74 | L7: 0 | M7: Pagado | O7: NO INFORMADO | P7: VALIDO | Q7: Otros servicios | R7: 7
A8: FX26-000003 | B8: 03/04/2026 | C8: 03/04/2026 | D8: Proveedor Ficticio X 033, S.L. | E8: Alquiler de equipos | servicio ficticio 0003 | G8: SIN REFERENCIA PO | H8: 7664.63 | I8: 766.46 | J8: 8431.09 | K8: 8431.09 | L8: 0 | M8: Pagado | O8: NO INFORMADO | P8: VALIDO | Q8: Subcontractors | R8: 8
A9: FX26-000004 | B9: 31/03/2026 | C9: 31/03/2026 | D9: Proveedor Ficticio X 129, S.L. | E9: Mantenimiento informatico | servicio ficticio 0004 | G9: SIN REFERENCIA PO | H9: 14042.21 | I9: 2948.86 | J9: 16991.07 | K9: 16991.07 | L9: 0 | M9: Pagado | O9: NO INFORMADO | P9: VALIDO | Q9: Arrendamientos y canones | R9: 9
A10: FX26-000005 | B10: 23/05/2026 | C10: 23/05/2026 | D10: Proveedor Ficticio X 087, S.L. | E10: O2690065 | Servicios logisticos | ejemplo ficticio | F10: O2690065 | G10: VINCULADA | H10: 16745.32 | I10: 3516.52 | J10: 20261.84 | K10: 20261.84 | L10: 0 | M10: Pagado | N10: XPR26-00178 | Proyecto demostracion 00178 | O10: VALIDO | P10: VALIDO | Q10: Equipos para procesos de informacion | R10: 10
A11: FX26-000006 | B11: 11/01/2026 | C11: 11/01/2026 | D11: Proveedor Ficticio X 111, S.L. | E11: Produccion audiovisual | servicio ficticio 0006 | G11: SIN REFERENCIA PO | H11: 10788.79 | I11: 2265.65 | J11: 13054.44 | K11: 0 | L11: 13054.44 | M11: Vencido | O11: NO INFORMADO | P11: VALIDO | Q11: Otros servicios | R11: 11
A12: FX26-000007 | B12: 02/01/2026 | C12: 02/01/2026 | D12: Proveedor Ficticio X 084, S.L. | E12: O2690025 | Campana de marketing | ejemplo ficticio | F12: O2690025 | G12: VINCULADA | H12: 3569.53 | I12: 0 | J12: 3569.53 | K12: 3569.53 | L12: 0 | M12: Pagado | N12: XPR26-00654 | Proyecto demostracion 00654 | O12: VALIDO | P12: VALIDO | Q12: Material de oficina | R12: 12
A13: FX26-000008 | B13: 13/09/2026 | C13: 13/09/2026 | D13: Proveedor Ficticio X 067, S.L. | E13: Traduccion y localizacion | servicio ficticio 0008 | G13: SIN REFERENCIA PO | H13: 1655.83 | I13: 0 | J13: 1655.83 | K13: 0 | L13: 1655.83 | M13: Pendiente | N13: XPR26-02313 | Proyecto demostracion 02313 | O13: VALIDO | P13: VALIDO | Q13: TRABAJOS REALIZADOS POR OTRAS EMPRESAS | R13: 13
A14: FX26-000009 | B14: 22/03/2026 | C14: 22/03/2026 | D14: Proveedor Ficticio X 156, S.L. | E14: Campana de marketing | servicio ficticio 0009 | G14: SIN REFERENCIA PO | H14: 8771.47 | I14: 1842.01 | J14: 10613.48 | K14: 10613.48 | L14: 0 | M14: Pagado | N14: XPR26-02771 | Proyecto demostracion 02771 | O14: VALIDO | P14: VALIDO | Q14: Material de oficina | R14: 14
A15: FX26-000010 | B15: 08/04/2026 | C15: 08/04/2026 | D15: Proveedor Ficticio X 135, S.L. | E15: Campana de marketing | servicio ficticio 0010 | G15: SIN REFERENCIA PO | H15: 790.82 | I15: 166.07 | J15: 956.89 | K15: 956.89 | L15: 0 | M15: Pagado | O15: NO INFORMADO | P15: VALIDO | Q15: Material de oficina | R15: 15
A16: FX26-000011 | B16: 30/03/2026 | C16: 30/03/2026 | D16: Proveedor Ficticio X 080, S.L. | E16: O2690047 | Traduccion y localizacion | ejemplo ficticio | F16: O2690047 | G16: VINCULADA | H16: 321.16 | I16: 67.44 | J16: 388.6 | K16: 388.6 | L16: 0 | M16: Pagado | N16: XPR26-00173 | Proyecto demostracion 00173 | O16: VALIDO | P16: VALIDO | Q16: TRABAJOS REALIZADOS POR OTRAS EMPRESAS | R16: 16
A17: FX26-000012 | B17: 03/06/2026 | C17: 03/06/2026 | D17: Proveedor Ficticio X 103, S.L. | E17: Equipamiento tecnologico | servicio ficticio 0012 | G17: SIN REFERENCIA PO | H17: 12304.53 | I17: 0 | J17: 12304.53 | K17: 0 | L17: 12304.53 | M17: Vencido | N17: XPR26-01517 | Proyecto demostracion 01517 | O17: VALIDO | P17: VALIDO | Q17: Otros servicios | R17: 17
A18: FX26-000013 | B18: 18/07/2026 | C18: 18/07/2026 | D18: Proveedor Ficticio X 148, S.L. | E18: Servicios logisticos | servicio ficticio 0013 | G18: SIN REFERENCIA PO | H18: 13489.57 | I18: 2832.81 | J18: 16322.38 | K18: 5269.63 | L18: 11052.75 | M18: Vencido | N18: XPR26-02407 | Proyecto demostracion 02407 | O18: VALIDO | P18: VALIDO | Q18: Equipos para procesos de informacion | R18: 18
A19: FX26-000014 | B19: 22/02/2026 | C19: 22/02/2026 | D19: Proveedor Ficticio X 191, S.L. | E19: Campana de marketing | servicio ficticio 0014 | G19: SIN REFERENCIA PO | H19: 8377.69 | I19: 1759.31 | J19: 10137 | K19: 10137 | L19: 0 | M19: Pagado | O19: NO INFORMADO | P19: VALIDO | Q19: Material de oficina | R19: 19
A20: FX26-000015 | B20: 27/01/2026 | C20: 27/01/2026 | D20: Proveedor Ficticio X 148, S.L. | E20: Servicios de diseno | servicio ficticio 0015 | G20: SIN REFERENCIA PO | H20: 8904.99 | I20: 1870.05 | J20: 10775.04 | K20: 10775.04 | L20: 0 | M20: Pagado | N20: XPR26-02563 | Proyecto demostracion 02563 | O20: VALIDO | P20: VALIDO | Q20: TRABAJOS REALIZADOS POR OTRAS EMPRESAS | R20: 20
A21: FX26-000016 | B21: 25/06/2026 | C21: 25/06/2026 | D21: Proveedor Ficticio X 030, S.L. | E21: Asesoria operativa | servicio ficticio 0016 | G21: SIN REFERENCIA PO | H21: 4375.16 | I21: 0 | J21: 4375.16 | K21: 0 | L21: 4375.16 | M21: Vencido | N21: XPR26-03887 | Proyecto demostracion 03887 | O21: VALIDO | P21: VALIDO | Q21: Transportes | R21: 21
A22: FX26-000017 | B22: 21/07/2026 | C22: 21/07/2026 | D22: Proveedor Ficticio X 104, S.L. | E22: O2690063 | Traduccion y localizacion | ejemplo ficticio | F22: O2690063 | G22: VINCULADA | H22: 1036.62 | I22: 217.69 | J22: 1254.31 | K22: 1254.31 | L22: 0 | M22: Pagado | N22: XPR26-01235 | Proyecto demostracion 01235 | O22: VALIDO | P22: VALIDO | Q22: TRABAJOS REALIZADOS POR OTRAS EMPRESAS | R22: 22
A23: FX26-000018 | B23: 14/01/2026 | C23: 14/01/2026 | D23: Proveedor Ficticio X 061, S.L. | E23: Material de oficina | servicio ficticio 0018 | G23: SIN REFERENCIA PO | H23: 1398.38 | I23: 293.66 | J23: 1692.04 | K23: 1692.04 | L23: 0 | M23: Pagado | N23: XPR26-03880 | Proyecto demostracion 03880 | O23: VALIDO | P23: VALIDO | Q23: Servicios profesionales independientes | R23: 23
A24: FX26-000019 | B24: 12/01/2026 | C24: 12/01/2026 | D24: Proveedor Ficticio X 200, S.L. | E24: Produccion audiovisual | servicio ficticio 0019 | G24: SIN REFERENCIA PO | H24: 10564.42 | I24: 0 | J24: 10564.42 | K24: 0 | L24: 10564.42 | M24: Vencido | O24: NO INFORMADO | P24: VALIDO | Q24: Otros servicios | R24: 24
A25: FX26-000020 | B25: 14/08/2026 | C25: 14/08/2026 | D25: Proveedor Ficticio X 193, S.L. | E25: Equipamiento tecnologico | servicio ficticio 0020 | G25: SIN REFERENCIA PO | H25: 8851.6 | I25: 1858.84 | J25: 10710.44 | K25: 0 | L25: 10710.44 | M25: Vencido | O25: NO INFORMADO | P25: VALIDO | Q25: Otros servicios | R25: 25
A26: FX26-000021 | B26: 17/07/2026 | C26: 17/07/2026 | D26: Proveedor Ficticio X 235, S.L. | E26: Equipamiento tecnologico | servicio ficticio 0021 | G26: SIN REFERENCIA PO | H26: 7306.35 | I26: 1534.33 | J26: 8840.68 | K26: 0 | L26: 8840.68 | M26: Vencido | O26: NO INFORMADO | P26: VALIDO | Q26: Otros servicios | R26: 26
A27: FX26-000022 | B27: 03/07/2026 | C27: 03/07/2026 | D27: Proveedor Ficticio X 026, S.L. | E27: Asesoria operativa | servicio ficticio 0022 | G27: SIN REFERENCIA PO | H27: 5629.55 | I27: 1182.21 | J27: 6811.76 | K27: 0 | L27: 6811.76 | M27: Vencido | N27: XPR26-01689 | Proyecto demostracion 01689 | O27: VALIDO | P27: VALIDO | Q27: Transportes | R27: 27
A28: FX26-000023 | B28: 25/07/2026 | C28: 25/07/2026 | D28: Proveedor Ficticio X 021, S.L. | E28: Material de oficina | servicio ficticio 0023 | G28: SIN REFERENCIA PO | H28: 9182.29 | I28: 1928.28 | J28: 11110.57 | K28: 11110.57 | L28: 0 | M28: Pagado | N28: XPR26-01043 | Proyecto demostracion 01043 | O28: VALIDO | P28: VALIDO | Q28: Servicios profesionales independientes | R28: 28
A29: FX26-000024 | B29: 22/05/2026 | C29: 22/05/2026 | D29: Proveedor Ficticio X 123, S.L. | E29: Mantenimiento informatico | servicio ficticio 0024 | G29: SIN REFERENCIA PO | H29: 6889.34 | I29: 1446.76 | J29: 8336.1 | K29: 0 | L29: 8336.1 | M29: Vencido | O29: NO INFORMADO | P29: VALIDO | Q29: Arrendamientos y canones | R29: 29
A30: FX26-000025 | B30: 31/08/2026 | C30: 31/08/2026 | D30: Proveedor Ficticio X 189, S.L. | E30: Mantenimiento informatico | servicio ficticio 0025 | G30: SIN REFERENCIA PO | H30: 12602.69 | I30: 2646.56 | J30: 15249.25 | K30: 15249.25 | L30: 0 | M30: Pagado | N30: XPR26-03492 | Proyecto demostracion 03492 | O30: VALIDO | P30: VALIDO | Q30: Arrendamientos y canones | R30: 30
A31: FX26-000026 | B31: 28/09/2026 | C31: 28/09/2026 | D31: Proveedor Ficticio X 139, S.L. | E31: Licencias de software | servicio ficticio 0026 | G31: SIN REFERENCIA PO | H31: 10216.13 | I31: 0 | J31: 10216.13 | K31: 10216.13 | L31: 0 | M31: Pagado | N31: XPR26-03582 | Proyecto demostracion 03582 | O31: VALIDO | P31: VALIDO | Q31: Subcontractors | R31: 31
A32: FX26-000027 | B32: 07/08/2026 | C32: 07/08/2026 | D32: Proveedor Ficticio X 036, S.L. | E32: O2690235 | Subcontratacion de proyectos | ejemplo ficticio | F32: O2690235 | G32: VINCULADA | H32: 9588.06 | I32: 0 | J32: 9588.06 | K32: 0 | L32: 9588.06 | M32: Vencido | N32: XPR26-01110 | Proyecto demostracion 01110 | O32: VALIDO | P32: VALIDO | Q32: Publicidad, propaganda y relaciones publicas | R32: 32
A33: FX26-000028 | B33: 27/07/2026 | C33: 27/07/2026 | D33: Proveedor Ficticio X 234, S.L. | E33: Asistencia tecnica | servicio ficticio 0028 | G33: SIN REFERENCIA PO | H33: 11076.17 | I33: 1107.62 | J33: 12183.79 | K33: 12183.79 | L33: 0 | M33: Pagado | O33: NO INFORMADO | P33: VALIDO | Q33: Material de oficina | R33: 33
A34: FX26-000029 | B34: 31/08/2026 | C34: 31/08/2026 | D34: Proveedor Ficticio X 226, S.L. | E34: Subcontratacion de proyectos | servicio ficticio 0029 | G34: SIN REFERENCIA PO | H34: 14153.31 | I34: 2972.2 | J34: 17125.51 | K34: 17125.51 | L34: 0 | M34: Pagado | O34: NO INFORMADO | P34: VALIDO | Q34: Publicidad, propaganda y relaciones publicas | R34: 34
A35: FX26-000030 | B35: 17/01/2026 | C35: 17/01/2026 | D35: Proveedor Ficticio X 167, S.L. | E35: Produccion de contenido | servicio ficticio 0030 | G35: SIN REFERENCIA PO | H35: 8523.51 | I35: 0 | J35: 8523.51 | K35: 8523.51 | L35: 0 | M35: Pagado | N35: XPR26-00039 | Proyecto demostracion 00039 | O35: VALIDO | P35: VALIDO | Q35: Reparaciones y conservacion | R35: 35
A36: FX26-000031 | B36: 10/01/2026 | C36: 10/01/2026 | D36: Proveedor Ficticio X 031, S.L. | E36: Material de oficina | servicio ficticio 0031 | G36: SIN REFERENCIA PO | H36: 10316.08 | I36: 2166.38 | J36: 12482.46 | K36: 12482.46 | L36: 0 | M36: Pagado | O36: NO INFORMADO | P36: VALIDO | Q36: Servicios profesionales independientes | R36: 36
A37: FX26-000032 | B37: 05/06/2026 | C37: 05/06/2026 | D37: Proveedor Ficticio X 173, S.L. | E37: Produccion de contenido | servicio ficticio 0032 | G37: SIN REFERENCIA PO | H37: 2694.98 | I37: 565.95 | J37: 3260.93 | K37: 3260.93 | L37: 0 | M37: Pagado | O37: NO INFORMADO | P37: VALIDO | Q37: Reparaciones y conservacion | R37: 37
A38: FX26-000033 | B38: 11/02/2026 | C38: 11/02/2026 | D38: Proveedor Ficticio X 034, S.L. | E38: Produccion audiovisual | servicio ficticio 0033 | G38: SIN REFERENCIA PO | H38: 11577.84 | I38: 2431.35 | J38: 14009.19 | K38: 14009.19 | L38: 0 | M38: Pagado | O38: NO INFORMADO | P38: VALIDO | Q38: Otros servicios | R38: 38
A39: FX26-000034 | B39: 19/06/2026 | C39: 19/06/2026 | D39: Proveedor Ficticio X 203, S.L. | E39: Mantenimiento informatico | servicio ficticio 0034 | G39: SIN REFERENCIA PO | H39: 33.27 | I39: 6.99 | J39: 40.26 | K39: 0 | L39: 40.26 | M39: Vencido | N39: XPR26-02580 | Proyecto demostracion 02580 | O39: VALIDO | P39: VALIDO | Q39: Arrendamientos y canones | R39: 39
A40: FX26-000035 | B40: 02/04/2026 | C40: 02/04/2026 | D40: Proveedor Ficticio X 224, S.L. | E40: Produccion audiovisual | servicio ficticio 0035 | G40: SIN REFERENCIA PO | H40: 6787.48 | I40: 0 | J40: 6787.48 | K40: 0 | L40: 6787.48 | M40: Vencido | N40: XPR26-01827 | Proyecto demostracion 01827 | O40: VALIDO | P40: VALIDO | Q40: Otros servicios | R40: 40
A41: FX26-000036 | B41: 11/05/2026 | C41: 11/05/2026 | D41: Proveedor Ficticio X 135, S.L. | E41: Asesoria operativa | servicio ficticio 0036 | G41: SIN REFERENCIA PO | H41: 10323.09 | I41: 2167.85 | J41: 12490.94 | K41: 0 | L41: 12490.94 | M41: Vencido | N41: XPR26-03887 | Proyecto demostracion 03887 | O41: VALIDO | P41: VALIDO | Q41: Transportes | R41: 41
A42: FX26-000037 | B42: 18/07/2026 | C42: 18/07/2026 | D42: Proveedor Ficticio X 259, S.L. | E42: Campana de marketing | servicio ficticio 0037 | G42: SIN REFERENCIA PO | H42: 12712.81 | I42: 2669.69 | J42: 15382.5 | K42: 7547.47 | L42: 7835.03 | M42: Vencido | O42: NO INFORMADO | P42: VALIDO | Q42: Material de oficina | R42: 42
A43: FX26-000038 | B43: 28/04/2026 | C43: 28/04/2026 | D43: Proveedor Ficticio X 240, S.L. | E43: Campana de marketing | servicio ficticio 0038 | G43: SIN REFERENCIA PO | H43: 10995.77 | I43: 2309.11 | J43: 13304.88 | K43: 0 | L43: 13304.88 | M43: Vencido | O43: NO INFORMADO | P43: VALIDO | Q43: Material de oficina | R43: 43
A44: FX26-000039 | B44: 22/05/2026 | C44: 22/05/2026 | D44: Proveedor Ficticio X 088, S.L. | E44: O2690280 | Equipamiento tecnologico | ejemplo ficticio | F44: O2690280 | G44: VINCULADA | H44: 3705.33 | I44: 778.12 | J44: 4483.45 | K44: 4483.45 | L44: 0 | M44: Pagado | O44: NO INFORMADO | P44: VALIDO | Q44: Otros servicios | R44: 44
A45: FX26-000040 | B45: 10/02/2026 | C45: 10/02/2026 | D45: Proveedor Ficticio X 186, S.L. | E45: Mantenimiento informatico | servicio ficticio 0040 | G45: SIN REFERENCIA PO | H45: 12142.88 | I45: 0 | J45: 12142.88 | K45: 12142.88 | L45: 0 | M45: Pagado | O45: NO INFORMADO | P45: VALIDO | Q45: Arrendamientos y canones | R45: 45
A46: FX26-000041 | B46: 11/07/2026 | C46: 11/07/2026 | D46: Proveedor Ficticio X 076, S.L. | E46: Produccion audiovisual | servicio ficticio 0041 | G46: SIN REFERENCIA PO | H46: 4797.47 | I46: 1007.47 | J46: 5804.94 | K46: 0 | L46: 5804.94 | M46: Vencido | N46: XPR26-01281 | Proyecto demostracion 01281 | O46: VALIDO | P46: VALIDO | Q46: Otros servicios | R46: 46
A47: FX26-000042 | B47: 07/05/2026 | C47: 07/05/2026 | D47: Proveedor Ficticio X 176, S.L. | E47: Produccion de contenido | servicio ficticio 0042 | G47: SIN REFERENCIA PO | H47: 10406.99 | I47: 2185.47 | J47: 12592.46 | K47: 12592.46 | L47: 0 | M47: Pagado | N47: XPR26-03880 | Proyecto demostracion 03880 | O47: VALIDO | P47: VALIDO | Q47: Reparaciones y conservacion | R47: 47
A48: FX26-000043 | B48: 11/06/2026 | C48: 11/06/2026 | D48: Proveedor Ficticio X 217, S.L. | E48: Subcontratacion de proyectos | servicio ficticio 0043 | G48: SIN REFERENCIA PO | H48: 12836.87 | I48: 2695.74 | J48: 15532.61 | K48: 0 | L48: 15532.61 | M48: Vencido | N48: XPR26-00086 | Proyecto demostracion 00086 | O48: VALIDO | P48: VALIDO | Q48: Publicidad, propaganda y relaciones publicas | R48: 48
A49: FX26-000044 | B49: 23/02/2026 | C49: 23/02/2026 | D49: Proveedor Ficticio X 218, S.L. | E49: Material de oficina | servicio ficticio 0044 | G49: SIN REFERENCIA PO | H49: 10913.31 | I49: 2291.8 | J49: 13205.11 | K49: 0 | L49: 13205.11 | M49: Vencido | O49: NO INFORMADO | P49: VALIDO | Q49: Servicios profesionales independientes | R49: 49
A50: FX26-000045 | B50: 27/05/2026 | C50: 27/05/2026 | D50: Proveedor Ficticio X 124, S.L. | E50: Asesoria operativa | servicio ficticio 0045 | G50: SIN REFERENCIA PO | H50: 751.46 | I50: 157.81 | J50: 909.27 | K50: 0 | L50: 909.27 | M50: Vencido | O50: NO INFORMADO | P50: VALIDO | Q50: Transportes | R50: 50
A51: FX26-000046 | B51: 04/08/2026 | C51: 04/08/2026 | D51: Proveedor Ficticio X 042, S.L. | E51: O2690001 | Asesoria operativa | ejemplo ficticio | F51: O2690001 | G51: VINCULADA | H51: 9952.69 | I51: 2090.06 | J51: 12042.75 | K51: 12042.75 | L51: 0 | M51: Pagado | O51: NO INFORMADO | P51: VALIDO | Q51: Transportes | R51: 51
A52: FX26-000047 | B52: 15/03/2026 | C52: 15/03/2026 | D52: Proveedor Ficticio X 161, S.L. | E52: Servicios profesionales | servicio ficticio 0047 | G52: SIN REFERENCIA PO | H52: 12254.59 | I52: 0 | J52: 10416.4 | K52: 10416.4 | L52: 0 | M52: Pagado | O52: NO INFORMADO | P52: VALIDO | Q52: Equipos para procesos de informacion | R52: 52
A53: FX26-000048 | B53: 28/07/2026 | C53: 28/07/2026 | D53: Proveedor Ficticio X 063, S.L. | E53: Material de oficina | servicio ficticio 0048 | G53: SIN REFERENCIA PO | H53: 34374.5 | I53: 0 | J53: 34374.5 | K53: 34374.5 | L53: 0 | M53: Pagado | O53: NO INFORMADO | P53: VALIDO | Q53: Servicios profesionales independientes | R53: 53
A54: FX26-000049 | B54: 03/03/2026 | C54: 03/03/2026 | D54: Proveedor Ficticio X 169, S.L. | E54: Produccion de contenido | servicio ficticio 0049 | G54: SIN REFERENCIA PO | H54: 683.11 | I54: 143.45 | J54: 826.56 | K54: 826.56 | L54: 0 | M54: Pagado | N54: XPR26-01546 | Proyecto demostracion 01546 | O54: VALIDO | P54: VALIDO | Q54: Reparaciones y conservacion | R54: 54
A55: FX26-000050 | B55: 05/03/2026 | C55: 05/03/2026 | D55: Proveedor Ficticio X 238, S.L. | E55: Subcontratacion de proyectos | servicio ficticio 0050 | G55: SIN REFERENCIA PO | H55: 609.08 | I55: 60.91 | J55: 669.99 | K55: 669.99 | L55: 0 | M55: Pagado | N55: XPR26-03245 | Proyecto demostracion 03245 | O55: VALIDO | P55: VALIDO | Q55: Publicidad, propaganda y relaciones publicas | R55: 55
A56: FX26-000051 | B56: 15/03/2026 | C56: 15/03/2026 | D56: Proveedor Ficticio X 170, S.L. | E56: Licencias de software | servicio ficticio 0051 | G56: SIN REFERENCIA PO | H56: 10481.14 | I56: 2201.04 | J56: 12682.18 | K56: 0 | L56: 12682.18 | M56: Vencido | N56: XPR26-03792 | Proyecto demostracion 03792 | O56: VALIDO | P56: VALIDO | Q56: Subcontractors | R56: 56
A57: FX26-000052 | B57: 01/02/2026 | C57: 01/02/2026 | D57: Proveedor Ficticio X 027, S.L. | E57: Equipamiento tecnologico | servicio ficticio 0052 | G57: SIN REFERENCIA PO | H57: 5083.48 | I57: 1067.53 | J57: 6151.01 | K57: 6151.01 | L57: 0 | M57: Pagado | N57: XPR26-03880 | Proyecto demostracion 03880 | O57: VALIDO | P57: VALIDO | Q57: Otros servicios | R57: 57
A58: FX26-000053 | B58: 15/10/2026 | C58: 15/10/2026 | D58: Proveedor Ficticio X 018, S.L. | E58: Produccion de contenido | servicio ficticio 0053 | G58: SIN REFERENCIA PO | H58: 3884.06 | I58: 815.65 | J58: 4699.71 | K58: 0 | L58: 4699.71 | M58: Pendiente | O58: NO INFORMADO | P58: VALIDO | Q58: Reparaciones y conservacion | R58: 58
A59: FX26-000054 | B59: 04/06/2026 | C59: 04/06/2026 | D59: Proveedor Ficticio X 112, S.L. | E59: O2690153 | Produccion audiovisual | ejemplo ficticio | F59: O2690153 | G59: VINCULADA | H59: 10388.56 | I59: 2181.6 | J59: 12570.16 | K59: 12570.16 | L59: 0 | M59: Pagado | N59: XPR26-01893 | Proyecto demostracion 01893 | O59: VALIDO | P59: VALIDO | Q59: Otros servicios | R59: 59
A60: FX26-000055 | B60: 20/03/2026 | C60: 20/03/2026 | D60: Proveedor Ficticio X 178, S.L. | E60: Servicios logisticos | servicio ficticio 0055 | G60: SIN REFERENCIA PO | H60: 4947.09 | I60: 1038.89 | J60: 5985.98 | K60: 4362.92 | L60: 1623.06 | M60: Vencido | N60: XPR26-00930 | Proyecto demostracion 00930 | O60: VALIDO | P60: VALIDO | Q60: Equipos para procesos de informacion | R60: 60
A61: FX26-000056 | B61: 09/09/2026 | C61: 09/09/2026 | D61: Proveedor Ficticio X 222, S.L. | E61: Produccion audiovisual | servicio ficticio 0056 | G61: SIN REFERENCIA PO | H61: 1175.33 | I61: 246.82 | J61: 1422.15 | K61: 0 | L61: 1422.15 | M61: Vencido | O61: NO INFORMADO | P61: VALIDO | Q61: Otros servicios | R61: 61
A62: FX26-000057 | B62: 15/03/2026 | C62: 15/03/2026 | D62: Proveedor Ficticio X 059, S.L. | E62: O2690395 | Alquiler de equipos | ejemplo ficticio | F62: O2690395 | G62: VINCULADA | H62: 8668.39 | I62: 1820.36 | J62: 10488.75 | K62: 10488.75 | L62: 0 | M62: Pagado | N62: XPR26-02096 | Proyecto demostracion 02096 | O62: VALIDO | P62: VALIDO | Q62: Subcontractors | R62: 62
A63: FX26-000058 | B63: 01/08/2026 | C63: 01/08/2026 | D63: Proveedor Ficticio X 051, S.L. | E63: Servicios logisticos | servicio ficticio 0058 | G63: SIN REFERENCIA PO | H63: 3177.62 | I63: 667.3 | J63: 3844.92 | K63: 1169.65 | L63: 2675.27 | M63: Parcialmente | N63: XPR26-01037 | Proyecto demostracion 01037 | O63: VALIDO | P63: VALIDO | Q63: Equipos para procesos de informacion | R63: 63
A64: FX26-000059 | B64: 23/08/2026 | C64: 23/08/2026 | D64: Proveedor Ficticio X 081, S.L. | E64: Alquiler de equipos | servicio ficticio 0059 | G64: SIN REFERENCIA PO | H64: 6201.39 | I64: 1302.29 | J64: 7503.68 | K64: 7503.68 | L64: 0 | M64: Pagado | O64: NO INFORMADO | P64: VALIDO | Q64: Subcontractors | R64: 64
A65: FX26-000060 | B65: 01/02/2026 | C65: 01/02/2026 | D65: Proveedor Ficticio X 174, S.L. | E65: Asesoria operativa | servicio ficticio 0060 | G65: SIN REFERENCIA PO | H65: 11812.89 | I65: 2480.71 | J65: 14293.6 | K65: 14293.6 | L65: 0 | M65: Pagado | O65: NO INFORMADO | P65: VALIDO | Q65: Transportes | R65: 65
A66: FX26-000061 | B66: 16/07/2026 | C66: 16/07/2026 | D66: Proveedor Ficticio X 082, S.L. | E66: Servicios profesionales | servicio ficticio 0061 | G66: SIN REFERENCIA PO | H66: 1163.02 | I66: 244.23 | J66: 1407.25 | K66: 1407.25 | L66: 0 | M66: Pagado | N66: XPR26-00324 | Proyecto demostracion 00324 | O66: VALIDO | P66: VALIDO | Q66: Equipos para procesos de informacion | R66: 66
A67: FX26-000062 | B67: 26/01/2026 | C67: 26/01/2026 | D67: Proveedor Ficticio X 069, S.L. | E67: Mantenimiento informatico | servicio ficticio 0062 | G67: SIN REFERENCIA PO | H67: 7423.91 | I67: 0 | J67: 7423.91 | K67: 0 | L67: 7423.91 | M67: Vencido | O67: NO INFORMADO | P67: VALIDO | Q67: Arrendamientos y canones | R67: 67
A68: FX26-000063 | B68: 29/04/2026 | C68: 29/04/2026 | D68: Proveedor Ficticio X 173, S.L. | E68: Equipamiento tecnologico | servicio ficticio 0063 | G68: SIN REFERENCIA PO | H68: 4582.9 | I68: 962.41 | J68: 5545.31 | K68: 5545.31 | L68: 0 | M68: Pagado | O68: NO INFORMADO | P68: VALIDO | Q68: Otros servicios | R68: 68
A69: FX26-000064 | B69: 13/04/2026 | C69: 13/04/2026 | D69: Proveedor Ficticio X 084, S.L. | E69: Material de oficina | servicio ficticio 0064 | G69: SIN REFERENCIA PO | H69: 7537.59 | I69: 1582.89 | J69: 9120.48 | K69: 0 | L69: 9120.48 | M69: Vencido | N69: XPR26-01117 | Proyecto demostracion 01117 | O69: VALIDO | P69: VALIDO | Q69: Servicios profesionales independientes | R69: 69
A70: FX26-000065 | B70: 16/05/2026 | C70: 16/05/2026 | D70: Proveedor Ficticio X 239, S.L. | E70: Licencias de software | servicio ficticio 0065 | G70: SIN REFERENCIA PO | H70: 14127.52 | I70: 2966.78 | J70: 17094.3 | K70: 8186 | L70: 8908.3 | M70: Vencido | O70: NO INFORMADO | P70: VALIDO | Q70: Subcontractors | R70: 70
A71: FX26-000066 | B71: 06/01/2026 | C71: 06/01/2026 | D71: Proveedor Ficticio X 171, S.L. | E71: O2690385 | Mantenimiento informatico | ejemplo ficticio | F71: O2690385 | G71: VINCULADA | H71: 22994.88 | I71: 4828.92 | J71: 27823.8 | K71: 27823.8 | L71: 0 | M71: Pagado | N71: XPR26-00166 | Proyecto demostracion 00166 | O71: VALIDO | P71: VALIDO | Q71: Arrendamientos y canones | R71: 71
A72: FX26-000067 | B72: 09/05/2026 | C72: 09/05/2026 | D72: Proveedor Ficticio X 184, S.L. | E72: Equipamiento tecnologico | servicio ficticio 0067 | G72: SIN REFERENCIA PO | H72: 9329.2 | I72: 1959.13 | J72: 11288.33 | K72: 0 | L72: 11288.33 | M72: Vencido | O72: NO INFORMADO | P72: VALIDO | Q72: Otros servicios | R72: 72
A73: FX26-000068 | B73: 01/02/2026 | C73: 01/02/2026 | D73: Proveedor Ficticio X 237, S.L. | E73: Subcontratacion de proyectos | servicio ficticio 0068 | G73: SIN REFERENCIA PO | H73: 3749.88 | I73: 787.47 | J73: 4537.35 | K73: 0 | L73: 4537.35 | M73: Vencido | O73: NO INFORMADO | P73: VALIDO | Q73: Publicidad, propaganda y relaciones publicas | R73: 73
A74: FX26-000069 | B74: 20/10/2026 | C74: 20/10/2026 | D74: Proveedor Ficticio X 166, S.L. | E74: O2690232 | Servicios profesionales | ejemplo ficticio | F74: O2690232 | G74: VINCULADA | H74: 20565.05 | I74: 4318.66 | J74: 24883.71 | K74: 0 | L74: 24883.71 | M74: Pendiente | N74: XPR26-02632 | Proyecto demostracion 02632 | O74: VALIDO | P74: VALIDO | Q74: Equipos para procesos de informacion | R74: 74
A75: FX26-000070 | B75: 11/06/2026 | C75: 11/06/2026 | D75: Proveedor Ficticio X 152, S.L. | E75: Asesoria operativa | servicio ficticio 0070 | G75: SIN REFERENCIA PO | H75: 2356.22 | I75: 494.81 | J75: 2851.03 | K75: 2851.03 | L75: 0 | M75: Pagado | O75: NO INFORMADO | P75: VALIDO | Q75: Transportes | R75: 75
A76: FX26-000071 | B76: 18/02/2026 | C76: 18/02/2026 | D76: Proveedor Ficticio X 153, S.L. | E76: Produccion de contenido | servicio ficticio 0071 | G76: SIN REFERENCIA PO | H76: 6888.78 | I76: 0 | J76: 6888.78 | K76: 0 | L76: 6888.78 | M76: Vencido | N76: XPR26-01211 | Proyecto demostracion 01211 | O76: VALIDO | P76: VALIDO | Q76: Reparaciones y conservacion | R76: 76
A77: FX26-000072 | B77: 22/04/2026 | C77: 22/04/2026 | D77: Proveedor Ficticio X 185, S.L. | E77: Servicios logisticos | servicio ficticio 0072 | G77: SIN REFERENCIA PO | H77: 9821.18 | I77: 2062.45 | J77: 11883.63 | K77: 11883.63 | L77: 0 | M77: Pagado | N77: XPR26-03653 | Proyecto demostracion 03653 | O77: VALIDO | P77: VALIDO | Q77: Equipos para procesos de informacion | R77: 77
A78: FX26-000073 | B78: 30/08/2026 | C78: 30/08/2026 | D78: Proveedor Ficticio X 231, S.L. | E78: Equipamiento tecnologico | servicio ficticio 0073 | G78: SIN REFERENCIA PO | H78: 6156.52 | I78: 1292.87 | J78: 7449.39 | K78: 0 | L78: 7449.39 | M78: Vencido | O78: NO INFORMADO | P78: VALIDO | Q78: Otros servicios | R78: 78
A79: FX26-000074 | B79: 26/07/2026 | C79: 26/07/2026 | D79: Proveedor Ficticio X 032, S.L. | E79: Servicios logisticos | servicio ficticio 0074 | G79: SIN REFERENCIA PO | H79: 4559.8 | I79: 0 | J79: 4559.8 | K79: 4559.8 | L79: 0 | M79: Pagado | O79: NO INFORMADO | P79: VALIDO | Q79: Equipos para procesos de informacion | R79: 79
A80: FX26-000075 | B80: 11/07/2026 | C80: 11/07/2026 | D80: Proveedor Ficticio X 023, S.L. | E80: Subcontratacion de proyectos | servicio ficticio 0075 | G80: SIN REFERENCIA PO | H80: 6431.9 | I80: 1350.7 | J80: 7782.6 | K80: 7782.6 | L80: 0 | M80: Pagado | N80: XPR26-03460 | Proyecto demostracion 03460 | O80: VALIDO | P80: VALIDO | Q80: Publicidad, propaganda y relaciones publicas | R80: 80
A81: FX26-000076 | B81: 21/01/2026 | C81: 21/01/2026 | D81: Proveedor Ficticio X 045, S.L. | E81: Subcontratacion de proyectos | servicio ficticio 0076 | G81: SIN REFERENCIA PO | H81: 3912.63 | I81: 391.26 | J81: 4303.89 | K81: 4303.89 | L81: 0 | M81: Pagado | O81: NO INFORMADO | P81: VALIDO | Q81: Publicidad, propaganda y relaciones publicas | R81: 81
A82: FX26-000077 | B82: 14/04/2026 | C82: 14/04/2026 | D82: Proveedor Ficticio X 141, S.L. | E82: Campana de marketing | servicio ficticio 0077 | G82: SIN REFERENCIA PO | H82: 9817.34 | I82: 0 | J82: 9817.34 | K82: 0 | L82: 9817.34 | M82: Vencido | N82: XPR26-00557 | Proyecto demostracion 00557 | O82: VALIDO | P82: VALIDO | Q82: Material de oficina | R82: 82
A83: FX26-000078 | B83: 06/03/2026 | C83: 06/03/2026 | D83: Proveedor Ficticio X 125, S.L. | E83: Subcontratacion de proyectos | servicio ficticio 0078 | G83: SIN REFERENCIA PO | H83: 6406.57 | I83: 0 | J83: 6406.57 | K83: 0 | L83: 6406.57 | M83: Vencido | N83: XPR26-02296 | Proyecto demostracion 02296 | O83: VALIDO | P83: VALIDO | Q83: Publicidad, propaganda y relaciones publicas | R83: 83
A84: FX26-000079 | B84: 29/01/2026 | C84: 29/01/2026 | D84: Proveedor Ficticio X 016, S.L. | E84: Servicios profesionales | servicio ficticio 0079 | G84: SIN REFERENCIA PO | H84: 12487.92 | I84: 0 | J84: 12487.92 | K84: 12487.92 | L84: 0 | M84: Pagado | N84: XPR26-00318 | Proyecto demostracion 00318 | O84: VALIDO | P84: VALIDO | Q84: Equipos para procesos de informacion | R84: 84
A85: FX26-000080 | B85: 04/03/2026 | C85: 04/03/2026 | D85: Proveedor Ficticio X 128, S.L. | E85: Produccion audiovisual | servicio ficticio 0080 | G85: SIN REFERENCIA PO | H85: 4829.18 | I85: 1014.13 | J85: 5843.31 | K85: 0 | L85: 5843.31 | M85: Vencido | O85: NO INFORMADO | P85: VALIDO | Q85: Otros servicios | R85: 85
A86: FX26-000081 | B86: 07/05/2026 | C86: 07/05/2026 | D86: Proveedor Ficticio X 102, S.L. | E86: Equipamiento tecnologico | servicio ficticio 0081 | G86: SIN REFERENCIA PO | H86: 3015.85 | I86: 0 | J86: 3015.85 | K86: 3015.85 | L86: 0 | M86: Pagado | O86: NO INFORMADO | P86: VALIDO | Q86: Otros servicios | R86: 86
A87: FX26-000082 | B87: 12/01/2026 | C87: 12/01/2026 | D87: Proveedor Ficticio X 004, S.L. | E87: O2690298 | Mantenimiento informatico | ejemplo ficticio | F87: O2690298 | G87: VINCULADA | H87: 75680.59 | I87: 15892.92 | J87: 91573.51 | K87: 0 | L87: 91573.51 | M87: Vencido | N87: XPR26-01869 | Proyecto demostracion 01869 | O87: VALIDO | P87: VALIDO | Q87: Arrendamientos y canones | R87: 87
A88: FX26-000083 | B88: 15/07/2026 | C88: 15/07/2026 | D88: Proveedor Ficticio X 026, S.L. | E88: Servicios de diseno | servicio ficticio 0083 | G88: SIN REFERENCIA PO | H88: 4099.4 | I88: 860.87 | J88: 4960.27 | K88: 4960.27 | L88: 0 | M88: Pagado | N88: XPR26-00741 | Proyecto demostracion 00741 | O88: VALIDO | P88: VALIDO | Q88: TRABAJOS REALIZADOS POR OTRAS EMPRESAS | R88: 88
A89: FX26-000084 | B89: 16/08/2026 | C89: 16/08/2026 | D89: Proveedor Ficticio X 131, S.L. | E89: Subcontratacion de proyectos | servicio ficticio 0084 | G89: SIN REFERENCIA PO | H89: 11158.56 | I89: 2343.3 | J89: 13501.86 | K89: 13501.86 | L89: 0 | M89: Pagado | N89: XPR26-02892 | Proyecto demostracion 02892 | O89: VALIDO | P89: VALIDO | Q89: Publicidad, propaganda y relaciones publicas | R89: 89
A90: FX26-000085 | B90: 24/03/2026 | C90: 24/03/2026 | D90: Proveedor Ficticio X 071, S.L. | E90: Licencias de software | servicio ficticio 0085 | G90: SIN REFERENCIA PO | H90: 13523.43 | I90: 2839.92 | J90: 16363.35 | K90: 16363.35 | L90: 0 | M90: Pagado | O90: NO INFORMADO | P90: VALIDO | Q90: Subcontractors | R90: 90
A91: FX26-000086 | B91: 10/09/2026 | C91: 10/09/2026 | D91: Proveedor Ficticio X 097, S.L. | E91: O2690097 | Asistencia tecnica | ejemplo ficticio | F91: O2690097 | G91: VINCULADA | H91: 6421.3 | I91: 642.13 | J91: 7063.43 | K91: 7063.43 | L91: 0 | M91: Pagado | O91: NO INFORMADO | P91: VALIDO | Q91: Material de oficina | R91: 91
A92: FX26-000087 | B92: 23/07/2026 | C92: 23/07/2026 | D92: Proveedor Ficticio X 176, S.L. | E92: Asesoria operativa | servicio ficticio 0087 | G92: SIN REFERENCIA PO | H92: 6485.12 | I92: 1361.88 | J92: 7847 | K92: 0 | L92: 7847 | M92: Vencido | N92: XPR26-01827 | Proyecto demostracion 01827 | O92: VALIDO | P92: VALIDO | Q92: Transportes | R92: 92
A93: FX26-000088 | B93: 07/02/2026 | C93: 07/02/2026 | D93: Proveedor Ficticio X 141, S.L. | E93: Campana de marketing | servicio ficticio 0088 | G93: SIN REFERENCIA PO | H93: 9134.8 | I93: 1918.31 | J93: 11053.11 | K93: 0 | L93: 11053.11 | M93: Vencido | N93: XPR26-00464 | Proyecto demostracion 00464 | O93: VALIDO | P93: VALIDO | Q93: Material de oficina | R93: 93
A94: FX26-000071 | B94: 18/02/2026 | C94: 18/02/2026 | D94: Proveedor Ficticio X 153, S.L. | E94: Produccion de contenido | servicio ficticio 0089 | G94: SIN REFERENCIA PO | H94: 6888.78 | I94: 0 | J94: 6888.78 | K94: 0 | L94: 6888.78 | M94: Pendiente | N94: XPR26-01211 | Proyecto demostracion 01211 | O94: VALIDO | P94: VALIDO | Q94: Reparaciones y conservacion | R94: 94
A95: FX26-000090 | B95: 27/06/2026 | C95: 27/06/2026 | D95: Proveedor Ficticio X 149, S.L. | E95: Asistencia tecnica | servicio ficticio 0090 | G95: SIN REFERENCIA PO | H95: 1793.28 | I95: 0 | J95: 1793.28 | K95: 1793.28 | L95: 0 | M95: Pagado | N95: XPR26-00747 | Proyecto demostracion 00747 | O95: VALIDO | P95: VALIDO | Q95: Material de oficina | R95: 95
A96: FX26-000091 | B96: 16/05/2026 | C96: 16/05/2026 | D96: Proveedor Ficticio X 086, S.L. | E96: Asesoria operativa | servicio ficticio 0091 | G96: SIN REFERENCIA PO | H96: 870 | I96: 0 | J96: 870 | K96: 0 | L96: 870 | M96: Vencido | O96: NO INFORMADO | P96: VALIDO | Q96: Transportes | R96: 96
A97: FX26-000092 | B97: 13/10/2026 | C97: 13/10/2026 | D97: Proveedor Ficticio X 039, S.L. | E97: Equipamiento tecnologico | servicio ficticio 0092 | G97: SIN REFERENCIA PO | H97: 9446.9 | I97: 1983.85 | J97: 11430.75 | K97: 0 | L97: 11430.75 | M97: Pendiente | O97: NO INFORMADO | P97: VALIDO | Q97: Otros servicios | R97: 97
A98: FX26-000093 | B98: 17/06/2026 | C98: 17/06/2026 | D98: Proveedor Ficticio X 156, S.L. | E98: Mantenimiento informatico | servicio ficticio 0093 | G98: SIN REFERENCIA PO | H98: 7934.05 | I98: 1666.15 | J98: 9600.2 | K98: 9600.2 | L98: 0 | M98: Pagado | N98: XPR26-03880 | Proyecto demostracion 03880 | O98: VALIDO | P98: VALIDO | Q98: Arrendamientos y canones | R98: 98
A99: FX26-000094 | B99: 19/04/2026 | C99: 19/04/2026 | D99: Proveedor Ficticio X 253, S.L. | E99: Material de oficina | servicio ficticio 0094 | G99: SIN REFERENCIA PO | H99: 11706.68 | I99: 2458.4 | J99: 14165.08 | K99: 14165.08 | L99: 0 | M99: Pagado | O99: NO INFORMADO | P99: VALIDO | Q99: Servicios profesionales independientes | R99: 99
A100: FX26-000095 | B100: 31/05/2026 | C100: 31/05/2026 | D100: Proveedor Ficticio X 173, S.L. | E100: Mantenimiento informatico | servicio ficticio 0095 | G100: SIN REFERENCIA PO | H100: 2466.09 | I100: 517.88 | J100: 2983.97 | K100: 0 | L100: 2983.97 | M100: Vencido | O100: NO INFORMADO | P100: VALIDO | Q100: Arrendamientos y canones | R100: 100
A101: FX26-000096 | B101: 31/08/2026 | C101: 31/08/2026 | D101: Proveedor Ficticio X 053, S.L. | E101: O2690267 | Asesoria operativa | ejemplo ficticio | F101: O2690267 | G101: VINCULADA | H101: 4915.44 | I101: 1032.24 | J101: 5947.68 | K101: 0 | L101: 5947.68 | M101: Pendiente | N101: XPR26-00795 | Proyecto demostracion 00795 | O101: VALIDO | P101: VALIDO | Q101: Transportes | R101: 101
A102: FX26-000097 | B102: 19/02/2026 | C102: 19/02/2026 | D102: Proveedor Ficticio X 165, S.L. | E102: Servicios de diseno | servicio ficticio 0097 | G102: SIN REFERENCIA PO | H102: 744.93 | I102: 0 | J102: 744.93 | K102: 0 | L102: 744.93 | M102: Vencido | O102: NO INFORMADO | P102: VALIDO | Q102: TRABAJOS REALIZADOS POR OTRAS EMPRESAS | R102: 102
...

Sheet 04_Pedidos
A1: UNIVERSO DE PEDIDOS
A3: Fuente completa de pedidos. La presencia de factura no sustituye evidencia de recepción ni autorización.
A5: PO | B5: Fecha | C5: Proveedor | D5: Descripción | E5: Subtotal € | F5: Total € | G5: Facturado ERP € | H5: Aprobación | I5: Estado | J5: Proyecto | K5: Val. proyecto | L5: Etiquetas | M5: Val. CECO | N5: Cuenta | O5: Nº facturas | P5: Vínculo | Q5: Fila origen
A6: O2690001 | B6: 19/07/2026 | C6: Proveedor Ficticio X 042, S.L. | D6: Asesoria operativa - operacion ficticia | E6: 22613.57 | F6: 27362.42 | G6: 29765.03 | H6: Aceptado | I6: Facturado | K6: NO INFORMADO | L6: #etiqueta_demo_sin_ceco | M6: NO INFORMADO | N6: Transportes | O6: 2 | P6: SOBRE PEDIDO | Q6: 6
A7: O2690002 | B7: 17/04/2026 | C7: Proveedor Ficticio X 140, S.L. | D7: Servicios logisticos - operacion ficticia | E7: 7894.52 | F7: 7894.52 | G7: 0 | H7: Aceptado | I7: Pendiente | J7: XPR26-00164 | Proyecto demostracion 00164 | K7: VALIDO | L7: #tecnologia_x214 #entorno_demo | M7: VALIDO | N7: Equipos para procesos de informacion | O7: 0 | P7: SIN FACTURA LOCALIZADA | Q7: 7
A8: O2690003 | B8: 07/09/2026 | C8: Proveedor Ficticio X 121, S.L. | D8: Servicios profesionales - operacion ficticia | E8: 7835.67 | F8: 9481.16 | G8: 0 | H8: Aceptado | I8: Pendiente | J8: XPR26-01546 | Proyecto demostracion 01546 | K8: VALIDO | L8: #comercial_x080 #entorno_demo | M8: VALIDO | N8: Equipos para procesos de informacion | O8: 0 | P8: SIN FACTURA LOCALIZADA | Q8: 8
A9: O2690004 | B9: 25/03/2026 | C9: Proveedor Ficticio X 004, S.L. | D9: Produccion audiovisual - operacion ficticia | E9: 23238.22 | F9: 28118.25 | G9: 28118.25 | H9: Aceptado | I9: Facturado | J9: XPR26-00086 | Proyecto demostracion 00086 | K9: VALIDO | L9: #tecnologia_x204 #entorno_demo | M9: VALIDO | N9: Otros servicios | O9: 3 | P9: CONCILIADO | Q9: 9
A10: O2690005 | B10: 05/09/2026 | C10: Proveedor Ficticio X 121, S.L. | D10: Traduccion y localizacion - operacion ficticia | E10: 23387.16 | F10: 28298.46 | G10: 0 | H10: Aceptado | I10: Pendiente | J10: XPR26-03638 | Proyecto demostracion 03638 | K10: VALIDO | L10: #creatividad_x142 #entorno_demo | M10: VALIDO | N10: TRABAJOS REALIZADOS POR OTRAS EMPRESAS | O10: 0 | P10: SIN FACTURA LOCALIZADA | Q10: 10
A11: O2690006 | B11: 11/07/2026 | C11: Proveedor Ficticio X 151, S.L. | D11: Servicios profesionales - operacion ficticia | E11: 50087.31 | F11: 60605.65 | G11: 0 | H11: Cancelado | I11: Pendiente | J11: XPR26-01049 | Proyecto demostracion 01049 | K11: VALIDO | L11: #creatividad_x232 #entorno_demo | M11: VALIDO | N11: Equipos para procesos de informacion | O11: 0 | P11: CANCELADO / SIN FACTURA | Q11: 11
A12: O2690007 | B12: 10/08/2026 | C12: Proveedor Ficticio X 006, S.L. | D12: Mantenimiento informatico - operacion ficticia | E12: 16761.22 | F12: 20281.08 | G12: 0 | H12: Aceptado | I12: Pendiente | K12: NO INFORMADO | L12: #produccion_x231 #entorno_demo | M12: VALIDO | N12: Arrendamientos y canones | O12: 0 | P12: SIN FACTURA LOCALIZADA | Q12: 12
A13: O2690008 | B13: 25/07/2026 | C13: Proveedor Ficticio X 079, S.L. | D13: Produccion audiovisual - operacion ficticia | E13: 12008.13 | F13: 14529.84 | G13: 0 | H13: Aceptado | I13: Pendiente | J13: XPR26-01278 | Proyecto demostracion 01278 | K13: VALIDO | L13: #creatividad_x252 #entorno_demo | M13: VALIDO | N13: Otros servicios | O13: 0 | P13: SIN FACTURA LOCALIZADA | Q13: 13
A14: O2690009 | B14: 29/07/2026 | C14: Proveedor Ficticio X 152, S.L. | D14: Traduccion y localizacion - operacion ficticia | E14: 312.25 | F14: 312.25 | G14: 312.25 | H14: Aceptado | I14: Facturado | K14: NO INFORMADO | L14: #consultoria_x119 #entorno_demo | M14: VALIDO | N14: TRABAJOS REALIZADOS POR OTRAS EMPRESAS | O14: 1 | P14: CONCILIADO | Q14: 14
A15: O2690010 | B15: 17/03/2026 | C15: Proveedor Ficticio X 032, S.L. | D15: Subcontratacion de proyectos - operacion ficticia | E15: 20270.29 | F15: 24527.05 | G15: 24527.05 | H15: Pendiente | I15: Facturado | J15: XPR26-02376 | Proyecto demostracion 02376 | K15: VALIDO | L15: #administracion_x246 #entorno_demo | M15: VALIDO | N15: Publicidad, propaganda y relaciones publicas | O15: 3 | P15: CONCILIADO | Q15: 15
A16: O2690011 | B16: 06/09/2026 | C16: Proveedor Ficticio X 138, S.L. | D16: Servicios profesionales - operacion ficticia | E16: 13057.68 | F16: 15799.79 | G16: 15799.8 | H16: Aceptado | I16: Facturado | K16: NO INFORMADO | L16: #finanzas_x247 #entorno_demo | M16: VALIDO | N16: Equipos para procesos de informacion | O16: 2 | P16: CONCILIADO | Q16: 16
A17: O2690012 | B17: 24/07/2026 | C17: Proveedor Ficticio X 090, S.L. | D17: Subcontratacion de proyectos - operacion ficticia | E17: 4937.37 | F17: 5974.22 | G17: 0 | H17: Aceptado | I17: Pendiente | J17: XPR26-02296 | Proyecto demostracion 02296 | K17: VALIDO | L17: #comercial_x080 #entorno_demo | M17: VALIDO | N17: Publicidad, propaganda y relaciones publicas | O17: 0 | P17: SIN FACTURA LOCALIZADA | Q17: 17
A18: O2690013 | B18: 23/03/2026 | C18: Proveedor Ficticio X 095, S.L. | D18: Alquiler de equipos - operacion ficticia | E18: 14145.04 | F18: 14145.04 | G18: 14145.04 | H18: Aceptado | I18: Facturado | J18: XPR26-00606 | Proyecto demostracion 00606 | K18: VALIDO | L18: #creatividad_x192 #entorno_demo | M18: VALIDO | N18: Subcontractors | O18: 1 | P18: CONCILIADO | Q18: 18
A19: O2690014 | B19: 05/05/2026 | C19: Proveedor Ficticio X 137, S.L. | D19: Servicios logisticos - operacion ficticia | E19: 13163.86 | F19: 15928.27 | G19: 15928.27 | H19: Aceptado | I19: Facturado | J19: XPR26-01348 | Proyecto demostracion 01348 | K19: VALIDO | L19: #creatividad_x192 #entorno_demo | M19: VALIDO | N19: Equipos para procesos de informacion | O19: 1 | P19: CONCILIADO | Q19: 19
A20: O2690015 | B20: 24/06/2026 | C20: Proveedor Ficticio X 123, S.L. | D20: Servicios de diseno - operacion ficticia | E20: 8627.58 | F20: 10439.37 | G20: 10439.37 | H20: Aceptado | I20: Facturado | K20: NO INFORMADO | L20: #creatividad_x042 #entorno_demo | M20: VALIDO | N20: TRABAJOS REALIZADOS POR OTRAS EMPRESAS | O20: 1 | P20: CONCILIADO | Q20: 20
A21: O2690016 | B21: 13/05/2026 | C21: Proveedor Ficticio X 022, S.L. | D21: Produccion audiovisual - operacion ficticia | E21: 79795.05 | F21: 96552.01 | G21: 96552.01 | H21: Aceptado | I21: Facturado | K21: NO INFORMADO | L21: #consultoria_x159 #entorno_demo | M21: VALIDO | N21: Otros servicios | O21: 1 | P21: CONCILIADO | Q21: 21
A22: O2690017 | B22: 17/08/2026 | C22: Proveedor Ficticio X 015, S.L. | D22: Mantenimiento informatico - operacion ficticia | E22: 10336.33 | F22: 11369.96 | G22: 5211.29 | H22: Aceptado | I22: Parcialmente | J22: XPR26-00396 | Proyecto demostracion 00396 | K22: VALIDO | L22: #creatividad_x032 #entorno_demo | M22: VALIDO | N22: Arrendamientos y canones | O22: 2 | P22: PARCIAL / DIFERENCIA | Q22: 22
A23: O2690018 | B23: 19/01/2026 | C23: Proveedor Ficticio X 041, S.L. | D23: Licencias de software - operacion ficticia | E23: 50116.93 | F23: 60641.49 | G23: 24764.57 | H23: Aceptado | I23: Parcialmente | J23: XPR26-03653 | Proyecto demostracion 03653 | K23: VALIDO | L23: #comercial_x040 #entorno_demo | M23: VALIDO | N23: Subcontractors | O23: 1 | P23: PARCIAL / DIFERENCIA | Q23: 23
A24: O2690019 | B24: 13/07/2026 | C24: Proveedor Ficticio X 020, S.L. | D24: Traduccion y localizacion - operacion ficticia | E24: 18737.32 | F24: 22672.16 | G24: 0 | H24: Aceptado | I24: Pendiente | K24: NO INFORMADO | L24: #consultoria_x009 #entorno_demo | M24: VALIDO | N24: TRABAJOS REALIZADOS POR OTRAS EMPRESAS | O24: 0 | P24: SIN FACTURA LOCALIZADA | Q24: 24
A25: O2690020 | B25: 21/01/2026 | C25: Proveedor Ficticio X 139, S.L. | D25: Equipamiento tecnologico - operacion ficticia | E25: 9265.32 | F25: 11211.04 | G25: 11211.04 | H25: Aceptado | I25: Facturado | J25: XPR26-01281 | Proyecto demostracion 01281 | K25: VALIDO | L25: #etiqueta_demo_sin_ceco | M25: NO INFORMADO | N25: Otros servicios | O25: 2 | P25: CONCILIADO | Q25: 25
A26: O2690021 | B26: 05/10/2026 | C26: Proveedor Ficticio X 120, S.L. | D26: Subcontratacion de proyectos - operacion ficticia | E26: 3536.49 | F26: 4279.15 | G26: 0 | H26: Aceptado | I26: Pendiente | K26: NO INFORMADO | L26: #tecnologia_x154 #entorno_demo | M26: VALIDO | N26: Publicidad, propaganda y relaciones publicas | O26: 0 | P26: SIN FACTURA LOCALIZADA | Q26: 26
A27: O2690022 | B27: 06/09/2026 | C27: Proveedor Ficticio X 116, S.L. | D27: Equipamiento tecnologico - operacion ficticia | E27: 5646.18 | F27: 5646.18 | G27: 0 | H27: Aceptado | I27: Pendiente | J27: XPR26-02771 | Proyecto demostracion 02771 | K27: VALIDO | L27: #finanzas_x117 #entorno_demo | M27: VALIDO | N27: Otros servicios | O27: 0 | P27: SIN FACTURA LOCALIZADA | Q27: 27
A28: O2690023 | B28: 10/02/2026 | C28: Proveedor Ficticio X 080, S.L. | D28: Asesoria operativa - operacion ficticia | E28: 21106.11 | F28: 21106.11 | G28: 15849.8 | H28: Aceptado | I28: Parcialmente | J28: XPR26-03635 | Proyecto demostracion 03635 | K28: VALIDO | L28: #creatividad_x112 #entorno_demo | M28: VALIDO | N28: Transportes | O28: 2 | P28: PARCIAL / DIFERENCIA | Q28: 28
A29: O2690024 | B29: 14/01/2026 | C29: Proveedor Ficticio X 167, S.L. | D29: Servicios logisticos - operacion ficticia | E29: 8781.05 | F29: 10625.07 | G29: 0 | H29: Cancelado | I29: Pendiente | K29: NO INFORMADO | L29: #operaciones_x013 #entorno_demo | M29: VALIDO | N29: Equipos para procesos de informacion | O29: 0 | P29: CANCELADO / SIN FACTURA | Q29: 29
A30: O2690025 | B30: 02/01/2026 | C30: Proveedor Ficticio X 084, S.L. | D30: Campana de marketing - operacion ficticia | E30: 14902.77 | F30: 14902.77 | G30: 14902.77 | H30: Aceptado | I30: Facturado | J30: XPR26-00654 | Proyecto demostracion 00654 | K30: VALIDO | L30: #operaciones_x113 #entorno_demo | M30: VALIDO | N30: Material de oficina | O30: 2 | P30: CONCILIADO | Q30: 30
A31: O2690026 | B31: 02/08/2026 | C31: Proveedor Ficticio X 150, S.L. | D31: Licencias de software - operacion ficticia | E31: 17708.57 | F31: 19479.43 | G31: 21651.03 | H31: Aceptado | I31: Facturado | J31: XPR26-01689 | Proyecto demostracion 01689 | K31: VALIDO | L31: #finanzas_x227 #entorno_demo | M31: VALIDO | N31: Subcontractors | O31: 1 | P31: SOBRE PEDIDO | Q31: 31
A32: O2690027 | B32: 20/04/2026 | C32: Proveedor Ficticio X 176, S.L. | D32: Produccion audiovisual - operacion ficticia | E32: 7100.22 | F32: 8591.27 | G32: 8591.27 | H32: Aceptado | I32: Facturado | K32: NO INFORMADO | L32: #comercial_x140 #entorno_demo | M32: VALIDO | N32: Otros servicios | O32: 1 | P32: CONCILIADO | Q32: 32
A33: O2690028 | B33: 13/07/2026 | C33: Proveedor Ficticio X 156, S.L. | D33: Servicios de diseno - operacion ficticia | E33: 17623.74 | F33: 21324.73 | G33: 21324.73 | H33: Aceptado | I33: Facturado | K33: NO INFORMADO | L33: #finanzas_x037 #entorno_demo | M33: VALIDO | N33: TRABAJOS REALIZADOS POR OTRAS EMPRESAS | O33: 1 | P33: CONCILIADO | Q33: 33
A34: O2690029 | B34: 23/07/2026 | C34: Proveedor Ficticio X 130, S.L. | D34: Subcontratacion de proyectos - operacion ficticia | E34: 21009.4 | F34: 25421.37 | G34: 25421.37 | H34: Pendiente | I34: Facturado | J34: XPR26-02650 | Proyecto demostracion 02650 | K34: VALIDO | L34: #produccion_x231 #entorno_demo | M34: VALIDO | N34: Publicidad, propaganda y relaciones publicas | O34: 1 | P34: CONCILIADO | Q34: 34
A35: O2690030 | B35: 20/06/2026 | C35: Proveedor Ficticio X 048, S.L. | D35: Licencias de software - operacion ficticia | E35: 5101.92 | F35: 5101.92 | G35: 5101.92 | H35: Pendiente | I35: Facturado | J35: XPR26-03114 | Proyecto demostracion 03114 | K35: VALIDO | L35: #diseno_x178 #entorno_demo | M35: VALIDO | N35: Subcontractors | O35: 1 | P35: CONCILIADO | Q35: 35
A36: O2690031 | B36: 22/07/2026 | C36: Proveedor Ficticio X 097, S.L. | D36: Subcontratacion de proyectos - operacion ficticia | E36: 17251.93 | F36: 20874.84 | G36: 20874.84 | H36: Aceptado | I36: Facturado | J36: XPR26-01419 | Proyecto demostracion 01419 | K36: VALIDO | L36: #tecnologia_x204 #entorno_demo | M36: VALIDO | N36: Publicidad, propaganda y relaciones publicas | O36: 1 | P36: CONCILIADO | Q36: 36
A37: O2690032 | B37: 09/01/2026 | C37: Proveedor Ficticio X 049, S.L. | D37: Asesoria operativa - operacion ficticia | E37: 14622.99 | F37: 17693.82 | G37: 17693.82 | H37: Pendiente | I37: Facturado | J37: XPR26-03191 | Proyecto demostracion 03191 | K37: VALIDO | L37: #consultoria_x109 #entorno_demo | M37: VALIDO | N37: Transportes | O37: 1 | P37: CONCILIADO | Q37: 37
A38: O2690033 | B38: 22/01/2026 | C38: Proveedor Ficticio X 133, S.L. | D38: Servicios de diseno - operacion ficticia | E38: 4463.21 | F38: 5400.48 | G38: 5400.48 | H38: Pendiente | I38: Facturado | K38: NO INFORMADO | L38: #creatividad_x052 #entorno_demo | M38: VALIDO | N38: TRABAJOS REALIZADOS POR OTRAS EMPRESAS | O38: 1 | P38: CONCILIADO | Q38: 38
A39: O2690034 | B39: 11/01/2026 | C39: Proveedor Ficticio X 002, S.L. | D39: Subcontratacion de proyectos - operacion ficticia | E39: 9939.52 | F39: 12026.82 | G39: 0 | H39: Aceptado | I39: Pendiente | K39: NO INFORMADO | L39: #tecnologia_x134 #entorno_demo | M39: VALIDO | N39: Publicidad, propaganda y relaciones publicas | O39: 0 | P39: SIN FACTURA LOCALIZADA | Q39: 39
A40: O2690035 | B40: 23/09/2026 | C40: Proveedor Ficticio X 182, S.L. | D40: Material de oficina - operacion ficticia | E40: 7145.88 | F40: 8646.51 | G40: 6073.78 | H40: Aceptado | I40: Parcialmente | J40: XPR26-00209 | Proyecto demostracion 00209 | K40: VALIDO | L40: #comercial_x150 #entorno_demo | M40: VALIDO | N40: Servicios profesionales independientes | O40: 1 | P40: PARCIAL / DIFERENCIA | Q40: 40
A41: O2690036 | B41: 09/07/2026 | C41: Proveedor Ficticio X 007, S.L. | D41: Servicios de diseno - operacion ficticia | E41: 459.6 | F41: 459.6 | G41: 168.33 | H41: Pendiente | I41: Parcialmente | K41: NO INFORMADO | L41: #marketing_x275 #entorno_demo | M41: VALIDO | N41: TRABAJOS REALIZADOS POR OTRAS EMPRESAS | O41: 1 | P41: PARCIAL / DIFERENCIA | Q41: 41
A42: O2690037 | B42: 03/03/2026 | C42: Proveedor Ficticio X 001, S.L. | D42: Equipamiento tecnologico - operacion ficticia | E42: 3786.48 | F42: 4581.64 | G42: 4581.64 | H42: Aceptado | I42: Facturado | J42: XPR26-00986 | Proyecto demostracion 00986 | K42: VALIDO | L42: #consultoria_x029 #entorno_demo | M42: VALIDO | N42: Otros servicios | O42: 1 | P42: CONCILIADO | Q42: 42
A43: O2690038 | B43: 09/09/2026 | C43: Proveedor Ficticio X 155, S.L. | D43: Servicios de diseno - operacion ficticia | E43: 19795.58 | F43: 23952.65 | G43: 0 | H43: Aceptado | I43: Pendiente | J43: XPR26-00923 | Proyecto demostracion 00923 | K43: VALIDO | L43: #creatividad_x062 #entorno_demo | M43: VALIDO | N43: TRABAJOS REALIZADOS POR OTRAS EMPRESAS | O43: 0 | P43: SIN FACTURA LOCALIZADA | Q43: 43
A44: O2690039 | B44: 29/08/2026 | C44: Proveedor Ficticio X 075, S.L. | D44: Asistencia tecnica - operacion ficticia | E44: 3408.37 | F44: 3408.37 | G44: 0 | H44: Pendiente | I44: Pendiente | J44: XPR26-00930 | Proyecto demostracion 00930 | K44: VALIDO | L44: #etiqueta_demo_sin_ceco | M44: NO INFORMADO | N44: Material de oficina | O44: 0 | P44: SIN FACTURA LOCALIZADA | Q44: 44
A45: O2690040 | B45: 09/09/2026 | C45: Proveedor Ficticio X 139, S.L. | D45: Mantenimiento informatico - operacion ficticia | E45: 14996.4 | F45: 14996.4 | G45: 0 | H45: Pendiente | I45: Pendiente | J45: XPR26-00795 | Proyecto demostracion 00795 | K45: VALIDO | L45: #produccion_x071 #entorno_demo | M45: VALIDO | N45: Arrendamientos y canones | O45: 0 | P45: SIN FACTURA LOCALIZADA | Q45: 45
A46: O2690041 | B46: 21/03/2026 | C46: Proveedor Ficticio X 082, S.L. | D46: Servicios logisticos - operacion ficticia | E46: 13210.22 | F46: 15984.37 | G46: 9425.62 | H46: Aceptado | I46: Parcialmente | J46: XPR26-00137 | Proyecto demostracion 00137 | K46: VALIDO | L46: #administracion_x046 #entorno_demo | M46: VALIDO | N46: Equipos para procesos de informacion | O46: 1 | P46: PARCIAL / DIFERENCIA | Q46: 46
A47: O2690042 | B47: 13/09/2026 | C47: Proveedor Ficticio X 184, S.L. | D47: Traduccion y localizacion - operacion ficticia | E47: 19835.47 | F47: 24000.92 | G47: 24000.92 | H47: Aceptado | I47: Facturado | K47: NO INFORMADO | L47: #tecnologia_x044 #entorno_demo | M47: VALIDO | N47: TRABAJOS REALIZADOS POR OTRAS EMPRESAS | O47: 1 | P47: CONCILIADO | Q47: 47
A48: O2690043 | B48: 20/09/2026 | C48: Proveedor Ficticio X 112, S.L. | D48: Mantenimiento informatico - operacion ficticia | E48: 13292.25 | F48: 16083.62 | G48: 16083.62 | H48: Aceptado | I48: Facturado | J48: XPR26-00435 | Proyecto demostracion 00435 | K48: VALIDO | L48: #diseno_x208 #entorno_demo | M48: VALIDO | N48: Arrendamientos y canones | O48: 1 | P48: CONCILIADO | Q48: 48
A49: O2690044 | B49: 28/09/2026 | C49: Proveedor Ficticio X 161, S.L. | D49: Mantenimiento informatico - operacion ficticia | E49: 2826.08 | F49: 3419.56 | G49: 1222.06 | H49: Aceptado | I49: Parcialmente | K49: NO INFORMADO | L49: #finanzas_x127 #entorno_demo | M49: VALIDO | N49: Arrendamientos y canones | O49: 1 | P49: PARCIAL / DIFERENCIA | Q49: 49
A50: O2690045 | B50: 13/08/2026 | C50: Proveedor Ficticio X 177, S.L. | D50: Licencias de software - operacion ficticia | E50: 19336.43 | F50: 23397.08 | G50: 20012.67 | H50: Aceptado | I50: Parcialmente | J50: XPR26-01869 | Proyecto demostracion 01869 | K50: VALIDO | L50: #finanzas_x277 #entorno_demo | M50: VALIDO | N50: Subcontractors | O50: 1 | P50: PARCIAL / DIFERENCIA | Q50: 50
A51: O2690046 | B51: 19/03/2026 | C51: Proveedor Ficticio X 089, S.L. | D51: Servicios de diseno - operacion ficticia | E51: 15600.28 | F51: 18876.34 | G51: 18876.34 | H51: Pendiente | I51: Facturado | J51: XPR26-00166 | Proyecto demostracion 00166 | K51: VALIDO | L51: #finanzas_x177 #entorno_demo | M51: VALIDO | N51: TRABAJOS REALIZADOS POR OTRAS EMPRESAS | O51: 1 | P51: CONCILIADO | Q51: 51
A52: O2690047 | B52: 25/01/2026 | C52: Proveedor Ficticio X 080, S.L. | D52: Traduccion y localizacion - operacion ficticia | E52: 782.27 | F52: 946.55 | G52: 946.54 | H52: Aceptado | I52: Facturado | J52: XPR26-00173 | Proyecto demostracion 00173 | K52: VALIDO | L52: #diseno_x148 #entorno_demo | M52: VALIDO | N52: TRABAJOS REALIZADOS POR OTRAS EMPRESAS | O52: 2 | P52: CONCILIADO | Q52: 52
A53: O2690048 | B53: 08/10/2026 | C53: Proveedor Ficticio X 095, S.L. | D53: Equipamiento tecnologico - operacion ficticia | E53: 5391.33 | F53: 5391.33 | G53: 6379.4 | H53: Aceptado | I53: Facturado | J53: XPR26-03191 | Proyecto demostracion 03191 | K53: VALIDO | L53: #consultoria_x109 #entorno_demo | M53: VALIDO | N53: Otros servicios | O53: 1 | P53: SOBRE PEDIDO | Q53: 53
A54: O2690049 | B54: 21/02/2026 | C54: Proveedor Ficticio X 167, S.L. | D54: Asistencia tecnica - operacion ficticia | E54: 11382.77 | F54: 11382.77 | G54: 0 | H54: Pendiente | I54: Pendiente | J54: XPR26-00667 | Proyecto demostracion 00667 | K54: VALIDO | L54: #comercial_x080 #entorno_demo | M54: VALIDO | N54: Material de oficina | O54: 0 | P54: SIN FACTURA LOCALIZADA | Q54: 54
A55: O2690050 | B55: 27/08/2026 | C55: Proveedor Ficticio X 146, S.L. | D55: Subcontratacion de proyectos - operacion ficticia | E55: 646.08 | F55: 781.76 | G55: 0 | H55: Aceptado | I55: Pendiente | J55: XPR26-03762 | Proyecto demostracion 03762 | K55: VALIDO | L55: #finanzas_x147 #entorno_demo | M55: VALIDO | N55: Publicidad, propaganda y relaciones publicas | O55: 0 | P55: SIN FACTURA LOCALIZADA | Q55: 55
A56: O2690051 | B56: 03/01/2026 | C56: Proveedor Ficticio X 144, S.L. | D56: Servicios logisticos - operacion ficticia | E56: 9734.72 | F56: 11779.01 | G56: 11779.01 | H56: Aceptado | I56: Facturado | J56: XPR26-02632 | Proyecto demostracion 02632 | K56: VALIDO | L56: #diseno_x058 #entorno_demo | M56: VALIDO | N56: Equipos para procesos de informacion | O56: 1 | P56: CONCILIADO | Q56: 56
A57: O2690052 | B57: 04/03/2026 | C57: Proveedor Ficticio X 031, S.L. | D57: Servicios logisticos - operacion ficticia | E57: 20168.21 | F57: 24403.53 | G57: 0 | H57: Aceptado | I57: Pendiente | K57: NO INFORMADO | L57: #produccion_x091 #entorno_demo | M57: VALIDO | N57: Equipos para procesos de informacion | O57: 0 | P57: SIN FACTURA LOCALIZADA | Q57: 57
A58: O2690053 | B58: 19/02/2026 | C58: Proveedor Ficticio X 176, S.L. | D58: Asesoria operativa - operacion ficticia | E58: 1072.85 | F58: 1298.15 | G58: 1298.15 | H58: Aceptado | I58: Facturado | J58: XPR26-01984 | Proyecto demostracion 01984 | K58: VALIDO | L58: #administracion_x196 #entorno_demo | M58: VALIDO | N58: Transportes | O58: 1 | P58: CONCILIADO | Q58: 58
A59: O2690054 | B59: 28/03/2026 | C59: Proveedor Ficticio X 012, S.L. | D59: Servicios de diseno - operacion ficticia | E59: 17717.28 | F59: 21437.91 | G59: 0 | H59: Aceptado | I59: Pendiente | J59: XPR26-00964 | Proyecto demostracion 00964 | K59: VALIDO | L59: #diseno_x238 #entorno_demo | M59: VALIDO | N59: TRABAJOS REALIZADOS POR OTRAS EMPRESAS | O59: 0 | P59: SIN FACTURA LOCALIZADA | Q59: 59
A60: O2690055 | B60: 16/05/2026 | C60: Proveedor Ficticio X 104, S.L. | D60: Servicios logisticos - operacion ficticia | E60: 22297.89 | F60: 26980.45 | G60: 26980.45 | H60: Aceptado | I60: Facturado | K60: NO INFORMADO | L60: #marketing_x085 #entorno_demo | M60: VALIDO | N60: Equipos para procesos de informacion | O60: 1 | P60: CONCILIADO | Q60: 60
A61: O2690056 | B61: 06/03/2026 | C61: Proveedor Ficticio X 070, S.L. | D61: Mantenimiento informatico - operacion ficticia | E61: 14599.21 | F61: 17665.04 | G61: 17665.04 | H61: Aceptado | I61: Facturado | J61: XPR26-02976 | Proyecto demostracion 02976 | K61: VALIDO | L61: #consultoria_x199 #entorno_demo | M61: VALIDO | N61: Arrendamientos y canones | O61: 1 | P61: CONCILIADO | Q61: 61
A62: O2690057 | B62: 29/07/2026 | C62: Proveedor Ficticio X 020, S.L. | D62: Equipamiento tecnologico - operacion ficticia | E62: 658.84 | F62: 797.2 | G62: 0 | H62: Aceptado | I62: Pendiente | J62: XPR26-02237 | Proyecto demostracion 02237 | K62: VALIDO | L62: #finanzas_x167 #entorno_demo | M62: VALIDO | N62: Otros servicios | O62: 0 | P62: SIN FACTURA LOCALIZADA | Q62: 62
A63: O2690058 | B63: 20/09/2026 | C63: Proveedor Ficticio X 140, S.L. | D63: Asistencia tecnica - operacion ficticia | E63: 9310.52 | F63: 11265.73 | G63: 11265.73 | H63: Aceptado | I63: Facturado | J63: XPR26-02936 | Proyecto demostracion 02936 | K63: VALIDO | L63: #etiqueta_demo_sin_ceco | M63: NO INFORMADO | N63: Material de oficina | O63: 1 | P63: CONCILIADO | Q63: 63
A64: O2690059 | B64: 02/02/2026 | C64: Proveedor Ficticio X 133, S.L. | D64: Traduccion y localizacion - operacion ficticia | E64: 21156.14 | F64: 25598.93 | G64: 0 | H64: Cancelado | I64: Pendiente | J64: XPR26-02407 | Proyecto demostracion 02407 | K64: VALIDO | L64: #produccion_x091 #entorno_demo | M64: VALIDO | N64: TRABAJOS REALIZADOS POR OTRAS EMPRESAS | O64: 0 | P64: CANCELADO / SIN FACTURA | Q64: 64
A65: O2690060 | B65: 03/03/2026 | C65: Proveedor Ficticio X 172, S.L. | D65: Alquiler de equipos - operacion ficticia | E65: 19510.41 | F65: 21461.45 | G65: 21461.45 | H65: Aceptado | I65: Facturado | J65: XPR26-02528 | Proyecto demostracion 02528 | K65: VALIDO | L65: #marketing_x215 #entorno_demo | M65: VALIDO | N65: Subcontractors | O65: 1 | P65: CONCILIADO | Q65: 65
A66: O2690061 | B66: 08/02/2026 | C66: Proveedor Ficticio X 077, S.L. | D66: Traduccion y localizacion - operacion ficticia | E66: 44630.67 | F66: 54003.11 | G66: 0 | H66: Aceptado | I66: Pendiente | K66: NO INFORMADO | L66: #consultoria_x089 #entorno_demo | M66: VALIDO | N66: TRABAJOS REALIZADOS POR OTRAS EMPRESAS | O66: 0 | P66: SIN FACTURA LOCALIZADA | Q66: 66
A67: O2690062 | B67: 12/09/2026 | C67: Proveedor Ficticio X 056, S.L. | D67: Licencias de software - operacion ficticia | E67: 202.69 | F67: 245.25 | G67: 245.25 | H67: Pendiente | I67: Facturado | J67: XPR26-02237 | Proyecto demostracion 02237 | K67: VALIDO | L67: #finanzas_x167 #entorno_demo | M67: VALIDO | N67: Subcontractors | O67: 1 | P67: CONCILIADO | Q67: 67
A68: O2690063 | B68: 27/06/2026 | C68: Proveedor Ficticio X 104, S.L. | D68: Traduccion y localizacion - operacion ficticia | E68: 1036.62 | F68: 1254.31 | G68: 1254.31 | H68: Aceptado | I68: Facturado | J68: XPR26-01235 | Proyecto demostracion 01235 | K68: VALIDO | L68: #administracion_x036 #entorno_demo | M68: VALIDO | N68: TRABAJOS REALIZADOS POR OTRAS EMPRESAS | O68: 1 | P68: CONCILIADO | Q68: 68
A69: O2690064 | B69: 22/06/2026 | C69: Proveedor Ficticio X 133, S.L. | D69: Traduccion y localizacion - operacion ficticia | E69: 1766.97 | F69: 2138.03 | G69: 756.42 | H69: Aceptado | I69: Parcialmente | J69: XPR26-00091 | Proyecto demostracion 00091 | K69: VALIDO | L69: #operaciones_x063 #entorno_demo | M69: VALIDO | N69: TRABAJOS REALIZADOS POR OTRAS EMPRESAS | O69: 1 | P69: PARCIAL / DIFERENCIA | Q69: 69
A70: O2690065 | B70: 13/03/2026 | C70: Proveedor Ficticio X 087, S.L. | D70: Servicios logisticos - operacion ficticia | E70: 16745.32 | F70: 20261.84 | G70: 20261.84 | H70: Aceptado | I70: Facturado | J70: XPR26-00178 | Proyecto demostracion 00178 | K70: VALIDO | L70: #consultoria_x089 #entorno_demo | M70: VALIDO | N70: Equipos para procesos de informacion | O70: 1 | P70: CONCILIADO | Q70: 70
A71: O2690066 | B71: 18/07/2026 | C71: Proveedor Ficticio X 065, S.L. | D71: Produccion de contenido - operacion ficticia | E71: 14876.11 | F71: 18000.09 | G71: 0 | H71: Aceptado | I71: Pendiente | K71: NO INFORMADO | L71: #operaciones_x253 #entorno_demo | M71: VALIDO | N71: Reparaciones y conservacion | O71: 0 | P71: SIN FACTURA LOCALIZADA | Q71: 71
A72: O2690067 | B72: 09/09/2026 | C72: Proveedor Ficticio X 061, S.L. | D72: Produccion audiovisual - operacion ficticia | E72: 6553.89 | F72: 7930.21 | G72: 7930.2 | H72: Aceptado | I72: Facturado | J72: XPR26-01869 | Proyecto demostracion 01869 | K72: VALIDO | L72: #finanzas_x277 #entorno_demo | M72: VALIDO | N72: Otros servicios | O72: 2 | P72: CONCILIADO | Q72: 72
A73: O2690068 | B73: 14/05/2026 | C73: Proveedor Ficticio X 026, S.L. | D73: Produccion de contenido - operacion ficticia | E73: 19992.27 | F73: 24190.65 | G73: 24190.65 | H73: Aceptado | I73: Facturado | J73: XPR26-02958 | Proyecto demostracion 02958 | K73: VALIDO | L73: #creatividad_x232 #entorno_demo | M73: VALIDO | N73: Reparaciones y conservacion | O73: 1 | P73: CONCILIADO | Q73: 73
A74: O2690069 | B74: 29/01/2026 | C74: Proveedor Ficticio X 096, S.L. | D74: Material de oficina - operacion ficticia | E74: 17751.76 | F74: 21479.63 | G74: 0 | H74: Aceptado | I74: Pendiente | K74: NO INFORMADO | L74: #marketing_x055 #entorno_demo | M74: VALIDO | N74: Servicios profesionales independientes | O74: 0 | P74: SIN FACTURA LOCALIZADA | Q74: 74
A75: O2690070 | B75: 26/06/2026 | C75: Proveedor Ficticio X 140, S.L. | D75: Equipamiento tecnologico - operacion ficticia | E75: 14012.62 | F75: 16955.27 | G75: 0 | H75: Aceptado | I75: Pendiente | J75: XPR26-03729 | Proyecto demostracion 03729 | K75: VALIDO | L75: #diseno_x238 #entorno_demo | M75: VALIDO | N75: Otros servicios | O75: 0 | P75: SIN FACTURA LOCALIZADA | Q75: 75
A76: O2690071 | B76: 01/03/2026 | C76: Proveedor Ficticio X 181, S.L. | D76: Alquiler de equipos - operacion ficticia | E76: 20224.64 | F76: 20224.64 | G76: 11455.69 | H76: Aceptado | I76: Parcialmente | K76: NO INFORMADO | L76: #consultoria_x169 #entorno_demo | M76: VALIDO | N76: Subcontractors | O76: 1 | P76: PARCIAL / DIFERENCIA | Q76: 76
A77: O2690072 | B77: 24/02/2026 | C77: Proveedor Ficticio X 138, S.L. | D77: Servicios profesionales - operacion ficticia | E77: 2024.4 | F77: 2449.52 | G77: 0 | H77: Aceptado | I77: Pendiente | J77: XPR26-01878 | Proyecto demostracion 01878 | K77: VALIDO | L77: #marketing_x165 #entorno_demo | M77: VALIDO | N77: Equipos para procesos de informacion | O77: 0 | P77: SIN FACTURA LOCALIZADA | Q77: 77
A78: O2690073 | B78: 06/02/2026 | C78: Proveedor Ficticio X 080, S.L. | D78: Campana de marketing - operacion ficticia | E78: 4461.85 | F78: 5398.84 | G78: 0 | H78: Aceptado | I78: Pendiente | J78: XPR26-00316 | Proyecto demostracion 00316 | K78: VALIDO | L78: #finanzas_x077 #entorno_demo | M78: VALIDO | N78: Material de oficina | O78: 0 | P78: SIN FACTURA LOCALIZADA | Q78: 78
A79: O2690074 | B79: 21/02/2026 | C79: Proveedor Ficticio X 060, S.L. | D79: Mantenimiento informatico - operacion ficticia | E79: 74974.02 | F79: 82471.42 | G79: 82471.42 | H79: Aceptado | I79: Facturado | K79: NO INFORMADO | L79: #marketing_x025 #entorno_demo | M79: VALIDO | N79: Arrendamientos y canones | O79: 1 | P79: CONCILIADO | Q79: 79
A80: O2690075 | B80: 16/04/2026 | C80: Proveedor Ficticio X 084, S.L. | D80: Subcontratacion de proyectos - operacion ficticia | E80: 4472.8 | F80: 5412.09 | G80: 6250.29 | H80: Aceptado | I80: Facturado | J80: XPR26-02313 | Proyecto demostracion 02313 | K80: VALIDO | L80: #diseno_x218 #entorno_demo | M80: VALIDO | N80: Publicidad, propaganda y relaciones publicas | O80: 1 | P80: SOBRE PEDIDO | Q80: 80
A81: O2690076 | B81: 23/01/2026 | C81: Proveedor Ficticio X 053, S.L. | D81: Asistencia tecnica - operacion ficticia | E81: 15561.97 | F81: 18829.98 | G81: 9969.19 | H81: Aceptado | I81: Parcialmente | J81: XPR26-00923 | Proyecto demostracion 00923 | K81: VALIDO | L81: #creatividad_x062 #entorno_demo | M81: VALIDO | N81: Material de oficina | O81: 1 | P81: PARCIAL / DIFERENCIA | Q81: 81
A82: O2690077 | B82: 19/07/2026 | C82: Proveedor Ficticio X 015, S.L. | D82: Alquiler de equipos - operacion ficticia | E82: 18886.43 | F82: 22852.58 | G82: 0 | H82: Aceptado | I82: Pendiente | J82: XPR26-00923 | Proyecto demostracion 00923 | K82: VALIDO | L82: #etiqueta_demo_sin_ceco | M82: NO INFORMADO | N82: Subcontractors | O82: 0 | P82: SIN FACTURA LOCALIZADA | Q82: 82
A83: O2690078 | B83: 01/04/2026 | C83: Proveedor Ficticio X 057, S.L. | D83: Servicios logisticos - operacion ficticia | E83: 13489.97 | F83: 16322.86 | G83: 0 | H83: Aceptado | I83: Pendiente | J83: XPR26-03886 | Proyecto demostracion 03886 | K83: VALIDO | L83: #marketing_x205 #entorno_demo | M83: VALIDO | N83: Equipos para procesos de informacion | O83: 0 | P83: SIN FACTURA LOCALIZADA | Q83: 83
A84: O2690079 | B84: 02/07/2026 | C84: Proveedor Ficticio X 071, S.L. | D84: Asesoria operativa - operacion ficticia | E84: 12706.98 | F84: 13977.68 | G84: 15466.73 | H84: Pendiente | I84: Facturado | K84: NO INFORMADO | L84: #tecnologia_x214 #entorno_demo | M84: VALIDO | N84: Transportes | O84: 2 | P84: SOBRE PEDIDO | Q84: 84
A85: O2690080 | B85: 23/04/2026 | C85: Proveedor Ficticio X 095, S.L. | D85: Mantenimiento informatico - operacion ficticia | E85: 22788.64 | F85: 27574.25 | G85: 18393.91 | H85: Aceptado | I85: Parcialmente | K85: NO INFORMADO | L85: #marketing_x135 #entorno_demo | M85: VALIDO | N85: Arrendamientos y canones | O85: 1 | P85: PARCIAL / DIFERENCIA | Q85: 85
A86: O2690081 | B86: 29/04/2026 | C86: Proveedor Ficticio X 156, S.L. | D86: Subcontratacion de proyectos - operacion ficticia | E86: 13328.55 | F86: 16127.55 | G86: 16127.55 | H86: Aceptado | I86: Facturado | J86: XPR26-01443 | Proyecto demostracion 01443 | K86: VALIDO | L86: #finanzas_x007 #entorno_demo | M86: VALIDO | N86: Publicidad, propaganda y relaciones publicas | O86: 1 | P86: CONCILIADO | Q86: 86
A87: O2690082 | B87: 02/05/2026 | C87: Proveedor Ficticio X 113, S.L. | D87: Asistencia tecnica - operacion ficticia | E87: 4337.95 | F87: 5248.92 | G87: 6445.48 | H87: Aceptado | I87: Facturado | J87: XPR26-03739 | Proyecto demostracion 03739 | K87: VALIDO | L87: #diseno_x148 #entorno_demo | M87: VALIDO | N87: Material de oficina | O87: 1 | P87: SOBRE PEDIDO | Q87: 87
A88: O2690083 | B88: 04/01/2026 | C88: Proveedor Ficticio X 022, S.L. | D88: Produccion audiovisual - operacion ficticia | E88: 18734.33 | F88: 22668.54 | G88: 0 | H88: Aceptado | I88: Pendiente | K88: NO INFORMADO | L88: #consultoria_x169 #entorno_demo | M88: VALIDO | N88: Otros servicios | O88: 0 | P88: SIN FACTURA LOCALIZADA | Q88: 88
A89: O2690084 | B89: 14/01/2026 | C89: Proveedor Ficticio X 053, S.L. | D89: Asistencia tecnica - operacion ficticia | E89: 21412.87 | F89: 23554.16 | G89: 23554.16 | H89: Aceptado | I89: Facturado | J89: XPR26-03729 | Proyecto demostracion 03729 | K89: VALIDO | L89: #diseno_x238 #entorno_demo | M89: VALIDO | N89: Material de oficina | O89: 1 | P89: CONCILIADO | Q89: 89
A90: O2690085 | B90: 12/01/2026 | C90: Proveedor Ficticio X 008, S.L. | D90: Servicios logisticos - operacion ficticia | E90: 10850.06 | F90: 13128.57 | G90: 13128.57 | H90: Aceptado | I90: Facturado | J90: XPR26-00986 | Proyecto demostracion 00986 | K90: VALIDO | L90: #consultoria_x029 #entorno_demo | M90: VALIDO | N90: Equipos para procesos de informacion | O90: 1 | P90: CONCILIADO | Q90: 90
A91: O2690086 | B91: 13/04/2026 | C91: Proveedor Ficticio X 036, S.L. | D91: Servicios profesionales - operacion ficticia | E91: 1317.65 | F91: 1594.36 | G91: 0 | H91: Aceptado | I91: Pendiente | J91: XPR26-00491 | Proyecto demostracion 00491 | K91: VALIDO | L91: #consultoria_x159 #entorno_demo | M91: VALIDO | N91: Equipos para procesos de informacion | O91: 0 | P91: SIN FACTURA LOCALIZADA | Q91: 91
A92: O2690087 | B92: 19/07/2026 | C92: Proveedor Ficticio X 053, S.L. | D92: Mantenimiento informatico - operacion ficticia | E92: 3552.93 | F92: 4299.05 | G92: 4299.05 | H92: Pendiente | I92: Facturado | J92: XPR26-00178 | Proyecto demostracion 00178 | K92: VALIDO | L92: #consultoria_x089 #entorno_demo | M92: VALIDO | N92: Arrendamientos y canones | O92: 1 | P92: CONCILIADO | Q92: 92
A93: O2690088 | B93: 01/10/2026 | C93: Proveedor Ficticio X 017, S.L. | D93: Equipamiento tecnologico - operacion ficticia | E93: 10928.26 | F93: 10928.26 | G93: 6208.73 | H93: Pendiente | I93: Parcialmente | J93: XPR26-02930 | Proyecto demostracion 02930 | K93: VALIDO | L93: #marketing_x145 #entorno_demo | M93: VALIDO | N93: Otros servicios | O93: 1 | P93: PARCIAL / DIFERENCIA | Q93: 93
A94: O2690089 | B94: 27/07/2026 | C94: Proveedor Ficticio X 175, S.L. | D94: Subcontratacion de proyectos - operacion ficticia | E94: 12979.45 | F94: 15705.13 | G94: 15705.13 | H94: Aceptado | I94: Facturado | J94: XPR26-02324 | Proyecto demostracion 02324 | K94: VALIDO | L94: #comercial_x070 #entorno_demo | M94: VALIDO | N94: Publicidad, propaganda y relaciones publicas | O94: 1 | P94: CONCILIADO | Q94: 94
A95: O2690090 | B95: 31/05/2026 | C95: Proveedor Ficticio X 173, S.L. | D95: Equipamiento tecnologico - operacion ficticia | E95: 1669.1 | F95: 2019.61 | G95: 2019.62 | H95: Pendiente | I95: Facturado | J95: XPR26-03739 | Proyecto demostracion 03739 | K95: VALIDO | L95: #diseno_x148 #entorno_demo | M95: VALIDO | N95: Otros servicios | O95: 2 | P95: CONCILIADO | Q95: 95
A96: O2690091 | B96: 11/02/2026 | C96: Proveedor Ficticio X 128, S.L. | D96: Mantenimiento informatico - operacion ficticia | E96: 224.76 | F96: 271.96 | G96: 271.97 | H96: Aceptado | I96: Facturado | J96: XPR26-00964 | Proyecto demostracion 00964 | K96: VALIDO | L96: #diseno_x238 #entorno_demo | M96: VALIDO | N96: Arrendamientos y canones | O96: 3 | P96: CONCILIADO | Q96: 96
A97: O2690092 | B97: 25/07/2026 | C97: Proveedor Ficticio X 160, S.L. | D97: Mantenimiento informatico - operacion ficticia | E97: 14635.32 | F97: 17708.74 | G97: 17708.74 | H97: Aceptado | I97: Facturado | K97: NO INFORMADO | L97: #operaciones_x133 #entorno_demo | M97: VALIDO | N97: Arrendamientos y canones | O97: 1 | P97: CONCILIADO | Q97: 97
A98: O2690093 | B98: 16/01/2026 | C98: Proveedor Ficticio X 015, S.L. | D98: Alquiler de equipos - operacion ficticia | E98: 23186.05 | F98: 28055.12 | G98: 12694.76 | H98: Aceptado | I98: Parcialmente | J98: XPR26-02315 | Proyecto demostracion 02315 | K98: VALIDO | L98: #tecnologia_x184 #entorno_demo | M98: VALIDO | N98: Subcontractors | O98: 1 | P98: PARCIAL / DIFERENCIA | Q98: 98
A99: O2690094 | B99: 23/08/2026 | C99: Proveedor Ficticio X 082, S.L. | D99: Servicios logisticos - operacion ficticia | E99: 12100.17 | F99: 12100.17 | G99: 12100.17 | H99: Aceptado | I99: Facturado | J99: XPR26-00310 | Proyecto demostracion 00310 | K99: VALIDO | L99: #marketing_x245 #entorno_demo | M99: VALIDO | N99: Equipos para procesos de informacion | O99: 1 | P99: CONCILIADO | Q99: 99
A100: O2690095 | B100: 13/08/2026 | C100: Proveedor Ficticio X 021, S.L. | D100: Licencias de software - operacion ficticia | E100: 18884.38 | F100: 22850.1 | G100: 0 | H100: Pendiente | I100: Pendiente | K100: NO INFORMADO | L100: #marketing_x165 #entorno_demo | M100: VALIDO | N100: Subcontractors | O100: 0 | P100: SIN FACTURA LOCALIZADA | Q100: 100
A101: O2690096 | B101: 09/04/2026 | C101: Proveedor Ficticio X 106, S.L. | D101: Campana de marketing - operacion ficticia | E101: 15937.27 | F101: 15937.27 | G101: 18372.14 | H101: Aceptado | I101: Facturado | J101: XPR26-01668 | Proyecto demostracion 01668 | K101: VALIDO | L101: #etiqueta_demo_sin_ceco | M101: NO INFORMADO | N101: Material de oficina | O101: 1 | P101: SOBRE PEDIDO | Q101: 101
A102: O2690097 | B102: 11/08/2026 | C102: Proveedor Ficticio X 097, S.L. | D102: Asistencia tecnica - operacion ficticia | E102: 18593.26 | F102: 20452.59 | G102: 13983.43 | H102: Pendiente | I102: Parcialmente | K102: NO INFORMADO | L102: #marketing_x115 #entorno_demo | M102: VALIDO | N102: Material de oficina | O102: 2 | P102: PARCIAL / DIFERENCIA | Q102: 102
...

Sheet 05_Excepciones
A1: REGISTRO DE EXCEPCIONES / WORKPAPERS
A3: Cada alerta es una hipótesis de riesgo; el auditor debe documentar evidencia, criterio y resolución.
A5: ID estable | B5: Prioridad | C5: Control | D5: Origen | E5: Referencia | F5: Proveedor | G5: Motivo / evidencia pendiente | H5: Impacto indicativo € | I5: Estado revisión | J5: Responsable | K5: Conclusión / notas | L5: Fila origen
A6: EX-656C82BAF0 | B6: Alta | C6: DUP_VENDOR_INVOICE | D6: FACTURA | E6: FX26-000071 | F6: Proveedor Ficticio X 153, S.L. | G6: Se repite combinación proveedor + número de factura. | H6: 6888.78 | I6: Pendiente | L6: 76
A7: EX-73D214BCC0 | B7: Alta | C7: DUP_VENDOR_INVOICE | D7: FACTURA | E7: FX26-000071 | F7: Proveedor Ficticio X 153, S.L. | G7: Se repite combinación proveedor + número de factura. | H7: 6888.78 | I7: Pendiente | L7: 94
A8: EX-3CB494038B | B8: Alta | C8: DUP_VENDOR_INVOICE | D8: FACTURA | E8: FX26-000241 | F8: Proveedor Ficticio X 148, S.L. | G8: Se repite combinación proveedor + número de factura. | H8: 2340.21 | I8: Pendiente | L8: 263
A9: EX-604642CB29 | B9: Alta | C9: DUP_VENDOR_INVOICE | D9: FACTURA | E9: FX26-000241 | F9: Proveedor Ficticio X 148, S.L. | G9: Se repite combinación proveedor + número de factura. | H9: 2340.21 | I9: Pendiente | L9: 246
A10: EX-0B4F35DD98 | B10: Alta | C10: DUP_VENDOR_INVOICE | D10: FACTURA | E10: FX26-000322 | F10: Proveedor Ficticio X 176, S.L. | G10: Se repite combinación proveedor + número de factura. | H10: 13218.97 | I10: Pendiente | L10: 348
A11: EX-B8CD97588E | B11: Alta | C11: DUP_VENDOR_INVOICE | D11: FACTURA | E11: FX26-000322 | F11: Proveedor Ficticio X 176, S.L. | G11: Se repite combinación proveedor + número de factura. | H11: 13218.97 | I11: Pendiente | L11: 327
A12: EX-32F8DA39CE | B12: Alta | C12: DUP_VENDOR_INVOICE | D12: FACTURA | E12: FX26-000511 | F12: Proveedor Ficticio X 161, S.L. | G12: Se repite combinación proveedor + número de factura. | H12: 2773.05 | I12: Pendiente | L12: 516
A13: EX-B0E1FC0A1B | B13: Alta | C13: DUP_VENDOR_INVOICE | D13: FACTURA | E13: FX26-000511 | F13: Proveedor Ficticio X 161, S.L. | G13: Se repite combinación proveedor + número de factura. | H13: 2773.05 | I13: Pendiente | L13: 547
A14: EX-36E55AC224 | B14: Alta | C14: DUP_VENDOR_INVOICE | D14: FACTURA | E14: FX26-000802 | F14: Proveedor Ficticio X 239, S.L. | G14: Se repite combinación proveedor + número de factura. | H14: 7259.06 | I14: Pendiente | L14: 807
A15: EX-4748D56E18 | B15: Alta | C15: DUP_VENDOR_INVOICE | D15: FACTURA | E15: FX26-000802 | F15: Proveedor Ficticio X 239, S.L. | G15: Se repite combinación proveedor + número de factura. | H15: 7259.06 | I15: Pendiente | L15: 829
A16: EX-A2C0809B1C | B16: Alta | C16: DUP_VENDOR_INVOICE | D16: FACTURA | E16: FX26-001011 | F16: Proveedor Ficticio X 105, S.L. | G16: Se repite combinación proveedor + número de factura. | H16: 16036.29 | I16: Pendiente | L16: 1016
A17: EX-CEF25F026D | B17: Alta | C17: DUP_VENDOR_INVOICE | D17: FACTURA | E17: FX26-001011 | F17: Proveedor Ficticio X 105, S.L. | G17: Se repite combinación proveedor + número de factura. | H17: 16036.29 | I17: Pendiente | L17: 1026
... A253: EX-3C544F7FE1 | B253: Media | C253: PO_INVOICE_NOT_FOUND | D253: PEDIDO | E253: O2690424 | F253: Proveedor Ficticio X 084, S.L. | G253: No consta factura referenciada; valorar estado, servicio recibido y accruals. | H253: 27947.35 | I253: Pendiente | L253: 429

Sheet 06_Sin_Factura
A1: PEDIDOS SIN FACTURA VINCULADA
A3: Diferenciar 'facturado ERP sin referencia' de 'sin factura localizada' y de pedidos cancelados.
A5: PO | B5: Fecha | C5: Proveedor | D5: Total PO € | E5: Facturado ERP € | F5: Aprobación | G5: Estado | H5: Clasificación | I5: Proyecto | J5: Etiquetas | K5: Fila origen
A6: O2690002 | B6: 17/04/2026 | C6: Proveedor Ficticio X 140, S.L. | D6: 7894.52 | E6: 0 | F6: Aceptado | G6: Pendiente | H6: SIN FACTURA LOCALIZADA | I6: XPR26-00164 | Proyecto demostracion 00164 | J6: #tecnologia_x214 #entorno_demo | K6: 7
A7: O2690003 | B7: 07/09/2026 | C7: Proveedor Ficticio X 121, S.L. | D7: 9481.16 | E7: 0 | F7: Aceptado | G7: Pendiente | H7: SIN FACTURA LOCALIZADA | I7: XPR26-01546 | Proyecto demostracion 01546 | J7: #comercial_x080 #entorno_demo | K7: 8
A8: O2690005 | B8: 05/09/2026 | C8: Proveedor Ficticio X 121, S.L. | D8: 28298.46 | E8: 0 | F8: Aceptado | G8: Pendiente | H8: SIN FACTURA LOCALIZADA | I8: XPR26-03638 | Proyecto demostracion 03638 | J8: #creatividad_x142 #entorno_demo | K8: 10
A9: O2690006 | B9: 11/07/2026 | C9: Proveedor Ficticio X 151, S.L. | D9: 60605.65 | E9: 0 | F9: Cancelado | G9: Pendiente | H9: CANCELADO / SIN FACTURA | I9: XPR26-01049 | Proyecto demostracion 01049 | J9: #creatividad_x232 #entorno_demo | K9: 11
A10: O2690007 | B10: 10/08/2026 | C10: Proveedor Ficticio X 006, S.L. | D10: 20281.08 | E10: 0 | F10: Aceptado | G10: Pendiente | H10: SIN FACTURA LOCALIZADA | J10: #produccion_x231 #entorno_demo | K10: 12
A11: O2690008 | B11: 25/07/2026 | C11: Proveedor Ficticio X 079, S.L. | D11: 14529.84 | E11: 0 | F11: Aceptado | G11: Pendiente | H11: SIN FACTURA LOCALIZADA | I11: XPR26-01278 | Proyecto demostracion 01278 | J11: #creatividad_x252 #entorno_demo | K11: 13
A12: O2690012 | B12: 24/07/2026 | C12: Proveedor Ficticio X 090, S.L. | D12: 5974.22 | E12: 0 | F12: Aceptado | G12: Pendiente | H12: SIN FACTURA LOCALIZADA | I12: XPR26-02296 | Proyecto demostracion 02296 | J12: #comercial_x080 #entorno_demo | K12: 17
A13: O2690019 | B13: 13/07/2026 | C13: Proveedor Ficticio X 020, S.L. | D13: 22672.16 | E13: 0 | F13: Aceptado | G13: Pendiente | H13: SIN FACTURA LOCALIZADA | J13: #consultoria_x009 #entorno_demo | K13: 24
A14: O2690021 | B14: 05/10/2026 | C14: Proveedor Ficticio X 120, S.L. | D14: 4279.15 | E14: 0 | F14: Aceptado | G14: Pendiente | H14: SIN FACTURA LOCALIZADA | J14: #tecnologia_x154 #entorno_demo | K14: 26
A15: O2690022 | B15: 06/09/2026 | C15: Proveedor Ficticio X 116, S.L. | D15: 5646.18 | E15: 0 | F15: Aceptado | G15: Pendiente | H15: SIN FACTURA LOCALIZADA | I15: XPR26-02771 | Proyecto demostracion 02771 | J15: #finanzas_x117 #entorno_demo | K15: 27
A16: O2690024 | B16: 14/01/2026 | C16: Proveedor Ficticio X 167, S.L. | D16: 10625.07 | E16: 0 | F16: Cancelado | G16: Pendiente | H16: CANCELADO / SIN FACTURA | J16: #operaciones_x013 #entorno_demo | K16: 29
A17: O2690034 | B17: 11/01/2026 | C17: Proveedor Ficticio X 002, S.L. | D17: 12026.82 | E17: 0 | F17: Aceptado | G17: Pendiente | H17: SIN FACTURA LOCALIZADA | J17: #tecnologia_x134 #entorno_demo | K17: 39
A18: O2690038 | B18: 09/09/2026 | C18: Proveedor Ficticio X 155, S.L. | D18: 23952.65 | E18: 0 | F18: Aceptado | G18: Pendiente | H18: SIN FACTURA LOCALIZADA | I18: XPR26-00923 | Proyecto demostracion 00923 | J18: #creatividad_x062 #entorno_demo | K18: 43
A19: O2690039 | B19: 29/08/2026 | C19: Proveedor Ficticio X 075, S.L. | D19: 3408.37 | E19: 0 | F19: Pendiente | G19: Pendiente | H19: SIN FACTURA LOCALIZADA | I19: XPR26-00930 | Proyecto demostracion 00930 | J19: #etiqueta_demo_sin_ceco | K19: 44
A20: O2690040 | B20: 09/09/2026 | C20: Proveedor Ficticio X 139, S.L. | D20: 14996.4 | E20: 0 | F20: Pendiente | G20: Pendiente | H20: SIN FACTURA LOCALIZADA | I20: XPR26-00795 | Proyecto demostracion 00795 | J20: #produccion_x071 #entorno_demo | K20: 45
A21: O2690049 | B21: 21/02/2026 | C21: Proveedor Ficticio X 167, S.L. | D21: 11382.77 | E21: 0 | F21: Pendiente | G21: Pendiente | H21: SIN FACTURA LOCALIZADA | I21: XPR26-00667 | Proyecto demostracion 00667 | J21: #comercial_x080 #entorno_demo | K21: 54
A22: O2690050 | B22: 27/08/2026 | C22: Proveedor Ficticio X 146, S.L. | D22: 781.76 | E22: 0 | F22: Aceptado | G22: Pendiente | H22: SIN FACTURA LOCALIZADA | I22: XPR26-03762 | Proyecto demostracion 03762 | J22: #finanzas_x147 #entorno_demo | K22: 55
A23: O2690052 | B23: 04/03/2026 | C23: Proveedor Ficticio X 031, S.L. | D23: 24403.53 | E23: 0 | F23: Aceptado | G23: Pendiente | H23: SIN FACTURA LOCALIZADA | J23: #produccion_x091 #entorno_demo | K23: 57
A24: O2690054 | B24: 28/03/2026 | C24: Proveedor Ficticio X 012, S.L. | D24: 21437.91 | E24: 0 | F24: Aceptado | G24: Pendiente | H24: SIN FACTURA LOCALIZADA | I24: XPR26-00964 | Proyecto demostracion 00964 | J24: #diseno_x238 #entorno_demo | K24: 59
A25: O2690057 | B25: 29/07/2026 | C25: Proveedor Ficticio X 020, S.L. | D25: 797.2 | E25: 0 | F25: Aceptado | G25: Pendiente | H25: SIN FACTURA LOCALIZADA | I25: XPR26-02237 | Proyecto demostracion 02237 | J25: #finanzas_x167 #entorno_demo | K25: 62
A26: O2690059 | B26: 02/02/2026 | C26: Proveedor Ficticio X 133, S.L. | D26: 25598.93 | E26: 0 | F26: Cancelado | G26: Pendiente | H26: CANCELADO / SIN FACTURA | I26: XPR26-02407 | Proyecto demostracion 02407 | J26: #produccion_x091 #entorno_demo | K26: 64
A27: O2690061 | B27: 08/02/2026 | C27: Proveedor Ficticio X 077, S.L. | D27: 54003.11 | E27: 0 | F27: Aceptado | G27: Pendiente | H27: SIN FACTURA LOCALIZADA | J27: #consultoria_x089 #entorno_demo | K27: 66
A28: O2690066 | B28: 18/07/2026 | C28: Proveedor Ficticio X 065, S.L. | D28: 18000.09 | E28: 0 | F28: Aceptado | G28: Pendiente | H28: SIN FACTURA LOCALIZADA | J28: #operaciones_x253 #entorno_demo | K28: 71
A29: O2690069 | B29: 29/01/2026 | C29: Proveedor Ficticio X 096, S.L. | D29: 21479.63 | E29: 0 | F29: Aceptado | G29: Pendiente | H29: SIN FACTURA LOCALIZADA | J29: #marketing_x055 #entorno_demo | K29: 74
A30: O2690070 | B30: 26/06/2026 | C30: Proveedor Ficticio X 140, S.L. | D30: 16955.27 | E30: 0 | F30: Aceptado | G30: Pendiente | H30: SIN FACTURA LOCALIZADA | I30: XPR26-03729 | Proyecto demostracion 03729 | J30: #diseno_x238 #entorno_demo | K30: 75
A31: O2690072 | B31: 24/02/2026 | C31: Proveedor Ficticio X 138, S.L. | D31: 2449.52 | E31: 0 | F31: Aceptado | G31: Pendiente | H31: SIN FACTURA LOCALIZADA | I31: XPR26-01878 | Proyecto demostracion 01878 | J31: #marketing_x165 #entorno_demo | K31: 77
A32: O2690073 | B32: 06/02/2026 | C32: Proveedor Ficticio X 080, S.L. | D32: 5398.84 | E32: 0 | F32: Aceptado | G32: Pendiente | H32: SIN FACTURA LOCALIZADA | I32: XPR26-00316 | Proyecto demostracion 00316 | J32: #finanzas_x077 #entorno_demo | K32: 78
A33: O2690077 | B33: 19/07/2026 | C33: Proveedor Ficticio X 015, S.L. | D33: 22852.58 | E33: 0 | F33: Aceptado | G33: Pendiente | H33: SIN FACTURA LOCALIZADA | I33: XPR26-00923 | Proyecto demostracion 00923 | J33: #etiqueta_demo_sin_ceco | K33: 82
A34: O2690078 | B34: 01/04/2026 | C34: Proveedor Ficticio X 057, S.L. | D34: 16322.86 | E34: 0 | F34: Aceptado | G34: Pendiente | H34: SIN FACTURA LOCALIZADA | I34: XPR26-03886 | Proyecto demostracion 03886 | J34: #marketing_x205 #entorno_demo | K34: 83
A35: O2690083 | B35: 04/01/2026 | C35: Proveedor Ficticio X 022, S.L. | D35: 22668.54 | E35: 0 | F35: Aceptado | G35: Pendiente | H35: SIN FACTURA LOCALIZADA | J35: #consultoria_x169 #entorno_demo | K35: 88
A36: O2690086 | B36: 13/04/2026 | C36: Proveedor Ficticio X 036, S.L. | D36: 1594.36 | E36: 0 | F36: Aceptado | G36: Pendiente | H36: SIN FACTURA LOCALIZADA | I36: XPR26-00491 | Proyecto demostracion 00491 | J36: #consultoria_x159 #entorno_demo | K36: 91
A37: O2690095 | B37: 13/08/2026 | C37: Proveedor Ficticio X 021, S.L. | D37: 22850.1 | E37: 0 | F37: Pendiente | G37: Pendiente | H37: SIN FACTURA LOCALIZADA | J37: #marketing_x165 #entorno_demo | K37: 100
A38: O2690099 | B38: 05/04/2026 | C38: Proveedor Ficticio X 133, S.L. | D38: 6869.39 | E38: 0 | F38: Aceptado | G38: Pendiente | H38: SIN FACTURA LOCALIZADA | I38: XPR26-02124 | Proyecto demostracion 02124 | J38: #marketing_x255 #entorno_demo | K38: 104
A39: O2690103 | B39: 08/09/2026 | C39: Proveedor Ficticio X 152, S.L. | D39: 17847.78 | E39: 0 | F39: Aceptado | G39: Pendiente | H39: SIN FACTURA LOCALIZADA | J39: #produccion_x041 #entorno_demo | K39: 108
A40: O2690106 | B40: 21/03/2026 | C40: Proveedor Ficticio X 100, S.L. | D40: 10052.6 | E40: 0 | F40: Aceptado | G40: Pendiente | H40: SIN FACTURA LOCALIZADA | I40: XPR26-02650 | Proyecto demostracion 02650 | J40: #produccion_x231 #entorno_demo | K40: 111
A41: O2690114 | B41: 07/07/2026 | C41: Proveedor Ficticio X 003, S.L. | D41: 2644.04 | E41: 0 | F41: Aceptado | G41: Pendiente | H41: SIN FACTURA LOCALIZADA | I41: XPR26-03386 | Proyecto demostracion 03386 | J41: #creatividad_x142 #entorno_demo | K41: 119
A42: O2690117 | B42: 02/05/2026 | C42: Proveedor Ficticio X 179, S.L. | D42: 7777.72 | E42: 0 | F42: Pendiente | G42: Pendiente | H42: SIN FACTURA LOCALIZADA | J42: #comercial_x120 #entorno_demo | K42: 122
A43: O2690127 | B43: 16/02/2026 | C43: Proveedor Ficticio X 110, S.L. | D43: 1927.55 | E43: 0 | F43: Aceptado | G43: Pendiente | H43: SIN FACTURA LOCALIZADA | I43: XPR26-02124 | Proyecto demostracion 02124 | J43: #marketing_x255 #entorno_demo | K43: 132
A44: O2690128 | B44: 30/04/2026 | C44: Proveedor Ficticio X 075, S.L. | D44: 4179.91 | E44: 0 | F44: Aceptado | G44: Pendiente | H44: SIN FACTURA LOCALIZADA | I44: XPR26-01671 | Proyecto demostracion 01671 | J44: #diseno_x128 #entorno_demo | K44: 133
A45: O2690129 | B45: 17/09/2026 | C45: Proveedor Ficticio X 126, S.L. | D45: 11101.45 | E45: 0 | F45: Aceptado | G45: Pendiente | H45: SIN FACTURA LOCALIZADA | I45: XPR26-00222 | Proyecto demostracion 00222 | J45: #creatividad_x052 #entorno_demo | K45: 134
A46: O2690136 | B46: 01/06/2026 | C46: Proveedor Ficticio X 162, S.L. | D46: 22098.76 | E46: 0 | F46: Aceptado | G46: Pendiente | H46: SIN FACTURA LOCALIZADA | I46: XPR26-02443 | Proyecto demostracion 02443 | J46: #diseno_x218 #entorno_demo | K46: 141
A47: O2690140 | B47: 17/04/2026 | C47: Proveedor Ficticio X 162, S.L. | D47: 49979.19 | E47: 0 | F47: Aceptado | G47: Pendiente | H47: SIN FACTURA LOCALIZADA | I47: XPR26-00828 | Proyecto demostracion 00828 | J47: #consultoria_x029 #entorno_demo | K47: 145
A48: O2690141 | B48: 14/04/2026 | C48: Proveedor Ficticio X 078, S.L. | D48: 6779.01 | E48: 0 | F48: Cancelado | G48: Pendiente | H48: CANCELADO / SIN FACTURA | I48: XPR26-01110 | Proyecto demostracion 01110 | J48: #comercial_x180 #entorno_demo | K48: 146
A49: O2690142 | B49: 16/04/2026 | C49: Proveedor Ficticio X 177, S.L. | D49: 1048.94 | E49: 0 | F49: Aceptado | G49: Pendiente | H49: SIN FACTURA LOCALIZADA | J49: #produccion_x251 #entorno_demo | K49: 147
A50: O2690154 | B50: 01/02/2026 | C50: Proveedor Ficticio X 115, S.L. | D50: 23766.57 | E50: 0 | F50: Aceptado | G50: Pendiente | H50: SIN FACTURA LOCALIZADA | I50: XPR26-02494 | Proyecto demostracion 02494 | J50: #tecnologia_x184 #entorno_demo | K50: 159
A51: O2690165 | B51: 03/01/2026 | C51: Proveedor Ficticio X 148, S.L. | D51: 20002.84 | E51: 0 | F51: Cancelado | G51: Pendiente | H51: CANCELADO / SIN FACTURA | I51: XPR26-03638 | Proyecto demostracion 03638 | J51: #creatividad_x142 #entorno_demo | K51: 170
A52: O2690166 | B52: 07/09/2026 | C52: Proveedor Ficticio X 133, S.L. | D52: 21462.36 | E52: 0 | F52: Aceptado | G52: Pendiente | H52: SIN FACTURA LOCALIZADA | J52: #administracion_x216 #entorno_demo | K52: 171
A53: O2690167 | B53: 24/03/2026 | C53: Proveedor Ficticio X 069, S.L. | D53: 21762.06 | E53: 0 | F53: Cancelado | G53: Pendiente | H53: CANCELADO / SIN FACTURA | I53: XPR26-02563 | Proyecto demostracion 02563 | J53: #marketing_x055 #entorno_demo | K53: 172
A54: O2690168 | B54: 06/02/2026 | C54: Proveedor Ficticio X 006, S.L. | D54: 11069.41 | E54: 0 | F54: Aceptado | G54: Pendiente | H54: SIN FACTURA LOCALIZADA | J54: #finanzas_x017 #entorno_demo | K54: 173
A55: O2690172 | B55: 08/02/2026 | C55: Proveedor Ficticio X 055, S.L. | D55: 25665.04 | E55: 0 | F55: Aceptado | G55: Pendiente | H55: SIN FACTURA LOCALIZADA | J55: #etiqueta_demo_sin_ceco | K55: 177
A56: O2690176 | B56: 05/03/2026 | C56: Proveedor Ficticio X 123, S.L. | D56: 6599.38 | E56: 0 | F56: Aceptado | G56: Pendiente | H56: SIN FACTURA LOCALIZADA | J56: #administracion_x096 #entorno_demo | K56: 181
A57: O2690179 | B57: 16/04/2026 | C57: Proveedor Ficticio X 034, S.L. | D57: 13887.04 | E57: 0 | F57: Pendiente | G57: Pendiente | H57: SIN FACTURA LOCALIZADA | I57: XPR26-01195 | Proyecto demostracion 01195 | J57: #consultoria_x259 #entorno_demo | K57: 184
A58: O2690181 | B58: 01/05/2026 | C58: Proveedor Ficticio X 048, S.L. | D58: 13639.98 | E58: 0 | F58: Aceptado | G58: Pendiente | H58: SIN FACTURA LOCALIZADA | J58: #comercial_x090 #entorno_demo | K58: 186
A59: O2690195 | B59: 01/04/2026 | C59: Proveedor Ficticio X 041, S.L. | D59: 12018.22 | E59: 0 | F59: Aceptado | G59: Pendiente | H59: SIN FACTURA LOCALIZADA | I59: XPR26-03130 | Proyecto demostracion 03130 | J59: #consultoria_x069 #entorno_demo | K59: 200
A60: O2690196 | B60: 09/09/2026 | C60: Proveedor Ficticio X 164, S.L. | D60: 2079.67 | E60: 0 | F60: Aceptado | G60: Pendiente | H60: SIN FACTURA LOCALIZADA | I60: XPR26-00667 | Proyecto demostracion 00667 | J60: #comercial_x080 #entorno_demo | K60: 201
A61: O2690197 | B61: 30/01/2026 | C61: Proveedor Ficticio X 045, S.L. | D61: 13239.7 | E61: 0 | F61: Aceptado | G61: Pendiente | H61: SIN FACTURA LOCALIZADA | I61: XPR26-01063 | Proyecto demostracion 01063 | J61: #marketing_x075 #entorno_demo | K61: 202
A62: O2690199 | B62: 23/02/2026 | C62: Proveedor Ficticio X 081, S.L. | D62: 23914.61 | E62: 0 | F62: Cancelado | G62: Pendiente | H62: CANCELADO / SIN FACTURA | I62: XPR26-01347 | Proyecto demostracion 01347 | J62: #operaciones_x063 #entorno_demo | K62: 204
A63: O2690200 | B63: 01/10/2026 | C63: Proveedor Ficticio X 021, S.L. | D63: 21584.14 | E63: 0 | F63: Aceptado | G63: Pendiente | H63: SIN FACTURA LOCALIZADA | I63: XPR26-02686 | Proyecto demostracion 02686 | J63: #tecnologia_x044 #entorno_demo | K63: 205
A64: O2690205 | B64: 16/03/2026 | C64: Proveedor Ficticio X 069, S.L. | D64: 6937.34 | E64: 0 | F64: Aceptado | G64: Pendiente | H64: SIN FACTURA LOCALIZADA | I64: XPR26-01839 | Proyecto demostracion 01839 | J64: #finanzas_x137 #entorno_demo | K64: 210
A65: O2690206 | B65: 20/06/2026 | C65: Proveedor Ficticio X 104, S.L. | D65: 4839.77 | E65: 0 | F65: Aceptado | G65: Pendiente | H65: SIN FACTURA LOCALIZADA | J65: #operaciones_x143 #entorno_demo | K65: 211
A66: O2690207 | B66: 14/02/2026 | C66: Proveedor Ficticio X 032, S.L. | D66: 17473.66 | E66: 0 | F66: Aceptado | G66: Pendiente | H66: SIN FACTURA LOCALIZADA | I66: XPR26-01827 | Proyecto demostracion 01827 | J66: #finanzas_x187 #entorno_demo | K66: 212
A67: O2690213 | B67: 08/03/2026 | C67: Proveedor Ficticio X 030, S.L. | D67: 16420.45 | E67: 0 | F67: Aceptado | G67: Pendiente | H67: SIN FACTURA LOCALIZADA | I67: XPR26-02682 | Proyecto demostracion 02682 | J67: #marketing_x145 #entorno_demo | K67: 218
A68: O2690216 | B68: 23/06/2026 | C68: Proveedor Ficticio X 035, S.L. | D68: 16037.68 | E68: 0 | F68: Aceptado | G68: Pendiente | H68: SIN FACTURA LOCALIZADA | I68: XPR26-01211 | Proyecto demostracion 01211 | J68: #comercial_x130 #entorno_demo | K68: 221
A69: O2690219 | B69: 13/09/2026 | C69: Proveedor Ficticio X 043, S.L. | D69: 26074.9 | E69: 0 | F69: Cancelado | G69: Pendiente | H69: CANCELADO / SIN FACTURA | I69: XPR26-00986 | Proyecto demostracion 00986 | J69: #consultoria_x029 #entorno_demo | K69: 224
A70: O2690220 | B70: 22/04/2026 | C70: Proveedor Ficticio X 104, S.L. | D70: 4838.79 | E70: 0 | F70: Aceptado | G70: Pendiente | H70: SIN FACTURA LOCALIZADA | I70: XPR26-02313 | Proyecto demostracion 02313 | J70: #diseno_x218 #entorno_demo | K70: 225
A71: O2690223 | B71: 19/06/2026 | C71: Proveedor Ficticio X 099, S.L. | D71: 11104.18 | E71: 0 | F71: Aceptado | G71: Pendiente | H71: SIN FACTURA LOCALIZADA | I71: XPR26-01496 | Proyecto demostracion 01496 | J71: #consultoria_x089 #entorno_demo | K71: 228
A72: O2690224 | B72: 02/09/2026 | C72: Proveedor Ficticio X 040, S.L. | D72: 515.88 | E72: 0 | F72: Aceptado | G72: Pendiente | H72: SIN FACTURA LOCALIZADA | I72: XPR26-02975 | Proyecto demostracion 02975 | J72: #operaciones_x053 #entorno_demo | K72: 229
A73: O2690229 | B73: 17/06/2026 | C73: Proveedor Ficticio X 051, S.L. | D73: 20615.64 | E73: 0 | F73: Aceptado | G73: Pendiente | H73: SIN FACTURA LOCALIZADA | I73: XPR26-00173 | Proyecto demostracion 00173 | J73: #etiqueta_demo_sin_ceco | K73: 234
A74: O2690251 | B74: 06/08/2026 | C74: Proveedor Ficticio X 046, S.L. | D74: 24448.03 | E74: 0 | F74: Aceptado | G74: Pendiente | H74: SIN FACTURA LOCALIZADA | I74: XPR26-03221 | Proyecto demostracion 03221 | J74: #marketing_x025 #entorno_demo | K74: 256
A75: O2690253 | B75: 26/05/2026 | C75: Proveedor Ficticio X 011, S.L. | D75: 22993.33 | E75: 0 | F75: Aceptado | G75: Pendiente | H75: SIN FACTURA LOCALIZADA | J75: #operaciones_x003 #entorno_demo | K75: 258
A76: O2690254 | B76: 04/03/2026 | C76: Proveedor Ficticio X 159, S.L. | D76: 27165.41 | E76: 0 | F76: Aceptado | G76: Pendiente | H76: SIN FACTURA LOCALIZADA | J76: #tecnologia_x184 #entorno_demo | K76: 259
A77: O2690255 | B77: 12/09/2026 | C77: Proveedor Ficticio X 094, S.L. | D77: 4137.79 | E77: 0 | F77: Aceptado | G77: Pendiente | H77: SIN FACTURA LOCALIZADA | I77: XPR26-02909 | Proyecto demostracion 02909 | J77: #produccion_x151 #entorno_demo | K77: 260
A78: O2690269 | B78: 12/06/2026 | C78: Proveedor Ficticio X 068, S.L. | D78: 25463.34 | E78: 0 | F78: Aceptado | G78: Pendiente | H78: SIN FACTURA LOCALIZADA | I78: XPR26-00209 | Proyecto demostracion 00209 | J78: #comercial_x150 #entorno_demo | K78: 274
A79: O2690276 | B79: 04/07/2026 | C79: Proveedor Ficticio X 105, S.L. | D79: 14224.47 | E79: 0 | F79: Aceptado | G79: Pendiente | H79: SIN FACTURA LOCALIZADA | I79: XPR26-00747 | Proyecto demostracion 00747 | J79: #tecnologia_x224 #entorno_demo | K79: 281
A80: O2690278 | B80: 02/03/2026 | C80: Proveedor Ficticio X 127, S.L. | D80: 6325.28 | E80: 0 | F80: Aceptado | G80: Pendiente | H80: SIN FACTURA LOCALIZADA | J80: #operaciones_x203 #entorno_demo | K80: 283
A81: O2690279 | B81: 01/06/2026 | C81: Proveedor Ficticio X 150, S.L. | D81: 4731.48 | E81: 0 | F81: Aceptado | G81: Pendiente | H81: SIN FACTURA LOCALIZADA | I81: XPR26-00606 | Proyecto demostracion 00606 | J81: #creatividad_x192 #entorno_demo | K81: 284
A82: O2690284 | B82: 26/05/2026 | C82: Proveedor Ficticio X 171, S.L. | D82: 121134.46 | E82: 0 | F82: Aceptado | G82: Pendiente | H82: SIN FACTURA LOCALIZADA | I82: XPR26-02237 | Proyecto demostracion 02237 | J82: #finanzas_x167 #entorno_demo | K82: 289
A83: O2690285 | B83: 22/02/2026 | C83: Proveedor Ficticio X 121, S.L. | D83: 26270.12 | E83: 0 | F83: Aceptado | G83: Pendiente | H83: SIN FACTURA LOCALIZADA | I83: XPR26-03886 | Proyecto demostracion 03886 | J83: #marketing_x205 #entorno_demo | K83: 290
A84: O2690289 | B84: 11/05/2026 | C84: Proveedor Ficticio X 033, S.L. | D84: 12524.76 | E84: 0 | F84: Aceptado | G84: Pendiente | H84: SIN FACTURA LOCALIZADA | I84: XPR26-01419 | Proyecto demostracion 01419 | J84: #tecnologia_x204 #entorno_demo | K84: 294
A85: O2690297 | B85: 24/01/2026 | C85: Proveedor Ficticio X 021, S.L. | D85: 25354.4 | E85: 0 | F85: Aceptado | G85: Pendiente | H85: SIN FACTURA LOCALIZADA | I85: XPR26-01167 | Proyecto demostracion 01167 | J85: #produccion_x111 #entorno_demo | K85: 302
A86: O2690310 | B86: 02/10/2026 | C86: Proveedor Ficticio X 139, S.L. | D86: 22418.8 | E86: 0 | F86: Pendiente | G86: Pendiente | H86: SIN FACTURA LOCALIZADA | I86: XPR26-01517 | Proyecto demostracion 01517 | J86: #operaciones_x253 #entorno_demo | K86: 315
A87: O2690314 | B87: 06/02/2026 | C87: Proveedor Ficticio X 098, S.L. | D87: 25023.42 | E87: 0 | F87: Aceptado | G87: Pendiente | H87: SIN FACTURA LOCALIZADA | J87: #operaciones_x143 #entorno_demo | K87: 319
A88: O2690316 | B88: 01/06/2026 | C88: Proveedor Ficticio X 179, S.L. | D88: 4784.34 | E88: 0 | F88: Aceptado | G88: Pendiente | H88: SIN FACTURA LOCALIZADA | J88: #comercial_x030 #entorno_demo | K88: 321
A89: O2690322 | B89: 05/04/2026 | C89: Proveedor Ficticio X 153, S.L. | D89: 18915.15 | E89: 0 | F89: Aceptado | G89: Pendiente | H89: SIN FACTURA LOCALIZADA | I89: XPR26-03160 | Proyecto demostracion 03160 | J89: #tecnologia_x214 #entorno_demo | K89: 327
A90: O2690327 | B90: 07/06/2026 | C90: Proveedor Ficticio X 123, S.L. | D90: 817.3 | E90: 0 | F90: Aceptado | G90: Pendiente | H90: SIN FACTURA LOCALIZADA | J90: #diseno_x008 #entorno_demo | K90: 332
A91: O2690330 | B91: 12/05/2026 | C91: Proveedor Ficticio X 136, S.L. | D91: 18934.9 | E91: 0 | F91: Pendiente | G91: Pendiente | H91: SIN FACTURA LOCALIZADA | I91: XPR26-00086 | Proyecto demostracion 00086 | J91: #tecnologia_x204 #entorno_demo | K91: 335
A92: O2690331 | B92: 04/05/2026 | C92: Proveedor Ficticio X 028, S.L. | D92: 24610.01 | E92: 0 | F92: Aceptado | G92: Pendiente | H92: SIN FACTURA LOCALIZADA | J92: #diseno_x008 #entorno_demo | K92: 336
A93: O2690332 | B93: 16/01/2026 | C93: Proveedor Ficticio X 170, S.L. | D93: 9278.13 | E93: 0 | F93: Aceptado | G93: Pendiente | H93: SIN FACTURA LOCALIZADA | I93: XPR26-03492 | Proyecto demostracion 03492 | J93: #produccion_x151 #entorno_demo | K93: 337
A94: O2690335 | B94: 02/07/2026 | C94: Proveedor Ficticio X 131, S.L. | D94: 6207.88 | E94: 0 | F94: Aceptado | G94: Pendiente | H94: SIN FACTURA LOCALIZADA | J94: #administracion_x246 #entorno_demo | K94: 340
A95: O2690336 | B95: 22/09/2026 | C95: Proveedor Ficticio X 129, S.L. | D95: 11302.73 | E95: 0 | F95: Aceptado | G95: Pendiente | H95: SIN FACTURA LOCALIZADA | J95: #tecnologia_x054 #entorno_demo | K95: 341
A96: O2690338 | B96: 22/03/2026 | C96: Proveedor Ficticio X 169, S.L. | D96: 21496.34 | E96: 0 | F96: Aceptado | G96: Pendiente | H96: SIN FACTURA LOCALIZADA | J96: #diseno_x008 #entorno_demo | K96: 343
A97: O2690349 | B97: 15/02/2026 | C97: Proveedor Ficticio X 054, S.L. | D97: 18725.54 | E97: 0 | F97: Pendiente | G97: Pendiente | H97: SIN FACTURA LOCALIZADA | J97: #operaciones_x233 #entorno_demo | K97: 354
A98: O2690362 | B98: 22/07/2026 | C98: Proveedor Ficticio X 180, S.L. | D98: 67903.01 | E98: 0 | F98: Aceptado | G98: Pendiente | H98: SIN FACTURA LOCALIZADA | I98: XPR26-02748 | Proyecto demostracion 02748 | J98: #etiqueta_demo_sin_ceco | K98: 367
A99: O2690363 | B99: 01/05/2026 | C99: Proveedor Ficticio X 185, S.L. | D99: 44620.02 | E99: 0 | F99: Aceptado | G99: Pendiente | H99: SIN FACTURA LOCALIZADA | I99: XPR26-01745 | Proyecto demostracion 01745 | J99: #marketing_x125 #entorno_demo | K99: 368
A100: O2690364 | B100: 06/03/2026 | C100: Proveedor Ficticio X 133, S.L. | D100: 19697.29 | E100: 0 | F100: Cancelado | G100: Pendiente | H100: CANCELADO / SIN FACTURA | I100: XPR26-01652 | Proyecto demostracion 01652 | J100: #finanzas_x187 #entorno_demo | K100: 369
A101: O2690365 | B101: 05/05/2026 | C101: Proveedor Ficticio X 042, S.L. | D101: 2569.12 | E101: 0 | F101: Aceptado | G101: Pendiente | H101: SIN FACTURA LOCALIZADA | I101: XPR26-03386 | Proyecto demostracion 03386 | J101: #creatividad_x142 #entorno_demo | K101: 370
A102: O2690368 | B102: 01/09/2026 | C102: Proveedor Ficticio X 138, S.L. | D102: 14846.94 | E102: 0 | F102: Aceptado | G102: Pendiente | H102: SIN FACTURA LOCALIZADA | I102: XPR26-00316 | Proyecto demostracion 00316 | J102: #finanzas_x077 #entorno_demo | K102: 373
...

Sheet 07_Sin_PO
A1: FACTURAS SIN PO ENLAZADA
A3: No todas las compras requieren PO; aplicar política de autorizaciones antes de concluir incumplimientos.
A5: Factura | B5: Emisión | C5: Proveedor | D5: Descripción | E5: Total € | F5: Ref PO no localizada | G5: Estado | H5: Proyecto | I5: Fila origen
A6: FX26-000001 | B6: 26/02/2026 | C6: Proveedor Ficticio X 233, S.L. | D6: Subcontratacion de proyectos | servicio ficticio 0001 | E6: -12760.68 | G6: Pagado | H6: XPR26-03528 | Proyecto demostracion 03528 | I6: 6
A7: FX26-000002 | B7: 11/09/2026 | C7: Proveedor Ficticio X 194, S.L. | D7: Equipamiento tecnologico | servicio ficticio 0002 | E7: 14936.74 | G7: Pagado | I7: 7
A8: FX26-000003 | B8: 03/04/2026 | C8: Proveedor Ficticio X 033, S.L. | D8: Alquiler de equipos | servicio ficticio 0003 | E8: 8431.09 | G8: Pagado | I8: 8
A9: FX26-000004 | B9: 31/03/2026 | C9: Proveedor Ficticio X 129, S.L. | D9: Mantenimiento informatico | servicio ficticio 0004 | E9: 16991.07 | G9: Pagado | I9: 9
A10: FX26-000006 | B10: 11/01/2026 | C10: Proveedor Ficticio X 111, S.L. | D10: Produccion audiovisual | servicio ficticio 0006 | E10: 13054.44 | G10: Vencido | I10: 11
A11: FX26-000008 | B11: 13/09/2026 | C11: Proveedor Ficticio X 067, S.L. | D11: Traduccion y localizacion | servicio ficticio 0008 | E11: 1655.83 | G11: Pendiente | H11: XPR26-02313 | Proyecto demostracion 02313 | I11: 13
A12: FX26-000009 | B12: 22/03/2026 | C12: Proveedor Ficticio X 156, S.L. | D12: Campana de marketing | servicio ficticio 0009 | E12: 10613.48 | G12: Pagado | H12: XPR26-02771 | Proyecto demostracion 02771 | I12: 14
A13: FX26-000010 | B13: 08/04/2026 | C13: Proveedor Ficticio X 135, S.L. | D13: Campana de marketing | servicio ficticio 0010 | E13: 956.89 | G13: Pagado | I13: 15
A14: FX26-000012 | B14: 03/06/2026 | C14: Proveedor Ficticio X 103, S.L. | D14: Equipamiento tecnologico | servicio ficticio 0012 | E14: 12304.53 | G14: Vencido | H14: XPR26-01517 | Proyecto demostracion 01517 | I14: 17
A15: FX26-000013 | B15: 18/07/2026 | C15: Proveedor Ficticio X 148, S.L. | D15: Servicios logisticos | servicio ficticio 0013 | E15: 16322.38 | G15: Vencido | H15: XPR26-02407 | Proyecto demostracion 02407 | I15: 18
A16: FX26-000014 | B16: 22/02/2026 | C16: Proveedor Ficticio X 191, S.L. | D16: Campana de marketing | servicio ficticio 0014 | E16: 10137 | G16: Pagado | I16: 19
A17: FX26-000015 | B17: 27/01/2026 | C17: Proveedor Ficticio X 148, S.L. | D17: Servicios de diseno | servicio ficticio 0015 | E17: 10775.04 | G17: Pagado | H17: XPR26-02563 | Proyecto demostracion 02563 | I17: 20
A18: FX26-000016 | B18: 25/06/2026 | C18: Proveedor Ficticio X 030, S.L. | D18: Asesoria operativa | servicio ficticio 0016 | E18: 4375.16 | G18: Vencido | H18: XPR26-03887 | Proyecto demostracion 03887 | I18: 21
A19: FX26-000018 | B19: 14/01/2026 | C19: Proveedor Ficticio X 061, S.L. | D19: Material de oficina | servicio ficticio 0018 | E19: 1692.04 | G19: Pagado | H19: XPR26-03880 | Proyecto demostracion 03880 | I19: 23
A20: FX26-000019 | B20: 12/01/2026 | C20: Proveedor Ficticio X 200, S.L. | D20: Produccion audiovisual | servicio ficticio 0019 | E20: 10564.42 | G20: Vencido | I20: 24
A21: FX26-000020 | B21: 14/08/2026 | C21: Proveedor Ficticio X 193, S.L. | D21: Equipamiento tecnologico | servicio ficticio 0020 | E21: 10710.44 | G21: Vencido | I21: 25
A22: FX26-000021 | B22: 17/07/2026 | C22: Proveedor Ficticio X 235, S.L. | D22: Equipamiento tecnologico | servicio ficticio 0021 | E22: 8840.68 | G22: Vencido | I22: 26
A23: FX26-000022 | B23: 03/07/2026 | C23: Proveedor Ficticio X 026, S.L. | D23: Asesoria operativa | servicio ficticio 0022 | E23: 6811.76 | G23: Vencido | H23: XPR26-01689 | Proyecto demostracion 01689 | I23: 27
A24: FX26-000023 | B24: 25/07/2026 | C24: Proveedor Ficticio X 021, S.L. | D24: Material de oficina | servicio ficticio 0023 | E24: 11110.57 | G24: Pagado | H24: XPR26-01043 | Proyecto demostracion 01043 | I24: 28
A25: FX26-000024 | B25: 22/05/2026 | C25: Proveedor Ficticio X 123, S.L. | D25: Mantenimiento informatico | servicio ficticio 0024 | E25: 8336.1 | G25: Vencido | I25: 29
A26: FX26-000025 | B26: 31/08/2026 | C26: Proveedor Ficticio X 189, S.L. | D26: Mantenimiento informatico | servicio ficticio 0025 | E26: 15249.25 | G26: Pagado | H26: XPR26-03492 | Proyecto demostracion 03492 | I26: 30
A27: FX26-000026 | B27: 28/09/2026 | C27: Proveedor Ficticio X 139, S.L. | D27: Licencias de software | servicio ficticio 0026 | E27: 10216.13 | G27: Pagado | H27: XPR26-03582 | Proyecto demostracion 03582 | I27: 31
A28: FX26-000028 | B28: 27/07/2026 | C28: Proveedor Ficticio X 234, S.L. | D28: Asistencia tecnica | servicio ficticio 0028 | E28: 12183.79 | G28: Pagado | I28: 33
A29: FX26-000029 | B29: 31/08/2026 | C29: Proveedor Ficticio X 226, S.L. | D29: Subcontratacion de proyectos | servicio ficticio 0029 | E29: 17125.51 | G29: Pagado | I29: 34
A30: FX26-000030 | B30: 17/01/2026 | C30: Proveedor Ficticio X 167, S.L. | D30: Produccion de contenido | servicio ficticio 0030 | E30: 8523.51 | G30: Pagado | H30: XPR26-00039 | Proyecto demostracion 00039 | I30: 35
A31: FX26-000031 | B31: 10/01/2026 | C31: Proveedor Ficticio X 031, S.L. | D31: Material de oficina | servicio ficticio 0031 | E31: 12482.46 | G31: Pagado | I31: 36
A32: FX26-000032 | B32: 05/06/2026 | C32: Proveedor Ficticio X 173, S.L. | D32: Produccion de contenido | servicio ficticio 0032 | E32: 3260.93 | G32: Pagado | I32: 37
A33: FX26-000033 | B33: 11/02/2026 | C33: Proveedor Ficticio X 034, S.L. | D33: Produccion audiovisual | servicio ficticio 0033 | E33: 14009.19 | G33: Pagado | I33: 38
A34: FX26-000034 | B34: 19/06/2026 | C34: Proveedor Ficticio X 203, S.L. | D34: Mantenimiento informatico | servicio ficticio 0034 | E34: 40.26 | G34: Vencido | H34: XPR26-02580 | Proyecto demostracion 02580 | I34: 39
A35: FX26-000035 | B35: 02/04/2026 | C35: Proveedor Ficticio X 224, S.L. | D35: Produccion audiovisual | servicio ficticio 0035 | E35: 6787.48 | G35: Vencido | H35: XPR26-01827 | Proyecto demostracion 01827 | I35: 40
A36: FX26-000036 | B36: 11/05/2026 | C36: Proveedor Ficticio X 135, S.L. | D36: Asesoria operativa | servicio ficticio 0036 | E36: 12490.94 | G36: Vencido | H36: XPR26-03887 | Proyecto demostracion 03887 | I36: 41
A37: FX26-000037 | B37: 18/07/2026 | C37: Proveedor Ficticio X 259, S.L. | D37: Campana de marketing | servicio ficticio 0037 | E37: 15382.5 | G37: Vencido | I37: 42
A38: FX26-000038 | B38: 28/04/2026 | C38: Proveedor Ficticio X 240, S.L. | D38: Campana de marketing | servicio ficticio 0038 | E38: 13304.88 | G38: Vencido | I38: 43
A39: FX26-000040 | B39: 10/02/2026 | C39: Proveedor Ficticio X 186, S.L. | D39: Mantenimiento informatico | servicio ficticio 0040 | E39: 12142.88 | G39: Pagado | I39: 45
A40: FX26-000041 | B40: 11/07/2026 | C40: Proveedor Ficticio X 076, S.L. | D40: Produccion audiovisual | servicio ficticio 0041 | E40: 5804.94 | G40: Vencido | H40: XPR26-01281 | Proyecto demostracion 01281 | I40: 46
A41: FX26-000042 | B41: 07/05/2026 | C41: Proveedor Ficticio X 176, S.L. | D41: Produccion de contenido | servicio ficticio 0042 | E41: 12592.46 | G41: Pagado | H41: XPR26-03880 | Proyecto demostracion 03880 | I41: 47
A42: FX26-000043 | B42: 11/06/2026 | C42: Proveedor Ficticio X 217, S.L. | D42: Subcontratacion de proyectos | servicio ficticio 0043 | E42: 15532.61 | G42: Vencido | H42: XPR26-00086 | Proyecto demostracion 00086 | I42: 48
A43: FX26-000044 | B43: 23/02/2026 | C43: Proveedor Ficticio X 218, S.L. | D43: Material de oficina | servicio ficticio 0044 | E43: 13205.11 | G43: Vencido | I43: 49
A44: FX26-000045 | B44: 27/05/2026 | C44: Proveedor Ficticio X 124, S.L. | D44: Asesoria operativa | servicio ficticio 0045 | E44: 909.27 | G44: Vencido | I44: 50
A45: FX26-000047 | B45: 15/03/2026 | C45: Proveedor Ficticio X 161, S.L. | D45: Servicios profesionales | servicio ficticio 0047 | E45: 10416.4 | G45: Pagado | I45: 52
A46: FX26-000048 | B46: 28/07/2026 | C46: Proveedor Ficticio X 063, S.L. | D46: Material de oficina | servicio ficticio 0048 | E46: 34374.5 | G46: Pagado | I46: 53
A47: FX26-000049 | B47: 03/03/2026 | C47: Proveedor Ficticio X 169, S.L. | D47: Produccion de contenido | servicio ficticio 0049 | E47: 826.56 | G47: Pagado | H47: XPR26-01546 | Proyecto demostracion 01546 | I47: 54
A48: FX26-000050 | B48: 05/03/2026 | C48: Proveedor Ficticio X 238, S.L. | D48: Subcontratacion de proyectos | servicio ficticio 0050 | E48: 669.99 | G48: Pagado | H48: XPR26-03245 | Proyecto demostracion 03245 | I48: 55
A49: FX26-000051 | B49: 15/03/2026 | C49: Proveedor Ficticio X 170, S.L. | D49: Licencias de software | servicio ficticio 0051 | E49: 12682.18 | G49: Vencido | H49: XPR26-03792 | Proyecto demostracion 03792 | I49: 56
A50: FX26-000052 | B50: 01/02/2026 | C50: Proveedor Ficticio X 027, S.L. | D50: Equipamiento tecnologico | servicio ficticio 0052 | E50: 6151.01 | G50: Pagado | H50: XPR26-03880 | Proyecto demostracion 03880 | I50: 57
A51: FX26-000053 | B51: 15/10/2026 | C51: Proveedor Ficticio X 018, S.L. | D51: Produccion de contenido | servicio ficticio 0053 | E51: 4699.71 | G51: Pendiente | I51: 58
A52: FX26-000055 | B52: 20/03/2026 | C52: Proveedor Ficticio X 178, S.L. | D52: Servicios logisticos | servicio ficticio 0055 | E52: 5985.98 | G52: Vencido | H52: XPR26-00930 | Proyecto demostracion 00930 | I52: 60
A53: FX26-000056 | B53: 09/09/2026 | C53: Proveedor Ficticio X 222, S.L. | D53: Produccion audiovisual | servicio ficticio 0056 | E53: 1422.15 | G53: Vencido | I53: 61
A54: FX26-000058 | B54: 01/08/2026 | C54: Proveedor Ficticio X 051, S.L. | D54: Servicios logisticos | servicio ficticio 0058 | E54: 3844.92 | G54: Parcialmente | H54: XPR26-01037 | Proyecto demostracion 01037 | I54: 63
A55: FX26-000059 | B55: 23/08/2026 | C55: Proveedor Ficticio X 081, S.L. | D55: Alquiler de equipos | servicio ficticio 0059 | E55: 7503.68 | G55: Pagado | I55: 64
A56: FX26-000060 | B56: 01/02/2026 | C56: Proveedor Ficticio X 174, S.L. | D56: Asesoria operativa | servicio ficticio 0060 | E56: 14293.6 | G56: Pagado | I56: 65
A57: FX26-000061 | B57: 16/07/2026 | C57: Proveedor Ficticio X 082, S.L. | D57: Servicios profesionales | servicio ficticio 0061 | E57: 1407.25 | G57: Pagado | H57: XPR26-00324 | Proyecto demostracion 00324 | I57: 66
A58: FX26-000062 | B58: 26/01/2026 | C58: Proveedor Ficticio X 069, S.L. | D58: Mantenimiento informatico | servicio ficticio 0062 | E58: 7423.91 | G58: Vencido | I58: 67
A59: FX26-000063 | B59: 29/04/2026 | C59: Proveedor Ficticio X 173, S.L. | D59: Equipamiento tecnologico | servicio ficticio 0063 | E59: 5545.31 | G59: Pagado | I59: 68
A60: FX26-000064 | B60: 13/04/2026 | C60: Proveedor Ficticio X 084, S.L. | D60: Material de oficina | servicio ficticio 0064 | E60: 9120.48 | G60: Vencido | H60: XPR26-01117 | Proyecto demostracion 01117 | I60: 69
A61: FX26-000065 | B61: 16/05/2026 | C61: Proveedor Ficticio X 239, S.L. | D61: Licencias de software | servicio ficticio 0065 | E61: 17094.3 | G61: Vencido | I61: 70
A62: FX26-000067 | B62: 09/05/2026 | C62: Proveedor Ficticio X 184, S.L. | D62: Equipamiento tecnologico | servicio ficticio 0067 | E62: 11288.33 | G62: Vencido | I62: 72
A63: FX26-000068 | B63: 01/02/2026 | C63: Proveedor Ficticio X 237, S.L. | D63: Subcontratacion de proyectos | servicio ficticio 0068 | E63: 4537.35 | G63: Vencido | I63: 73
A64: FX26-000070 | B64: 11/06/2026 | C64: Proveedor Ficticio X 152, S.L. | D64: Asesoria operativa | servicio ficticio 0070 | E64: 2851.03 | G64: Pagado | I64: 75
A65: FX26-000071 | B65: 18/02/2026 | C65: Proveedor Ficticio X 153, S.L. | D65: Produccion de contenido | servicio ficticio 0071 | E65: 6888.78 | G65: Vencido | H65: XPR26-01211 | Proyecto demostracion 01211 | I65: 76
A66: FX26-000072 | B66: 22/04/2026 | C66: Proveedor Ficticio X 185, S.L. | D66: Servicios logisticos | servicio ficticio 0072 | E66: 11883.63 | G66: Pagado | H66: XPR26-03653 | Proyecto demostracion 03653 | I66: 77
A67: FX26-000073 | B67: 30/08/2026 | C67: Proveedor Ficticio X 231, S.L. | D67: Equipamiento tecnologico | servicio ficticio 0073 | E67: 7449.39 | G67: Vencido | I67: 78
A68: FX26-000074 | B68: 26/07/2026 | C68: Proveedor Ficticio X 032, S.L. | D68: Servicios logisticos | servicio ficticio 0074 | E68: 4559.8 | G68: Pagado | I68: 79
A69: FX26-000075 | B69: 11/07/2026 | C69: Proveedor Ficticio X 023, S.L. | D69: Subcontratacion de proyectos | servicio ficticio 0075 | E69: 7782.6 | G69: Pagado | H69: XPR26-03460 | Proyecto demostracion 03460 | I69: 80
A70: FX26-000076 | B70: 21/01/2026 | C70: Proveedor Ficticio X 045, S.L. | D70: Subcontratacion de proyectos | servicio ficticio 0076 | E70: 4303.89 | G70: Pagado | I70: 81
A71: FX26-000077 | B71: 14/04/2026 | C71: Proveedor Ficticio X 141, S.L. | D71: Campana de marketing | servicio ficticio 0077 | E71: 9817.34 | G71: Vencido | H71: XPR26-00557 | Proyecto demostracion 00557 | I71: 82
A72: FX26-000078 | B72: 06/03/2026 | C72: Proveedor Ficticio X 125, S.L. | D72: Subcontratacion de proyectos | servicio ficticio 0078 | E72: 6406.57 | G72: Vencido | H72: XPR26-02296 | Proyecto demostracion 02296 | I72: 83
A73: FX26-000079 | B73: 29/01/2026 | C73: Proveedor Ficticio X 016, S.L. | D73: Servicios profesionales | servicio ficticio 0079 | E73: 12487.92 | G73: Pagado | H73: XPR26-00318 | Proyecto demostracion 00318 | I73: 84
A74: FX26-000080 | B74: 04/03/2026 | C74: Proveedor Ficticio X 128, S.L. | D74: Produccion audiovisual | servicio ficticio 0080 | E74: 5843.31 | G74: Vencido | I74: 85
A75: FX26-000081 | B75: 07/05/2026 | C75: Proveedor Ficticio X 102, S.L. | D75: Equipamiento tecnologico | servicio ficticio 0081 | E75: 3015.85 | G75: Pagado | I75: 86
A76: FX26-000083 | B76: 15/07/2026 | C76: Proveedor Ficticio X 026, S.L. | D76: Servicios de diseno | servicio ficticio 0083 | E76: 4960.27 | G76: Pagado | H76: XPR26-00741 | Proyecto demostracion 00741 | I76: 88
A77: FX26-000084 | B77: 16/08/2026 | C77: Proveedor Ficticio X 131, S.L. | D77: Subcontratacion de proyectos | servicio ficticio 0084 | E77: 13501.86 | G77: Pagado | H77: XPR26-02892 | Proyecto demostracion 02892 | I77: 89
A78: FX26-000085 | B78: 24/03/2026 | C78: Proveedor Ficticio X 071, S.L. | D78: Licencias de software | servicio ficticio 0085 | E78: 16363.35 | G78: Pagado | I78: 90
A79: FX26-000087 | B79: 23/07/2026 | C79: Proveedor Ficticio X 176, S.L. | D79: Asesoria operativa | servicio ficticio 0087 | E79: 7847 | G79: Vencido | H79: XPR26-01827 | Proyecto demostracion 01827 | I79: 92
A80: FX26-000088 | B80: 07/02/2026 | C80: Proveedor Ficticio X 141, S.L. | D80: Campana de marketing | servicio ficticio 0088 | E80: 11053.11 | G80: Vencido | H80: XPR26-00464 | Proyecto demostracion 00464 | I80: 93
A81: FX26-000071 | B81: 18/02/2026 | C81: Proveedor Ficticio X 153, S.L. | D81: Produccion de contenido | servicio ficticio 0089 | E81: 6888.78 | G81: Pendiente | H81: XPR26-01211 | Proyecto demostracion 01211 | I81: 94
A82: FX26-000090 | B82: 27/06/2026 | C82: Proveedor Ficticio X 149, S.L. | D82: Asistencia tecnica | servicio ficticio 0090 | E82: 1793.28 | G82: Pagado | H82: XPR26-00747 | Proyecto demostracion 00747 | I82: 95
A83: FX26-000091 | B83: 16/05/2026 | C83: Proveedor Ficticio X 086, S.L. | D83: Asesoria operativa | servicio ficticio 0091 | E83: 870 | G83: Vencido | I83: 96
A84: FX26-000092 | B84: 13/10/2026 | C84: Proveedor Ficticio X 039, S.L. | D84: Equipamiento tecnologico | servicio ficticio 0092 | E84: 11430.75 | G84: Pendiente | I84: 97
A85: FX26-000093 | B85: 17/06/2026 | C85: Proveedor Ficticio X 156, S.L. | D85: Mantenimiento informatico | servicio ficticio 0093 | E85: 9600.2 | G85: Pagado | H85: XPR26-03880 | Proyecto demostracion 03880 | I85: 98
A86: FX26-000094 | B86: 19/04/2026 | C86: Proveedor Ficticio X 253, S.L. | D86: Material de oficina | servicio ficticio 0094 | E86: 14165.08 | G86: Pagado | I86: 99
A87: FX26-000095 | B87: 31/05/2026 | C87: Proveedor Ficticio X 173, S.L. | D87: Mantenimiento informatico | servicio ficticio 0095 | E87: 2983.97 | G87: Vencido | I87: 100
A88: FX26-000097 | B88: 19/02/2026 | C88: Proveedor Ficticio X 165, S.L. | D88: Servicios de diseno | servicio ficticio 0097 | E88: 744.93 | G88: Vencido | I88: 102
A89: FX26-000098 | B89: 03/01/2026 | C89: Proveedor Ficticio X 259, S.L. | D89: Servicios profesionales | servicio ficticio 0098 | E89: 11837.97 | G89: Vencido | I89: 103
A90: FX26-000099 | B90: 03/01/2026 | C90: Proveedor Ficticio X 218, S.L. | D90: Traduccion y localizacion | servicio ficticio 0099 | E90: 34468.39 | G90: Pagado | H90: XPR26-01668 | Proyecto demostracion 01668 | I90: 104
A91: FX26-000100 | B91: 11/04/2026 | C91: Proveedor Ficticio X 260, S.L. | D91: Servicios de diseno | servicio ficticio 0100 | E91: 6902.54 | G91: Pagado | I91: 105
A92: FX26-000101 | B92: 06/09/2026 | C92: Proveedor Ficticio X 198, S.L. | D92: Material de oficina | servicio ficticio 0101 | E92: 12436.39 | G92: Pagado | I92: 106
A93: FX26-000103 | B93: 11/06/2026 | C93: Proveedor Ficticio X 220, S.L. | D93: Mantenimiento informatico | servicio ficticio 0103 | E93: 14765.65 | G93: Vencido | I93: 108
A94: FX26-000105 | B94: 04/09/2026 | C94: Proveedor Ficticio X 022, S.L. | D94: Produccion de contenido | servicio ficticio 0105 | E94: 15769.82 | G94: Vencido | I94: 110
A95: FX26-000106 | B95: 22/02/2026 | C95: Proveedor Ficticio X 207, S.L. | D95: Licencias de software | servicio ficticio 0106 | E95: 3134.08 | G95: Vencido | I95: 111
A96: FX26-000108 | B96: 01/10/2026 | C96: Proveedor Ficticio X 209, S.L. | D96: Subcontratacion de proyectos | servicio ficticio 0108 | E96: 995.26 | G96: Pagado | H96: XPR26-00130 | Proyecto demostracion 00130 | I96: 113
A97: FX26-000109 | B97: 26/02/2026 | C97: Proveedor Ficticio X 211, S.L. | D97: Traduccion y localizacion | servicio ficticio 0109 | E97: 11623.37 | G97: Pagado | I97: 114
A98: FX26-000110 | B98: 08/06/2026 | C98: Proveedor Ficticio X 145, S.L. | D98: Mantenimiento informatico | servicio ficticio 0110 | E98: 9414.51 | G98: Pagado | H98: XPR26-00318 | Proyecto demostracion 00318 | I98: 115
A99: FX26-000111 | B99: 16/03/2026 | C99: Proveedor Ficticio X 014, S.L. | D99: Traduccion y localizacion | servicio ficticio 0111 | E99: 3727.3 | G99: Vencido | H99: XPR26-01615 | Proyecto demostracion 01615 | I99: 116
A100: FX26-000112 | B100: 16/09/2026 | C100: Proveedor Ficticio X 041, S.L. | D100: Subcontratacion de proyectos | servicio ficticio 0112 | E100: 8632.5 | G100: Pagado | H100: XPR26-03762 | Proyecto demostracion 03762 | I100: 117
A101: FX26-000113 | B101: 02/03/2026 | C101: Proveedor Ficticio X 132, S.L. | D101: Alquiler de equipos | servicio ficticio 0113 | E101: 11382.15 | G101: Pagado | I101: 118
A102: FX26-000115 | B102: 09/01/2026 | C102: Proveedor Ficticio X 200, S.L. | D102: Asistencia tecnica | servicio ficticio 0115 | E102: 7089.17 | G102: Pagado | H102: XPR26-03114 | Proyecto demostracion 03114 | I102: 120
...

Sheet 08_Duplicados
A1: DETECCIÓN DE DUPLICIDADES POTENCIALES
A3: Indicadores: proveedor+numero o proveedor+fecha+importe; requieren evidencia de facturas originales.
A5: Tipo | B5: Factura | C5: Proveedor | D5: Fecha | E5: Total € | F5: Estado | G5: Fila origen
A6: ID REPETIDO | B6: FX26-000071 | C6: Proveedor Ficticio X 153, S.L. | D6: 18/02/2026 | E6: 6888.78 | F6: Vencido | G6: 76
A7: ID REPETIDO | B7: FX26-000071 | C7: Proveedor Ficticio X 153, S.L. | D7: 18/02/2026 | E7: 6888.78 | F7: Pendiente | G7: 94
A8: ID REPETIDO | B8: FX26-000241 | C8: Proveedor Ficticio X 148, S.L. | D8: 15/04/2026 | E8: 2340.21 | F8: Vencido | G8: 246
A9: ID REPETIDO | B9: FX26-000241 | C9: Proveedor Ficticio X 148, S.L. | D9: 15/04/2026 | E9: 2340.21 | F9: Pendiente | G9: 263
A10: ID REPETIDO | B10: FX26-000322 | C10: Proveedor Ficticio X 176, S.L. | D10: 03/05/2026 | E10: 13218.97 | F10: Pagado | G10: 327
A11: ID REPETIDO | B11: FX26-000322 | C11: Proveedor Ficticio X 176, S.L. | D11: 03/05/2026 | E11: 13218.97 | F11: Pendiente | G11: 348
A12: ID REPETIDO | B12: FX26-000511 | C12: Proveedor Ficticio X 161, S.L. | D12: 25/01/2026 | E12: 2773.05 | F12: Vencido | G12: 516
A13: ID REPETIDO | B13: FX26-000511 | C13: Proveedor Ficticio X 161, S.L. | D13: 25/01/2026 | E13: 2773.05 | F13: Pendiente | G13: 547
A14: ID REPETIDO | B14: FX26-000802 | C14: Proveedor Ficticio X 239, S.L. | D14: 08/08/2026 | E14: 7259.06 | F14: Pagado | G14: 807
A15: ID REPETIDO | B15: FX26-000802 | C15: Proveedor Ficticio X 239, S.L. | D15: 08/08/2026 | E15: 7259.06 | F15: Pendiente | G15: 829
A16: ID REPETIDO | B16: FX26-001011 | C16: Proveedor Ficticio X 105, S.L. | D16: 01/09/2026 | E16: -16036.29 | F16: Pagado | G16: 1016
A17: ID REPETIDO | B17: FX26-001011 | C17: Proveedor Ficticio X 105, S.L. | D17: 01/09/2026 | E17: -16036.29 | F17: Pendiente | G17: 1026
... A33: COINCIDENCIA INDICIARIA | B33: FX26-001701 | C33: Proveedor Ficticio X 193, S.L. | D33: 02/06/2026 | E33: 14525.25 | F33: Pendiente | G33: 1728

Sheet 09_Fechas
A1: CONTROLES DE FECHAS / CUT-OFF
A3: Comparaciones preliminares. PO ≠ fecha de prestación; la diferencia de meses NO prueba ajuste.
A5: Tipo | B5: Documento(s) | C5: Fecha inicial | D5: Fecha comparada | E5: Observación | F5: Total factura € | G5: Proveedor
A6: PO-FACTURA | B6: O2690001 / FX26-000046 | C6: 19/07/2026 | D6: 04/08/2026 | E6: PO y factura en distinto mes (no demuestra error de corte) | F6: 12042.75 | G6: Proveedor Ficticio X 042, S.L.
A7: PO-FACTURA | B7: O2690004 / FX26-001774 | C7: 25/03/2026 | D7: 19/04/2026 | E7: PO y factura en distinto mes (no demuestra error de corte) | F7: 10467.11 | G7: Proveedor Ficticio X 004, S.L.
A8: PO-FACTURA | B8: O2690004 / FX26-002004 | C8: 25/03/2026 | D8: 12/03/2026 | E8: Factura emitida antes de PO (verificar autorización) | F8: 14027.86 | G8: Proveedor Ficticio X 004, S.L.
A9: PO-FACTURA | B9: O2690004 / FX26-002069 | C9: 25/03/2026 | D9: 09/06/2026 | E9: PO y factura en distinto mes (no demuestra error de corte) | F9: 3623.28 | G9: Proveedor Ficticio X 004, S.L.
A10: PO-FACTURA | B10: O2690009 / FX26-001284 | C10: 29/07/2026 | D10: 23/09/2026 | E10: PO y factura en distinto mes (no demuestra error de corte) | F10: 312.25 | G10: Proveedor Ficticio X 152, S.L.
A11: PO-FACTURA | B11: O2690010 / FX26-000846 | C11: 17/03/2026 | D11: 07/06/2026 | E11: PO y factura en distinto mes (no demuestra error de corte) | F11: 10295.61 | G11: Proveedor Ficticio X 032, S.L.
A12: PO-FACTURA | B12: O2690010 / FX26-001068 | C12: 17/03/2026 | D12: 11/03/2026 | E12: Factura emitida antes de PO (verificar autorización) | F12: 9942.46 | G12: Proveedor Ficticio X 032, S.L.
A13: PO-FACTURA | B13: O2690010 / FX26-001993 | C13: 17/03/2026 | D13: 14/06/2026 | E13: PO y factura en distinto mes (no demuestra error de corte) | F13: 4288.98 | G13: Proveedor Ficticio X 032, S.L.
A14: PO-FACTURA | B14: O2690011 / FX26-001875 | C14: 06/09/2026 | D14: 03/10/2026 | E14: PO y factura en distinto mes (no demuestra error de corte) | F14: 6786.53 | G14: Proveedor Ficticio X 138, S.L.
A15: PO-FACTURA | B15: O2690013 / FX26-000845 | C15: 23/03/2026 | D15: 18/03/2026 | E15: Factura emitida antes de PO (verificar autorización) | F15: 14145.04 | G15: Proveedor Ficticio X 095, S.L.
A16: PO-FACTURA | B16: O2690014 / FX26-000230 | C16: 05/05/2026 | D16: 09/07/2026 | E16: PO y factura en distinto mes (no demuestra error de corte) | F16: 15928.27 | G16: Proveedor Ficticio X 137, S.L.
A17: PO-FACTURA | B17: O2690015 / FX26-001256 | C17: 24/06/2026 | D17: 23/08/2026 | E17: PO y factura en distinto mes (no demuestra error de corte) | F17: 10439.37 | G17: Proveedor Ficticio X 123, S.L.
... A318: PO-FACTURA | B318: O2690427 / FX26-001007 | C318: 06/06/2026 | D318: 24/07/2026 | E318: PO y factura en distinto mes (no demuestra error de corte) | F318: 20398.48 | G318: Proveedor Ficticio X 142, S.L.

Sheet 10_CECO_Proyecto
A1: VALIDACIONES CECO Y PROYECTO
A3: Las ausencias pueden ser admisibles; solo 'no catalogado' indica fallo de integridad referencial.
A5: Tipo | B5: Referencia | C5: Proveedor | D5: Etiquetas | E5: Validación CECO | F5: Proyecto | G5: Validación proyecto | H5: Total €
A6: FACTURA | B6: FX26-000099 | C6: Proveedor Ficticio X 218, S.L. | E6: NO INFORMADO | F6: XPR26-01668 | Proyecto demostracion 01668 | G6: VALIDO | H6: 34468.39
A7: FACTURA | B7: FX26-000122 | C7: Proveedor Ficticio X 112, S.L. | E7: NO INFORMADO | F7: XPR26-02169 | Proyecto demostracion 02169 | G7: VALIDO | H7: 19679.25
A8: FACTURA | B8: FX26-000142 | C8: Proveedor Ficticio X 073, S.L. | E8: NO INFORMADO | F8: XPR26-01443 | Proyecto demostracion 01443 | G8: VALIDO | H8: 10180.09
A9: FACTURA | B9: FX26-000167 | C9: Proveedor Ficticio X 002, S.L. | E9: NO INFORMADO | G9: NO INFORMADO | H9: 4064.49
A10: FACTURA | B10: FX26-000199 | C10: Proveedor Ficticio X 145, S.L. | E10: NO INFORMADO | G10: NO INFORMADO | H10: 10553.56
A11: FACTURA | B11: FX26-000230 | C11: Proveedor Ficticio X 137, S.L. | E11: NO INFORMADO | F11: XPR26-01348 | Proyecto demostracion 01348 | G11: VALIDO | H11: 15928.27
A12: FACTURA | B12: FX26-000241 | C12: Proveedor Ficticio X 148, S.L. | E12: NO INFORMADO | G12: NO INFORMADO | H12: 2340.21
A13: FACTURA | B13: FX26-000245 | C13: Proveedor Ficticio X 233, S.L. | E13: NO INFORMADO | G13: NO INFORMADO | H13: 7955.76
A14: FACTURA | B14: FX26-000375 | C14: Proveedor Ficticio X 144, S.L. | E14: NO INFORMADO | G14: NO INFORMADO | H14: 18897.28
A15: FACTURA | B15: FX26-000432 | C15: Proveedor Ficticio X 072, S.L. | E15: NO INFORMADO | F15: XPR26-00986 | Proyecto demostracion 00986 | G15: VALIDO | H15: 2267.85
A16: FACTURA | B16: FX26-000440 | C16: Proveedor Ficticio X 091, S.L. | E16: NO INFORMADO | G16: NO INFORMADO | H16: 5002.55
A17: FACTURA | B17: FX26-000445 | C17: Proveedor Ficticio X 160, S.L. | E17: NO INFORMADO | G17: NO INFORMADO | H17: 13207.77
A18: FACTURA | B18: FX26-000517 | C18: Proveedor Ficticio X 050, S.L. | E18: NO INFORMADO | F18: XPR26-00126 | Proyecto demostracion 00126 | G18: VALIDO | H18: 1699.61
A19: FACTURA | B19: FX26-000560 | C19: Proveedor Ficticio X 115, S.L. | E19: NO INFORMADO | G19: NO INFORMADO | H19: 13098.59
A20: FACTURA | B20: FX26-000624 | C20: Proveedor Ficticio X 162, S.L. | E20: NO INFORMADO | G20: NO INFORMADO | H20: 11322.2
A21: FACTURA | B21: FX26-000625 | C21: Proveedor Ficticio X 055, S.L. | E21: NO INFORMADO | G21: NO INFORMADO | H21: 5994.56
A22: FACTURA | B22: FX26-000753 | C22: Proveedor Ficticio X 214, S.L. | E22: NO INFORMADO | G22: NO INFORMADO | H22: 11546.43
A23: FACTURA | B23: FX26-000760 | C23: Proveedor Ficticio X 131, S.L. | E23: NO INFORMADO | G23: NO INFORMADO | H23: 14550.02
A24: FACTURA | B24: FX26-000782 | C24: Proveedor Ficticio X 213, S.L. | E24: NO INFORMADO | F24: XPR26-00986 | Proyecto demostracion 00986 | G24: VALIDO | H24: 16628.63
A25: FACTURA | B25: FX26-000856 | C25: Proveedor Ficticio X 226, S.L. | E25: NO INFORMADO | F25: XPR26-01745 | Proyecto demostracion 01745 | G25: VALIDO | H25: 575.97
A26: FACTURA | B26: FX26-000882 | C26: Proveedor Ficticio X 097, S.L. | E26: NO INFORMADO | F26: XPR26-00464 | Proyecto demostracion 00464 | G26: VALIDO | H26: 14491.47
A27: FACTURA | B27: FX26-000909 | C27: Proveedor Ficticio X 123, S.L. | E27: NO INFORMADO | F27: XPR26-03191 | Proyecto demostracion 03191 | G27: VALIDO | H27: 12877.86
A28: FACTURA | B28: FX26-000941 | C28: Proveedor Ficticio X 069, S.L. | E28: NO INFORMADO | G28: NO INFORMADO | H28: 3387.66
A29: FACTURA | B29: FX26-000990 | C29: Proveedor Ficticio X 253, S.L. | E29: NO INFORMADO | G29: NO INFORMADO | H29: 2566.3
A30: FACTURA | B30: FX26-001182 | C30: Proveedor Ficticio X 003, S.L. | E30: NO INFORMADO | F30: XPR26-02633 | Proyecto demostracion 02633 | G30: VALIDO | H30: 3712.22
A31: FACTURA | B31: FX26-001283 | C31: Proveedor Ficticio X 154, S.L. | E31: NO INFORMADO | G31: NO INFORMADO | H31: 53197.48
A32: FACTURA | B32: FX26-001287 | C32: Proveedor Ficticio X 104, S.L. | E32: NO INFORMADO | F32: XPR26-01668 | Proyecto demostracion 01668 | G32: VALIDO | H32: 566.67
A33: FACTURA | B33: FX26-001335 | C33: Proveedor Ficticio X 024, S.L. | E33: NO INFORMADO | G33: NO INFORMADO | H33: 96733.27
A34: FACTURA | B34: FX26-001336 | C34: Proveedor Ficticio X 030, S.L. | E34: NO INFORMADO | G34: NO INFORMADO | H34: 8123.13
A35: FACTURA | B35: FX26-001438 | C35: Proveedor Ficticio X 075, S.L. | E35: NO INFORMADO | G35: NO INFORMADO | H35: 9713.94
A36: FACTURA | B36: FX26-001524 | C36: Proveedor Ficticio X 063, S.L. | E36: NO INFORMADO | F36: XPR26-02124 | Proyecto demostracion 02124 | G36: VALIDO | H36: 12861.62
A37: FACTURA | B37: FX26-001529 | C37: Proveedor Ficticio X 097, S.L. | E37: NO INFORMADO | G37: NO INFORMADO | H37: 6920
A38: FACTURA | B38: FX26-001548 | C38: Proveedor Ficticio X 186, S.L. | E38: NO INFORMADO | F38: XPR26-01195 | Proyecto demostracion 01195 | G38: VALIDO | H38: 7764.5
A39: FACTURA | B39: FX26-001670 | C39: Proveedor Ficticio X 077, S.L. | E39: NO INFORMADO | G39: NO INFORMADO | H39: 5103.55
A40: FACTURA | B40: FX26-001691 | C40: Proveedor Ficticio X 095, S.L. | E40: NO INFORMADO | F40: XPR26-02402 | Proyecto demostracion 02402 | G40: VALIDO | H40: 12992.53
A41: FACTURA | B41: FX26-001732 | C41: Proveedor Ficticio X 042, S.L. | E41: NO INFORMADO | F41: XPR26-00654 | Proyecto demostracion 00654 | G41: VALIDO | H41: 5780.78
A42: FACTURA | B42: FX26-001759 | C42: Proveedor Ficticio X 080, S.L. | E42: NO INFORMADO | G42: NO INFORMADO | H42: 10644.02
A43: FACTURA | B43: FX26-001911 | C43: Proveedor Ficticio X 235, S.L. | E43: NO INFORMADO | G43: NO INFORMADO | H43: 4772.68
A44: FACTURA | B44: FX26-001965 | C44: Proveedor Ficticio X 186, S.L. | E44: NO INFORMADO | F44: XPR26-00178 | Proyecto demostracion 00178 | G44: VALIDO | H44: 4502.88
A45: FACTURA | B45: FX26-002009 | C45: Proveedor Ficticio X 187, S.L. | E45: NO INFORMADO | G45: NO INFORMADO | H45: 7021.44
A46: FACTURA | B46: FX26-002010 | C46: Proveedor Ficticio X 054, S.L. | E46: NO INFORMADO | F46: XPR26-01281 | Proyecto demostracion 01281 | G46: VALIDO | H46: 3239.84
A47: FACTURA | B47: FX26-002050 | C47: Proveedor Ficticio X 207, S.L. | E47: NO INFORMADO | G47: NO INFORMADO | H47: 9667.52
A48: FACTURA | B48: FX26-002152 | C48: Proveedor Ficticio X 175, S.L. | E48: NO INFORMADO | G48: NO INFORMADO | H48: 5218.55
A49: FACTURA | B49: FX26-002154 | C49: Proveedor Ficticio X 013, S.L. | E49: NO INFORMADO | G49: NO INFORMADO | H49: 6975.03
A50: FACTURA | B50: FX26-002162 | C50: Proveedor Ficticio X 259, S.L. | E50: NO INFORMADO | F50: XPR26-01043 | Proyecto demostracion 01043 | G50: VALIDO | H50: 3823.3
A51: FACTURA | B51: FX26-002194 | C51: Proveedor Ficticio X 121, S.L. | E51: NO INFORMADO | G51: NO INFORMADO | H51: 13710.7
A52: FACTURA | B52: FX26-002207 | C52: Proveedor Ficticio X 013, S.L. | E52: NO INFORMADO | F52: XPR26-03114 | Proyecto demostracion 03114 | G52: VALIDO | H52: 7265.65
A53: FACTURA | B53: FX26-002218 | C53: Proveedor Ficticio X 082, S.L. | E53: NO INFORMADO | G53: NO INFORMADO | H53: 827.94
A54: FACTURA | B54: FX26-002227 | C54: Proveedor Ficticio X 067, S.L. | E54: NO INFORMADO | G54: NO INFORMADO | H54: 19535.81
A55: FACTURA | B55: FX26-002231 | C55: Proveedor Ficticio X 035, S.L. | E55: NO INFORMADO | F55: XPR26-01105 | Proyecto demostracion 01105 | G55: VALIDO | H55: 5256.51
A56: PEDIDO | B56: O2690001 | C56: Proveedor Ficticio X 042, S.L. | D56: #etiqueta_demo_sin_ceco | E56: NO INFORMADO | G56: NO INFORMADO | H56: 27362.42
A57: PEDIDO | B57: O2690020 | C57: Proveedor Ficticio X 139, S.L. | D57: #etiqueta_demo_sin_ceco | E57: NO INFORMADO | F57: XPR26-01281 | Proyecto demostracion 01281 | G57: VALIDO | H57: 11211.04
A58: PEDIDO | B58: O2690039 | C58: Proveedor Ficticio X 075, S.L. | D58: #etiqueta_demo_sin_ceco | E58: NO INFORMADO | F58: XPR26-00930 | Proyecto demostracion 00930 | G58: VALIDO | H58: 3408.37
A59: PEDIDO | B59: O2690058 | C59: Proveedor Ficticio X 140, S.L. | D59: #etiqueta_demo_sin_ceco | E59: NO INFORMADO | F59: XPR26-02936 | Proyecto demostracion 02936 | G59: VALIDO | H59: 11265.73
A60: PEDIDO | B60: O2690077 | C60: Proveedor Ficticio X 015, S.L. | D60: #etiqueta_demo_sin_ceco | E60: NO INFORMADO | F60: XPR26-00923 | Proyecto demostracion 00923 | G60: VALIDO | H60: 22852.58
A61: PEDIDO | B61: O2690096 | C61: Proveedor Ficticio X 106, S.L. | D61: #etiqueta_demo_sin_ceco | E61: NO INFORMADO | F61: XPR26-01668 | Proyecto demostracion 01668 | G61: VALIDO | H61: 15937.27
A62: PEDIDO | B62: O2690115 | C62: Proveedor Ficticio X 001, S.L. | D62: #etiqueta_demo_sin_ceco | E62: NO INFORMADO | F62: XPR26-03438 | Proyecto demostracion 03438 | G62: VALIDO | H62: 16288.26
A63: PEDIDO | B63: O2690134 | C63: Proveedor Ficticio X 126, S.L. | D63: #etiqueta_demo_sin_ceco | E63: NO INFORMADO | G63: NO INFORMADO | H63: 22637.81
A64: PEDIDO | B64: O2690153 | C64: Proveedor Ficticio X 112, S.L. | D64: #etiqueta_demo_sin_ceco | E64: NO INFORMADO | F64: XPR26-01893 | Proyecto demostracion 01893 | G64: VALIDO | H64: 11370.53
A65: PEDIDO | B65: O2690172 | C65: Proveedor Ficticio X 055, S.L. | D65: #etiqueta_demo_sin_ceco | E65: NO INFORMADO | G65: NO INFORMADO | H65: 25665.04
A66: PEDIDO | B66: O2690191 | C66: Proveedor Ficticio X 145, S.L. | D66: #etiqueta_demo_sin_ceco | E66: NO INFORMADO | G66: NO INFORMADO | H66: 24235.51
A67: PEDIDO | B67: O2690210 | C67: Proveedor Ficticio X 112, S.L. | D67: #etiqueta_demo_sin_ceco | E67: NO INFORMADO | F67: XPR26-03371 | Proyecto demostracion 03371 | G67: VALIDO | H67: 19112.95
A68: PEDIDO | B68: O2690229 | C68: Proveedor Ficticio X 051, S.L. | D68: #etiqueta_demo_sin_ceco | E68: NO INFORMADO | F68: XPR26-00173 | Proyecto demostracion 00173 | G68: VALIDO | H68: 20615.64
A69: PEDIDO | B69: O2690248 | C69: Proveedor Ficticio X 102, S.L. | D69: #etiqueta_demo_sin_ceco | E69: NO INFORMADO | F69: XPR26-01869 | Proyecto demostracion 01869 | G69: VALIDO | H69: 23674.98
A70: PEDIDO | B70: O2690267 | C70: Proveedor Ficticio X 053, S.L. | D70: #etiqueta_demo_sin_ceco | E70: NO INFORMADO | F70: XPR26-00795 | Proyecto demostracion 00795 | G70: VALIDO | H70: 5947.68
A71: PEDIDO | B71: O2690286 | C71: Proveedor Ficticio X 029, S.L. | D71: #etiqueta_demo_sin_ceco | E71: NO INFORMADO | F71: XPR26-00722 | Proyecto demostracion 00722 | G71: VALIDO | H71: 16636.46
A72: PEDIDO | B72: O2690305 | C72: Proveedor Ficticio X 077, S.L. | D72: #etiqueta_demo_sin_ceco | E72: NO INFORMADO | F72: XPR26-00606 | Proyecto demostracion 00606 | G72: VALIDO | H72: 75925.91
A73: PEDIDO | B73: O2690324 | C73: Proveedor Ficticio X 118, S.L. | D73: #etiqueta_demo_sin_ceco | E73: NO INFORMADO | F73: XPR26-02376 | Proyecto demostracion 02376 | G73: VALIDO | H73: 5477.05
A74: PEDIDO | B74: O2690343 | C74: Proveedor Ficticio X 097, S.L. | D74: #etiqueta_demo_sin_ceco | E74: NO INFORMADO | F74: XPR26-00134 | Proyecto demostracion 00134 | G74: VALIDO | H74: 16049.23
A75: PEDIDO | B75: O2690362 | C75: Proveedor Ficticio X 180, S.L. | D75: #etiqueta_demo_sin_ceco | E75: NO INFORMADO | F75: XPR26-02748 | Proyecto demostracion 02748 | G75: VALIDO | H75: 67903.01
A76: PEDIDO | B76: O2690381 | C76: Proveedor Ficticio X 118, S.L. | D76: #etiqueta_demo_sin_ceco | E76: NO INFORMADO | F76: XPR26-00782 | Proyecto demostracion 00782 | G76: VALIDO | H76: 10806.43
A77: PEDIDO | B77: O2690400 | C77: Proveedor Ficticio X 050, S.L. | D77: #etiqueta_demo_sin_ceco | E77: NO INFORMADO | F77: XPR26-00904 | Proyecto demostracion 00904 | G77: VALIDO | H77: 4199.99
A78: PEDIDO | B78: O2690419 | C78: Proveedor Ficticio X 063, S.L. | D78: #etiqueta_demo_sin_ceco | E78: NO INFORMADO | F78: XPR26-03190 | Proyecto demostracion 03190 | G78: VALIDO | H78: 21800.63

Sheet 11_Resumen_Mensual
A1: CUADRO DE CONTROL / EVOLUCIÓN 2026
A3: Los importes mensuales se asignan a su respectiva fecha de documento; no equivalen a caja ni a devengo.
A5: Mes | B5: Nº POs | C5: Total POs € | D5: Nº facturas | E5: Total facturas € | F5: Excepciones | G5: Prioridad alta
A6: Enero | B6: 51 | C6: 1314510.6 | D6: 231 | E6: 2273528.6 | F6: 24 | G6: 5
A7: Febrero | B7: 40 | C7: 823499.87 | D7: 202 | E7: 1752056.9 | F7: 26 | G7: 6
A8: Marzo | B8: 59 | C8: 1379280.9 | D8: 240 | E8: 2643238.7 | F8: 27 | G8: 6
A9: Abril | B9: 54 | C9: 1059362.6 | D9: 229 | E9: 2922022.4 | F9: 27 | G9: 11
A10: Mayo | B10: 45 | C10: 999177.37 | D10: 242 | E10: 2489288.2 | F10: 31 | G10: 11
A11: Junio | B11: 48 | C11: 846219.76 | D11: 245 | E11: 2764317.7 | F11: 24 | G11: 7
A12: Julio | B12: 43 | C12: 910525.36 | D12: 227 | E12: 2487481.6 | F12: 25 | G12: 9
A13: Agosto | B13: 32 | C13: 727887.21 | D13: 241 | E13: 2482764.6 | F13: 27 | G13: 13
A14: Septiembre | B14: 46 | C14: 647742.76 | D14: 232 | E14: 2401358.6 | F14: 28 | G14: 8
A15: Octubre | B15: 9 | C15: 114460.27 | D15: 150 | E15: 1713436.4 | F15: 9 | G15: 5
A16: Noviembre | B16: 0 | C16: 0 | D16: 0 | E16: 0 | F16: 0 | G16: 0
A17: Diciembre | B17: 0 | C17: 0 | D17: 0 | E17: 0 | F17: 0 | G17: 0

Sheet 12_Metodologia
A1: METODOLOGÍA, ALCANCE Y LIMITACIONES
A3: Guía de lectura: alcance del procedimiento, control de calidad y limitaciones probatorias.
A5: Paso | B5: Área | C5: Explicación / criterio
A6: 01 | B6: OBJETIVO | C6: Evaluar riesgos del ciclo de compras con análisis automatizado de POs, facturas, CECOs y proyectos.
A7: 02 | B7: FUENTES | C7: X_DEMO_Pedidos_Compra.xlsx, X_DEMO_Facturas_Compras.xlsx, X_DEMO_Proyectos.xlsx, X_DEMO_CECOs.xlsx
A8: 03 | B8: UNIVERSO | C8: 427 POs, 2239 facturas, 3916 proyectos, 277 CECOs.
A9: 04 | B9: RELACIÓN | C9: Referencias O###### en descripción de factura. Una PO admite varias facturas y cada factura multirreferencia se prorratea.
A10: 05 | B10: NO MATCH | C10: Factura sin PO explícita ≠ factura improcedente. PO sin factura explícita ≠ gasto omitido.
A11: 06 | B11: IMPORTE | C11: Diferencias de POs calculadas al total bruto con IVA; abonos negativos conservados.
A12: 07 | B12: CORTE | C12: Fechas de PO, emisión y contable son pruebas preliminares. Se requiere evidencia de entrega/devengo.
A13: 08 | B13: PAGOS | C13: Pagado/Pendiente procede del export de compras; no hay confirmación externa de banco.
A14: 09 | B14: CECO | C14: Solo cotejo por tokens completos etiqueta _X### contra catálogo; no por subcadenas ambiguas.
A15: 10 | B15: PROYECTO | C15: Cotejo por código XPR26-##### con maestro proyectos; ausencia no implica necesariamente error.
A16: 11 | B16: DUPLICIDAD | C16: Búsqueda exacta o indicio (proveedor + fecha + importe). No confirma pagos duplicados.
... A21: 16 | B21: REGENERACIÓN | C21: Al ejecutar el script se reemplaza el XLSX: exportar/guardar el estado del registro de excepciones antes.

Sheet 13_Catalogos
A1: CATÁLOGOS MAESTROS
A3: CECOs y proyectos usados exclusivamente para validación referencial.
A5: Tipo | B5: Código / valor | C5: Observación
A6: CECO | B6: PRODUCCION_X001
A7: CECO | B7: CREATIVIDAD_X002
A8: CECO | B8: OPERACIONES_X003
A9: CECO | B9: TECNOLOGIA_X004
A10: CECO | B10: MARKETING_X005
A11: CECO | B11: ADMINISTRACION_X006
A12: CECO | B12: FINANZAS_X007
A13: CECO | B13: DISENO_X008
A14: CECO | B14: CONSULTORIA_X009
A15: CECO | B15: COMERCIAL_X010
A16: CECO | B16: PRODUCCION_X011
A17: CECO | B17: CREATIVIDAD_X012
... A4198: PROYECTO | B4198: XPR26-03916
